Workbook

Sheet 📋 SEND CLIENT
C2: PRODUCT CONTROL
C5: =NOW() -> 46196.469
B6: 📦 TATA — ORDER DATA
B7: Vulcan Order (PO) | C7: Material | D7: Designation | F7: Order Date | G7: ETA to TETE | H7: Qty Ordered
B8: ='📋 ORDERS'!E4 -> 4300034814 | C8: ='📋 ORDERS'!F4 -> 15643491 | D8: ='📋 ORDERS'!G4 -> HA 3128 | E8: ='📋 ORDERS'!H4 -> BRG BUSHING ADAPTER 125.41MM HA 3128 SKF | F8: ='📋 ORDERS'!I4 -> 46057 | G8: 46181 | H8: ='📋 ORDERS'!L4 -> 4
B9: ='📋 ORDERS'!E5 -> 4300034814 | C9: ='📋 ORDERS'!F5 -> 13040369 | D9: ='📋 ORDERS'!G5 -> COP.ATL160M | E9: ='📋 ORDERS'!H5 -> LABYRINTH SEAL 160MMATL TIMKEN | F9: ='📋 ORDERS'!I5 -> 46057 | G9: 46181 | H9: ='📋 ORDERS'!L5 -> 2
B10: ='📋 ORDERS'!E6 -> 4300034814 | C10: ='📋 ORDERS'!F6 -> 15153568 | D10: ='📋 ORDERS'!G6 -> COP.01EB180MGR | E10: ='📋 ORDERS'!H6 -> BALL BRNG 01 B 180MM GR COOPER | F10: ='📋 ORDERS'!I6 -> 46057 | G10: 46181 | H10: ='📋 ORDERS'!L6 -> 2
B11: ='📋 ORDERS'!E7 -> 0 | C11: ='📋 ORDERS'!F7 -> 15002466 | D11: ='📋 ORDERS'!G7 -> 6322/C3VL0241 | E11: ='📋 ORDERS'!H7 -> DEEP GROOVE BALL BEARING - INSOCOAT 6322 | F11: ='📋 ORDERS'!I7 -> 46056 | G11: 46181 | H11: ='📋 ORDERS'!L7 -> 2
B12: ='📋 ORDERS'!E8 -> 4300033496 | C12: ='📋 ORDERS'!F8 -> 15501296 | D12: ='📋 ORDERS'!G8 -> COP.01EB125MGR | E12: ='📋 ORDERS'!H8 -> CYL ROLL BRG 01 B 125M GR COOPER | F12: ='📋 ORDERS'!I8 -> 46014 | G12: Read to Deliver | H12: ='📋 ORDERS'!L8 -> 1
B13: ='📋 ORDERS'!E9 -> 4300033496 | C13: ='📋 ORDERS'!F9 -> 13188279 | D13: ='📋 ORDERS'!G9 -> COP.01EB180MGR | E13: ='📋 ORDERS'!H9 -> CL RL BRG 01 B 180M GR COOPER BEARINGS | F13: ='📋 ORDERS'!I9 -> 46014 | G13: Read to Deliver | H13: ='📋 ORDERS'!L9 -> 3
B14: ='📋 ORDERS'!E10 -> 0 | C14: ='📋 ORDERS'!F10 -> 13188470 | D14: ='📋 ORDERS'!G10 -> COP.01EB140MGR | E14: ='📋 ORDERS'!H10 -> CL RL BRG 01 B 140M GR COOPER BEARINGS | F14: ='📋 ORDERS'!I10 -> 46161 | G14: 46268 | H14: ='📋 ORDERS'!L10 -> 1
B15: ='📋 ORDERS'!E11 -> 0 | C15: ='📋 ORDERS'!F11 -> 13040555 | D15: ='📋 ORDERS'!G11 -> COP.02EB180MGR | E15: ='📋 ORDERS'!H11 -> CL RL BRG 02 B 180M GR COOPER BEARINGS | F15: ='📋 ORDERS'!I11 -> 46161 | G15: 46268 | H15: ='📋 ORDERS'!L11 -> 5
B16: ='📋 ORDERS'!E12 -> 0 | C16: ='📋 ORDERS'!F12 -> 13040555 | D16: ='📋 ORDERS'!G12 -> COP.02EB180MGR | E16: ='📋 ORDERS'!H12 -> CL RL BRG 02 B 180M GR COOPER BEARINGS | F16: ='📋 ORDERS'!I12 -> 46161 | G16: 46268 | H16: ='📋 ORDERS'!L12 -> 2
B17: ='📋 ORDERS'!E13 -> 0 | C17: ='📋 ORDERS'!F13 -> 13188470 | D17: ='📋 ORDERS'!G13 -> COP.01EB140MGR | E17: ='📋 ORDERS'!H13 -> CL RL BRG 01 B 140M GR COOPER BEARINGS | F17: ='📋 ORDERS'!I13 -> 46161 | G17: 46268 | H17: ='📋 ORDERS'!L13 -> 1
B18: ='📋 ORDERS'!E14 -> 4300037223 | C18: ='📋 ORDERS'!F14 -> 15134397 | D18: ='📋 ORDERS'!G14 -> SRV.NU 407 | E18: ='📋 ORDERS'!H14 -> CYL ROL BEARING | F18: ='📋 ORDERS'!I14 -> 46154 | G18: 46254 | H18: ='📋 ORDERS'!L14 -> 3
B19: ='📋 ORDERS'!E15 -> 4300037815 | C19: ='📋 ORDERS'!F15 -> 13040555 | D19: ='📋 ORDERS'!G15 -> COP.02EB180MGR | E19: ='📋 ORDERS'!H15 -> CYL ROLL BRG MSM180BR TIMKEN | F19: ='📋 ORDERS'!I15 -> 46154 | G19: 46261 | H19: ='📋 ORDERS'!L15 -> 2
B20: ='📋 ORDERS'!E16 -> 4300037815 | C20: ='📋 ORDERS'!F16 -> 13040485 | D20: ='📋 ORDERS'!G16 -> COP.02EB220MGR | E20: ='📋 ORDERS'!H16 -> CYL ROLL BRG MSM220BR TIMKEN | F20: ='📋 ORDERS'!I16 -> 46154 | G20: 46261 | H20: ='📋 ORDERS'!L16 -> 1
B21: ='📋 ORDERS'!E17 -> 4300037815 | C21: ='📋 ORDERS'!F17 -> 13040555 | D21: ='📋 ORDERS'!G17 -> COP.02EB180MGR | E21: ='📋 ORDERS'!H17 -> CYL ROLL BRG MSM180BR TIMKEN | F21: ='📋 ORDERS'!I17 -> 46154 | G21: 46261 | H21: ='📋 ORDERS'!L17 -> 7
B22: ='📋 ORDERS'!E18 -> 4300037815 | C22: ='📋 ORDERS'!F18 -> 15509234 | D22: ='📋 ORDERS'!G18 -> 70X110X10 HMSA10 RG | E22: ='📋 ORDERS'!H18 -> LIP SEAL FKM 70MM 110MM | F22: ='📋 ORDERS'!I18 -> 46154 | G22: 46268 | H22: ='📋 ORDERS'!L18 -> 12
B23: ='📋 ORDERS'!E19 -> 4300034374 | C23: ='📋 ORDERS'!F19 -> 15744967 | D23: ='📋 ORDERS'!G19 -> 24152 CC/W33 | E23: ='📋 ORDERS'!H19 -> BEARING 24152 CC/W33 SKF | F23: ='📋 ORDERS'!I19 -> 46113 | G23: 46275 | H23: ='📋 ORDERS'!L19 -> 5
B24: ='📋 ORDERS'!E20 -> 4300034374 | C24: ='📋 ORDERS'!F20 -> 15744967 | D24: ='📋 ORDERS'!G20 -> 24152 CC/W33 | E24: ='📋 ORDERS'!H20 -> BEARING 24152 CC/W33 SKF | F24: ='📋 ORDERS'!I20 -> 46113 | G24: 46275 | H24: ='📋 ORDERS'!L20 -> 4
B25: ='📋 ORDERS'!E21 -> 4300034374 | C25: ='📋 ORDERS'!F21 -> 15744967 | D25: ='📋 ORDERS'!G21 -> 24152 CC/W33 | E25: ='📋 ORDERS'!H21 -> BEARING 24152 CC/W33 SKF | F25: ='📋 ORDERS'!I21 -> 46113 | G25: 46275 | H25: ='📋 ORDERS'!L21 -> 3
... B142: ='📋 ORDERS'!E138 -> 4300037783 | C142: ='📋 ORDERS'!F138 -> 15153017 | D142: ='📋 ORDERS'!G138 -> 6316/C3 | E142: ='📋 ORDERS'!H138 -> BEARING 6316-C3;FRAME 250S/M;WEG | F142: ='📋 ORDERS'!I138 -> 46154 | G142: 46240 | H142: ='📋 ORDERS'!L138 -> 2

Sheet 📋 ORDERS
B1: 📦 TATA — ORDER DATA
B2: 🔵 AZUL=preencha 🟢 VERDE=automático 🟣 ROXO=entrega cliente ➕ Copie linha para novos pedidos
B3: Order Line | C3: SKF Order | D3: TATA Order | E3: Vulcan Order (PO) | F3: Material | G3: Designation | H3: Short Text | I3: Order Date | J3: Est. SKF Delivery Date | K3: Warehouse | L3: Qty Ordered | M3: Qty Shipped | N3: % Shipped | O3: Unit Price | P3: Line Total USD | Q3: Invoice No. | R3: Status | S3: Days to Delivery | T3: Month/Year | U3: Est. Customer Delivery Month | V3: Qty Pending | W3: Customer ID | X3: SKF Collection Date | Y3: ✔ Delivered to Customer | Z3: Customer Delivery Date | AA3: Notes
B4: 0003A | C4: 26Z0000099 | D4: 252911949 | E4: 4300034814 | F4: 15643491 | G4: HA 3128 | H4: BRG BUSHING ADAPTER 125.41MM HA 3128 SKF | I4: 46057 | J4: 46127 | K4: EMWH | L4: 4 | M4: 4 | N4: =IF(L4=0,0,M4/L4) -> 1 | O4: 113.78 | P4: =L4*O4 -> 455.12 | Q4: 12568 | R4: COLLECTED | S4: =IF(Y4="✔","✔ OK",IF(OR(J4="",J4=0),"TBA",INT(J4-I4))) -> ✔ OK | T4: =IF(I4="","",TEXT(MONTH(I4),"00")&"/"&YEAR(I4)) -> 02/2026 | U4: =IF(Y4="✔","OK",IF(OR(J4="",J4=0),"",TEXT(MONTH(J4+20),"00")&"/"&TEXT(YEAR(J4+20),"0000"))) -> OK | V4: =L4-M4 -> 0 | W4: F66050 | X4: 46163 | Y4: ✔ | Z4: 46181
B5: 0005A | C5: 26Z0000099 | D5: 252911949 | E5: 4300034814 | F5: 13040369 | G5: COP.ATL160M | H5: LABYRINTH SEAL 160MMATL TIMKEN | I5: 46057 | J5: 46155 | K5: EMWH | L5: 2 | M5: 2 | N5: =IF(L5=0,0,M5/L5) -> 1 | O5: 266.66 | P5: =L5*O5 -> 533.32 | Q5: 12611 | R5: COLLECTED | S5: =IF(Y5="✔","✔ OK",IF(OR(J5="",J5=0),"TBA",INT(J5-I5))) -> ✔ OK | T5: =IF(I5="","",TEXT(MONTH(I5),"00")&"/"&YEAR(I5)) -> 02/2026 | U5: =IF(Y5="✔","OK",IF(OR(J5="",J5=0),"",TEXT(MONTH(J5+20),"00")&"/"&TEXT(YEAR(J5+20),"0000"))) -> OK | V5: =L5-M5 -> 0 | W5: F66050 | X5: 46163 | Y5: ✔ | Z5: 46181
B6: 0006A | C6: 26Z0000099 | D6: 252911949 | E6: 4300034814 | F6: 15153568 | G6: COP.01EB180MGR | H6: BALL BRNG 01 B 180MM GR COOPER | I6: 46057 | J6: 46169 | K6: EMWH | L6: 2 | M6: 2 | N6: =IF(L6=0,0,M6/L6) -> 1 | O6: 2441.75 | P6: =L6*O6 -> 4883.5 | Q6: 12660 | R6: COLLECTED | S6: =IF(Y6="✔","✔ OK",IF(OR(J6="",J6=0),"TBA",INT(J6-I6))) -> ✔ OK | T6: =IF(I6="","",TEXT(MONTH(I6),"00")&"/"&YEAR(I6)) -> 02/2026 | U6: =IF(Y6="✔","OK",IF(OR(J6="",J6=0),"",TEXT(MONTH(J6+20),"00")&"/"&TEXT(YEAR(J6+20),"0000"))) -> OK | V6: =L6-M6 -> 0 | W6: F66050 | X6: 46163 | Y6: ✔ | Z6: 46184
B7: 0001A | C7: 26Z0000097 | D7: 252911950 | F7: 15002466 | G7: 6322/C3VL0241 | H7: DEEP GROOVE BALL BEARING - INSOCOAT 6322 | I7: 46056 | J7: 46155 | K7: EMWH | L7: 2 | M7: 2 | N7: =IF(L7=0,0,M7/L7) -> 1 | O7: 915.85 | P7: =L7*O7 -> 1831.7 | Q7: 12612 | R7: COLLECTED | S7: =IF(Y7="✔","✔ OK",IF(OR(J7="",J7=0),"TBA",INT(J7-I7))) -> 99 | T7: =IF(I7="","",TEXT(MONTH(I7),"00")&"/"&YEAR(I7)) -> 02/2026 | U7: =IF(Y7="✔","OK",IF(OR(J7="",J7=0),"",TEXT(MONTH(J7+20),"00")&"/"&TEXT(YEAR(J7+20),"0000"))) -> 06/2026 | V7: =L7-M7 -> 0 | W7: F66050 | X7: 46163 | Y7: ⚠ | AA7: Delivery on the 8.06.2026
B8: 0001A | C8: 25Z0002759 | D8: 252911760 | E8: 4300033496 | F8: 15501296 | G8: COP.01EB125MGR | H8: CYL ROLL BRG 01 B 125M GR COOPER | I8: 46014 | J8: 46085 | K8: EMWH | L8: 1 | M8: 1 | N8: =IF(L8=0,0,M8/L8) -> 1 | O8: 1048.88 | P8: =L8*O8 -> 1048.88 | Q8: 12403 | R8: COLLECTED | S8: =IF(Y8="✔","✔ OK",IF(OR(J8="",J8=0),"TBA",INT(J8-I8))) -> ✔ OK | T8: =IF(I8="","",TEXT(MONTH(I8),"00")&"/"&YEAR(I8)) -> 12/2025 | U8: =IF(Y8="✔","OK",IF(OR(J8="",J8=0),"",TEXT(MONTH(J8+20),"00")&"/"&TEXT(YEAR(J8+20),"0000"))) -> OK | V8: =L8-M8 -> 0 | W8: F66050 | X8: 46128 | Y8: ✔ | Z8: 46191
B9: 0005A | C9: 25Z0002759 | D9: 252911760 | E9: 4300033496 | F9: 13188279 | G9: COP.01EB180MGR | H9: CL RL BRG 01 B 180M GR COOPER BEARINGS | I9: 46014 | J9: 46120 | K9: EMWH | L9: 3 | M9: 3 | N9: =IF(L9=0,0,M9/L9) -> 1 | O9: 2441.75 | P9: =L9*O9 -> 7325.25 | Q9: 12452 | R9: COLLECTED | S9: =IF(Y9="✔","✔ OK",IF(OR(J9="",J9=0),"TBA",INT(J9-I9))) -> ✔ OK | T9: =IF(I9="","",TEXT(MONTH(I9),"00")&"/"&YEAR(I9)) -> 12/2025 | U9: =IF(Y9="✔","OK",IF(OR(J9="",J9=0),"",TEXT(MONTH(J9+20),"00")&"/"&TEXT(YEAR(J9+20),"0000"))) -> OK | V9: =L9-M9 -> 0 | W9: F66050 | X9: 46128 | Y9: ✔ | Z9: 46191
B10: 0001A | C10: 26Z0000402 | D10: 262910345 | F10: 13188470 | G10: COP.01EB140MGR | H10: CL RL BRG 01 B 140M GR COOPER BEARINGS | I10: 46161 | J10: 46246 | K10: EMWH | L10: 1 | M10: 1 | N10: =IF(L10=0,0,M10/L10) -> 1 | O10: 1437.72 | P10: =L10*O10 -> 1437.72 | Q10: 0000000 | R10: SHS | S10: =IF(Y10="✔","✔ OK",IF(OR(J10="",J10=0),"TBA",INT(J10-I10))) -> 85 | T10: =IF(I10="","",TEXT(MONTH(I10),"00")&"/"&YEAR(I10)) -> 05/2026 | U10: =IF(Y10="✔","OK",IF(OR(J10="",J10=0),"",TEXT(MONTH(J10+20),"00")&"/"&TEXT(YEAR(J10+20),"0000"))) -> 09/2026 | V10: =L10-M10 -> 0 | W10: F66050 | Y10: ✘ | AA10: Expected delivery at SKF July 7
B11: 0005A | C11: 26Z0000402 | D11: 262910345 | F11: 13040555 | G11: COP.02EB180MGR | H11: CL RL BRG 02 B 180M GR COOPER BEARINGS | I11: 46161 | J11: 46253 | K11: EMWH | L11: 5 | M11: 5 | N11: =IF(L11=0,0,M11/L11) -> 1 | O11: 4238.23 | P11: =L11*O11 -> 21191.15 | Q11: 0000000 | R11: RPI | S11: =IF(Y11="✔","✔ OK",IF(OR(J11="",J11=0),"TBA",INT(J11-I11))) -> 92 | T11: =IF(I11="","",TEXT(MONTH(I11),"00")&"/"&YEAR(I11)) -> 05/2026 | U11: =IF(Y11="✔","OK",IF(OR(J11="",J11=0),"",TEXT(MONTH(J11+20),"00")&"/"&TEXT(YEAR(J11+20),"0000"))) -> 09/2026 | V11: =L11-M11 -> 0 | W11: F66050 | Y11: ✘ | AA11: Expected delivery at SKF July 7
B12: 0006A | C12: 26Z0000402 | D12: 262910345 | F12: 13040555 | G12: COP.02EB180MGR | H12: CL RL BRG 02 B 180M GR COOPER BEARINGS | I12: 46161 | J12: 46253 | K12: EMWH | L12: 2 | M12: 2 | N12: =IF(L12=0,0,M12/L12) -> 1 | O12: 4238.23 | P12: =L12*O12 -> 8476.46 | Q12: 0000000 | R12: RPI | S12: =IF(Y12="✔","✔ OK",IF(OR(J12="",J12=0),"TBA",INT(J12-I12))) -> 92 | T12: =IF(I12="","",TEXT(MONTH(I12),"00")&"/"&YEAR(I12)) -> 05/2026 | U12: =IF(Y12="✔","OK",IF(OR(J12="",J12=0),"",TEXT(MONTH(J12+20),"00")&"/"&TEXT(YEAR(J12+20),"0000"))) -> 09/2026 | V12: =L12-M12 -> 0 | W12: F66050 | Y12: ✘ | AA12: Expected delivery at SKF July 7
B13: 0009A | C13: 26Z0000402 | D13: 262910345 | F13: 13188470 | G13: COP.01EB140MGR | H13: CL RL BRG 01 B 140M GR COOPER BEARINGS | I13: 46161 | J13: 46225 | K13: EMWH | L13: 1 | M13: 1 | N13: =IF(L13=0,0,M13/L13) -> 1 | O13: 1437.72 | P13: =L13*O13 -> 1437.72 | Q13: 0000000 | R13: SHS | S13: =IF(Y13="✔","✔ OK",IF(OR(J13="",J13=0),"TBA",INT(J13-I13))) -> 64 | T13: =IF(I13="","",TEXT(MONTH(I13),"00")&"/"&YEAR(I13)) -> 05/2026 | U13: =IF(Y13="✔","OK",IF(OR(J13="",J13=0),"",TEXT(MONTH(J13+20),"00")&"/"&TEXT(YEAR(J13+20),"0000"))) -> 08/2026 | V13: =L13-M13 -> 0 | W13: F66050 | Y13: ✘ | AA13: Expected delivery at SKF July 7
B14: 0002B | C14: 26Z0000382 | D14: 262910320 | E14: 4300037223 | F14: 15134397 | G14: SRV.NU 407 | H14: CYL ROL BEARING | I14: 46154 | J14: 46239 | K14: EMWH | L14: 3 | M14: 0 | N14: =IF(L14=0,0,M14/L14) -> 0 | O14: 71.7 | P14: =L14*O14 -> 215.1 | Q14: 0000000 | R14: SHS | S14: =IF(Y14="✔","✔ OK",IF(OR(J14="",J14=0),"TBA",INT(J14-I14))) -> 85 | T14: =IF(I14="","",TEXT(MONTH(I14),"00")&"/"&YEAR(I14)) -> 05/2026 | U14: =IF(Y14="✔","OK",IF(OR(J14="",J14=0),"",TEXT(MONTH(J14+20),"00")&"/"&TEXT(YEAR(J14+20),"0000"))) -> 08/2026 | V14: =L14-M14 -> 3 | W14: F66050 | Y14: ✘ | AA14: Requested from EDC dispatch date
B15: 0004A | C15: 26Z0000383 | D15: 262910319 | E15: 4300037815 | F15: 13040555 | G15: COP.02EB180MGR | H15: CYL ROLL BRG MSM180BR TIMKEN | I15: 46154 | J15: 46246 | K15: EMWH | L15: 2 | M15: 2 | N15: =IF(L15=0,0,M15/L15) -> 1 | O15: 4395.2 | P15: =L15*O15 -> 8790.4 | Q15: 0000000 | R15: SHS | S15: =IF(Y15="✔","✔ OK",IF(OR(J15="",J15=0),"TBA",INT(J15-I15))) -> 92 | T15: =IF(I15="","",TEXT(MONTH(I15),"00")&"/"&YEAR(I15)) -> 05/2026 | U15: =IF(Y15="✔","OK",IF(OR(J15="",J15=0),"",TEXT(MONTH(J15+20),"00")&"/"&TEXT(YEAR(J15+20),"0000"))) -> 09/2026 | V15: =L15-M15 -> 0 | W15: F66050 | Y15: ✘ | AA15: Requested for improved production
B16: 0005A | C16: 26Z0000383 | D16: 262910319 | E16: 4300037815 | F16: 13040485 | G16: COP.02EB220MGR | H16: CYL ROLL BRG MSM220BR TIMKEN | I16: 46154 | J16: 46246 | K16: EMWH | L16: 1 | M16: 1 | N16: =IF(L16=0,0,M16/L16) -> 1 | O16: 10786.44 | P16: =L16*O16 -> 10786.44 | Q16: 0000000 | R16: SHS | S16: =IF(Y16="✔","✔ OK",IF(OR(J16="",J16=0),"TBA",INT(J16-I16))) -> 92 | T16: =IF(I16="","",TEXT(MONTH(I16),"00")&"/"&YEAR(I16)) -> 05/2026 | U16: =IF(Y16="✔","OK",IF(OR(J16="",J16=0),"",TEXT(MONTH(J16+20),"00")&"/"&TEXT(YEAR(J16+20),"0000"))) -> 09/2026 | V16: =L16-M16 -> 0 | W16: F66050 | Y16: ✘ | AA16: Requested for improved production
B17: 0006A | C17: 26Z0000383 | D17: 262910319 | E17: 4300037815 | F17: 13040555 | G17: COP.02EB180MGR | H17: CYL ROLL BRG MSM180BR TIMKEN | I17: 46154 | J17: 46246 | K17: EMWH | L17: 7 | M17: 7 | N17: =IF(L17=0,0,M17/L17) -> 1 | O17: 4395.2 | P17: =L17*O17 -> 30766.4 | Q17: 0000000 | R17: SHS | S17: =IF(Y17="✔","✔ OK",IF(OR(J17="",J17=0),"TBA",INT(J17-I17))) -> 92 | T17: =IF(I17="","",TEXT(MONTH(I17),"00")&"/"&YEAR(I17)) -> 05/2026 | U17: =IF(Y17="✔","OK",IF(OR(J17="",J17=0),"",TEXT(MONTH(J17+20),"00")&"/"&TEXT(YEAR(J17+20),"0000"))) -> 09/2026 | V17: =L17-M17 -> 0 | W17: F66050 | Y17: ✘ | AA17: Requested for improved production
B18: 0007A | C18: 26Z0000383 | D18: 262910319 | E18: 4300037815 | F18: 15509234 | G18: 70X110X10 HMSA10 RG | H18: LIP SEAL FKM 70MM 110MM | I18: 46154 | J18: 46239 | K18: EMWH | L18: 12 | M18: 12 | N18: =IF(L18=0,0,M18/L18) -> 1 | O18: 2.71 | P18: =L18*O18 -> 32.52 | Q18: 0000000 | R18: SHS | S18: =IF(Y18="✔","✔ OK",IF(OR(J18="",J18=0),"TBA",INT(J18-I18))) -> 85 | T18: =IF(I18="","",TEXT(MONTH(I18),"00")&"/"&YEAR(I18)) -> 05/2026 | U18: =IF(Y18="✔","OK",IF(OR(J18="",J18=0),"",TEXT(MONTH(J18+20),"00")&"/"&TEXT(YEAR(J18+20),"0000"))) -> 08/2026 | V18: =L18-M18 -> 0 | W18: F66050 | Y18: ✘ | AA18: 25.06.2026 ETA - SANR0409719
B19: 0002A | C19: 26Z0000279 | D19: 252912134 | E19: 4300034374 | F19: 15744967 | G19: 24152 CC/W33 | H19: BEARING 24152 CC/W33 SKF | I19: 46113 | J19: 46225 | K19: EMWH | L19: 5 | M19: 0 | N19: =IF(L19=0,0,M19/L19) -> 0 | O19: 2589.33 | P19: =L19*O19 -> 12946.65 | Q19: 0000000 | R19: RPI | S19: =IF(Y19="✔","✔ OK",IF(OR(J19="",J19=0),"TBA",INT(J19-I19))) -> 112 | T19: =IF(I19="","",TEXT(MONTH(I19),"00")&"/"&YEAR(I19)) -> 04/2026 | U19: =IF(Y19="✔","OK",IF(OR(J19="",J19=0),"",TEXT(MONTH(J19+20),"00")&"/"&TEXT(YEAR(J19+20),"0000"))) -> 08/2026 | V19: =L19-M19 -> 5 | W19: F66050 | X19: 46176 | Y19: 🔮 | AA19: Request to order directly from factory - Cephas to change order
B20: 0002B | C20: 26Z0000279 | D20: 252912134 | E20: 4300034374 | F20: 15744967 | G20: 24152 CC/W33 | H20: BEARING 24152 CC/W33 SKF | I20: 46113 | J20: 46225 | K20: EMWH | L20: 4 | M20: 0 | N20: =IF(L20=0,0,M20/L20) -> 0 | O20: 2589.33 | P20: =L20*O20 -> 10357.32 | Q20: 0000000 | R20: RPI | S20: =IF(Y20="✔","✔ OK",IF(OR(J20="",J20=0),"TBA",INT(J20-I20))) -> 112 | T20: =IF(I20="","",TEXT(MONTH(I20),"00")&"/"&YEAR(I20)) -> 04/2026 | U20: =IF(Y20="✔","OK",IF(OR(J20="",J20=0),"",TEXT(MONTH(J20+20),"00")&"/"&TEXT(YEAR(J20+20),"0000"))) -> 08/2026 | V20: =L20-M20 -> 4 | W20: F66050 | X20: 46176 | Y20: 🔮 | AA20: Request to order directly from factory - Cephas to change order
B21: 0002C | C21: 26Z0000279 | D21: 252912134 | E21: 4300034374 | F21: 15744967 | G21: 24152 CC/W33 | H21: BEARING 24152 CC/W33 SKF | I21: 46113 | J21: 46225 | K21: EMWH | L21: 3 | M21: 0 | N21: =IF(L21=0,0,M21/L21) -> 0 | O21: 2589.33 | P21: =L21*O21 -> 7767.99 | Q21: 0000000 | R21: RPI | S21: =IF(Y21="✔","✔ OK",IF(OR(J21="",J21=0),"TBA",INT(J21-I21))) -> 112 | T21: =IF(I21="","",TEXT(MONTH(I21),"00")&"/"&YEAR(I21)) -> 04/2026 | U21: =IF(Y21="✔","OK",IF(OR(J21="",J21=0),"",TEXT(MONTH(J21+20),"00")&"/"&TEXT(YEAR(J21+20),"0000"))) -> 08/2026 | V21: =L21-M21 -> 3 | W21: F66050 | X21: 46176 | Y21: 🔮 | AA21: Request to order directly from factory - Cephas to change order
B22: 0007A | C22: 26Z0000279 | D22: 252912134 | E22: 4300034374 | F22: 15744967 | G22: 24152 CC/W33 | H22: BEARING 24152 CC/W33 SKF | I22: 46113 | J22: 46225 | K22: EMWH | L22: 2 | M22: 0 | N22: =IF(L22=0,0,M22/L22) -> 0 | O22: 2589.33 | P22: =L22*O22 -> 5178.66 | Q22: 0000000 | R22: RPI | S22: =IF(Y22="✔","✔ OK",IF(OR(J22="",J22=0),"TBA",INT(J22-I22))) -> 112 | T22: =IF(I22="","",TEXT(MONTH(I22),"00")&"/"&YEAR(I22)) -> 04/2026 | U22: =IF(Y22="✔","OK",IF(OR(J22="",J22=0),"",TEXT(MONTH(J22+20),"00")&"/"&TEXT(YEAR(J22+20),"0000"))) -> 08/2026 | V22: =L22-M22 -> 2 | W22: F66050 | X22: 46176 | Y22: 🔮 | AA22: Request to order directly from factory - Cephas to change order
B23: 0002C | C23: 26Z0000280 | D23: 262910001 | E23: 4300036757 | F23: 15475312 | G23: CMPT 2310TX20 | H23: SENSOR INTEGRATED CABLE; CMPT 2310TX20 | I23: 46113 | J23: 46205 | K23: EMWH | L23: 7 | M23: 7 | N23: =IF(L23=0,0,M23/L23) -> 1 | O23: 495 | P23: =L23*O23 -> 3465 | Q23: 0000000 | R23: SHS | S23: =IF(Y23="✔","✔ OK",IF(OR(J23="",J23=0),"TBA",INT(J23-I23))) -> 92 | T23: =IF(I23="","",TEXT(MONTH(I23),"00")&"/"&YEAR(I23)) -> 04/2026 | U23: =IF(Y23="✔","OK",IF(OR(J23="",J23=0),"",TEXT(MONTH(J23+20),"00")&"/"&TEXT(YEAR(J23+20),"0000"))) -> 07/2026 | V23: =L23-M23 -> 0 | W23: F66050 | Y23: 🔮 | AA23: Requested for production improvement , no global availability
B24: 0003A | C24: 26Z0000280 | D24: 262910001 | E24: 4300036757 | F24: 15475312 | G24: CMPT 2310TX20 | H24: SENSOR INTEGRATED CABLE; CMPT 2310TX20 | I24: 46113 | J24: 46205 | K24: EMWH | L24: 13 | M24: 13 | N24: =IF(L24=0,0,M24/L24) -> 1 | O24: 495 | P24: =L24*O24 -> 6435 | Q24: 0000000 | R24: SHS | S24: =IF(Y24="✔","✔ OK",IF(OR(J24="",J24=0),"TBA",INT(J24-I24))) -> 92 | T24: =IF(I24="","",TEXT(MONTH(I24),"00")&"/"&YEAR(I24)) -> 04/2026 | U24: =IF(Y24="✔","OK",IF(OR(J24="",J24=0),"",TEXT(MONTH(J24+20),"00")&"/"&TEXT(YEAR(J24+20),"0000"))) -> 07/2026 | V24: =L24-M24 -> 0 | W24: F66050 | Y24: 🔮 | AA24: Requested for production improvement , no global availability
B25: 0002B | C25: 26Z0000240 | D25: 252912296 | E25: 4300036353 | F25: 13117942 | G25: PHF TB4545X65MM | H25: LCKG BUSH 65MM | I25: 46100 | J25: 46344 | K25: EMWH | L25: 4 | M25: 4 | N25: =IF(L25=0,0,M25/L25) -> 1 | O25: 60.21 | P25: =L25*O25 -> 240.84 | Q25: 0000000 | R25: RBK | S25: =IF(Y25="✔","✔ OK",IF(OR(J25="",J25=0),"TBA",INT(J25-I25))) -> 244 | T25: =IF(I25="","",TEXT(MONTH(I25),"00")&"/"&YEAR(I25)) -> 03/2026 | U25: =IF(Y25="✔","OK",IF(OR(J25="",J25=0),"",TEXT(MONTH(J25+20),"00")&"/"&TEXT(YEAR(J25+20),"0000"))) -> 12/2026 | V25: =L25-M25 -> 0 | W25: F66050 | Y25: ✘ | AA25: Awaiting improvement from Factory
B26: 0001A | C26: 26Z0000428 | D26: 262910449 | E26: 4300038759 | F26: 15647107 | G26: ASNH 526 | H26: SIDE COVER ASNH 526 SKF | I26: 46169 | J26: 46175 | K26: QZSS | L26: 2 | M26: 2 | N26: =IF(L26=0,0,M26/L26) -> 1 | O26: 5.54 | P26: =L26*O26 -> 11.08 | Q26: 12765 | R26: READY FOR COLLECTION | S26: =IF(Y26="✔","✔ OK",IF(OR(J26="",J26=0),"TBA",INT(J26-I26))) -> 6 | T26: =IF(I26="","",TEXT(MONTH(I26),"00")&"/"&YEAR(I26)) -> 05/2026 | U26: =IF(Y26="✔","OK",IF(OR(J26="",J26=0),"",TEXT(MONTH(J26+20),"00")&"/"&TEXT(YEAR(J26+20),"0000"))) -> 06/2026 | V26: =L26-M26 -> 0 | W26: F66050 | Y26: 🔮 | AA26: 2026-06-09 - SKF informed that it is available for collection.
B27: 0002A | C27: 26Z0000428 | D27: 262910449 | E27: 4300038759 | F27: 15647107 | G27: ASNH 526 | H27: SIDE COVER ASNH 526 SKF | I27: 46169 | J27: 46175 | K27: QZSS | L27: 2 | M27: 2 | N27: =IF(L27=0,0,M27/L27) -> 1 | O27: 5.54 | P27: =L27*O27 -> 11.08 | Q27: 12765 | R27: READY FOR COLLECTION | S27: =IF(Y27="✔","✔ OK",IF(OR(J27="",J27=0),"TBA",INT(J27-I27))) -> 6 | T27: =IF(I27="","",TEXT(MONTH(I27),"00")&"/"&YEAR(I27)) -> 05/2026 | U27: =IF(Y27="✔","OK",IF(OR(J27="",J27=0),"",TEXT(MONTH(J27+20),"00")&"/"&TEXT(YEAR(J27+20),"0000"))) -> 06/2026 | V27: =L27-M27 -> 0 | W27: F66050 | Y27: 🔮 | AA27: 2026-06-09 - SKF informed that it is available for collection.
B28: 0006A | C28: 26Z0000428 | D28: 262910449 | E28: 4300038759 | F28: 15056552 | G28: OH 3152 H | H28: ADAPTER SLEEVE;OH 3152 H;SKF | I28: 46169 | J28: 46175 | K28: QZSS | L28: 1 | M28: 1 | N28: =IF(L28=0,0,M28/L28) -> 1 | O28: 601.87 | P28: =L28*O28 -> 601.87 | Q28: 12765 | R28: READY FOR COLLECTION | S28: =IF(Y28="✔","✔ OK",IF(OR(J28="",J28=0),"TBA",INT(J28-I28))) -> 6 | T28: =IF(I28="","",TEXT(MONTH(I28),"00")&"/"&YEAR(I28)) -> 05/2026 | U28: =IF(Y28="✔","OK",IF(OR(J28="",J28=0),"",TEXT(MONTH(J28+20),"00")&"/"&TEXT(YEAR(J28+20),"0000"))) -> 06/2026 | V28: =L28-M28 -> 0 | W28: F66050 | Y28: 🔮 | AA28: 2026-06-09 - SKF informed that it is available for collection.
B29: 0008A | C29: 26Z0000428 | D29: 262910449 | E29: 4300038759 | F29: 15388676 | G29: 22316 E/C3 | H29: BEARING 22316 E C3 SKF | I29: 46169 | J29: 46175 | K29: QZSS | L29: 1 | M29: 1 | N29: =IF(L29=0,0,M29/L29) -> 1 | O29: 146.04 | P29: =L29*O29 -> 146.04 | Q29: 12765 | R29: READY FOR COLLECTION | S29: =IF(Y29="✔","✔ OK",IF(OR(J29="",J29=0),"TBA",INT(J29-I29))) -> 6 | T29: =IF(I29="","",TEXT(MONTH(I29),"00")&"/"&YEAR(I29)) -> 05/2026 | U29: =IF(Y29="✔","OK",IF(OR(J29="",J29=0),"",TEXT(MONTH(J29+20),"00")&"/"&TEXT(YEAR(J29+20),"0000"))) -> 06/2026 | V29: =L29-M29 -> 0 | W29: F66050 | Y29: 🔮 | AA29: 2026-06-09 - SKF informed that it is available for collection.
B30: 0009A | C30: 26Z0000428 | D30: 262910449 | E30: 4300038759 | F30: 15062473 | G30: H 318 | H30: ADAPTER SLEEVE H 318 SKF | I30: 46169 | J30: 46175 | K30: QZSS | L30: 3 | M30: 3 | N30: =IF(L30=0,0,M30/L30) -> 1 | O30: 31.31 | P30: =L30*O30 -> 93.93 | Q30: 12765 | R30: READY FOR COLLECTION | S30: =IF(Y30="✔","✔ OK",IF(OR(J30="",J30=0),"TBA",INT(J30-I30))) -> 6 | T30: =IF(I30="","",TEXT(MONTH(I30),"00")&"/"&YEAR(I30)) -> 05/2026 | U30: =IF(Y30="✔","OK",IF(OR(J30="",J30=0),"",TEXT(MONTH(J30+20),"00")&"/"&TEXT(YEAR(J30+20),"0000"))) -> 06/2026 | V30: =L30-M30 -> 0 | W30: F66050 | Y30: 🔮 | AA30: 2026-06-09 - SKF informed that it is available for collection.
B31: 0010A | C31: 26Z0000428 | D31: 262910449 | E31: 4300038759 | F31: 15647107 | G31: ASNH 526 | H31: SIDE COVER ASNH 526 SKF | I31: 46169 | J31: 46175 | K31: QZSS | L31: 1 | M31: 1 | N31: =IF(L31=0,0,M31/L31) -> 1 | O31: 5.54 | P31: =L31*O31 -> 5.54 | Q31: 12765 | R31: READY FOR COLLECTION | S31: =IF(Y31="✔","✔ OK",IF(OR(J31="",J31=0),"TBA",INT(J31-I31))) -> 6 | T31: =IF(I31="","",TEXT(MONTH(I31),"00")&"/"&YEAR(I31)) -> 05/2026 | U31: =IF(Y31="✔","OK",IF(OR(J31="",J31=0),"",TEXT(MONTH(J31+20),"00")&"/"&TEXT(YEAR(J31+20),"0000"))) -> 06/2026 | V31: =L31-M31 -> 0 | W31: F66050 | Y31: 🔮 | AA31: 2026-06-09 - SKF informed that it is available for collection.
B32: 0011A | C32: 26Z0000126 | D32: 252911981 | E32: 4300035325 | F32: 15149626 | G32: TU 50 TF | H32: BEARING UNIT NON-LOC PASS SPLIT PED | I32: 46066 | J32: 46134 | K32: EMWH | L32: 30 | M32: 30 | N32: =IF(L32=0,0,M32/L32) -> 1 | O32: 39.33 | P32: =L32*O32 -> 1179.9 | Q32: 12545 | R32: COLLECTED | S32: =IF(Y32="✔","✔ OK",IF(OR(J32="",J32=0),"TBA",INT(J32-I32))) -> 68 | T32: =IF(I32="","",TEXT(MONTH(I32),"00")&"/"&YEAR(I32)) -> 02/2026 | U32: =IF(Y32="✔","OK",IF(OR(J32="",J32=0),"",TEXT(MONTH(J32+20),"00")&"/"&TEXT(YEAR(J32+20),"0000"))) -> 05/2026 | V32: =L32-M32 -> 0 | W32: F66050 | X32: 46132 | Y32: ⚠ | AA32: Gate Pass Issue (Still it is in TATA Stock)
B33: 0013A | C33: 26Z0000126 | D33: 252911981 | E33: 4300035325 | F33: 15055683 | G33: 22240 CC/W33 | H33: BEARING 22240 CC/W33 SKF | I33: 46066 | J33: 46148 | K33: EMWH | L33: 1 | M33: 1 | N33: =IF(L33=0,0,M33/L33) -> 1 | O33: 1044.34 | P33: =L33*O33 -> 1044.34 | Q33: 12632 | R33: COLLECTED | S33: =IF(Y33="✔","✔ OK",IF(OR(J33="",J33=0),"TBA",INT(J33-I33))) -> 82 | T33: =IF(I33="","",TEXT(MONTH(I33),"00")&"/"&YEAR(I33)) -> 02/2026 | U33: =IF(Y33="✔","OK",IF(OR(J33="",J33=0),"",TEXT(MONTH(J33+20),"00")&"/"&TEXT(YEAR(J33+20),"0000"))) -> 05/2026 | V33: =L33-M33 -> 0 | W33: F66050 | X33: 46163 | Y33: ⚠ | AA33: Delivery on the 8.06.2026
B34: 0014A | C34: 26Z0000126 | D34: 252911981 | E34: 4300035325 | F34: 15375665 | G34: SNL 518-615 | H34: PILLOW BLOCK NOD CI 80MM SNL 518-615 SKF | I34: 46066 | J34: 46197 | K34: EMWH | L34: 5 | M34: 5 | N34: =IF(L34=0,0,M34/L34) -> 1 | O34: 110.25 | P34: =L34*O34 -> 551.25 | Q34: 12723 | R34: READY FOR COLLECTION | S34: =IF(Y34="✔","✔ OK",IF(OR(J34="",J34=0),"TBA",INT(J34-I34))) -> 131 | T34: =IF(I34="","",TEXT(MONTH(I34),"00")&"/"&YEAR(I34)) -> 02/2026 | U34: =IF(Y34="✔","OK",IF(OR(J34="",J34=0),"",TEXT(MONTH(J34+20),"00")&"/"&TEXT(YEAR(J34+20),"0000"))) -> 07/2026 | V34: =L34-M34 -> 0 | W34: F66050 | X34: 46175 | Y34: 🔮
B35: 0015A | C35: 26Z0000126 | D35: 252911981 | E35: 4300035325 | F35: 15351089 | G35: 22218 EK | H35: SPHERICAL ROLLER BEARING 22218 EK | I35: 46066 | J35: 46197 | K35: EMWH | L35: 5 | M35: 5 | N35: =IF(L35=0,0,M35/L35) -> 1 | O35: 108.14 | P35: =L35*O35 -> 540.7 | Q35: 12723 | R35: READY FOR COLLECTION | S35: =IF(Y35="✔","✔ OK",IF(OR(J35="",J35=0),"TBA",INT(J35-I35))) -> 131 | T35: =IF(I35="","",TEXT(MONTH(I35),"00")&"/"&YEAR(I35)) -> 02/2026 | U35: =IF(Y35="✔","OK",IF(OR(J35="",J35=0),"",TEXT(MONTH(J35+20),"00")&"/"&TEXT(YEAR(J35+20),"0000"))) -> 07/2026 | V35: =L35-M35 -> 0 | W35: F66050 | X35: 46175 | Y35: 🔮
B36: 0016A | C36: 26Z0000126 | D36: 252911981 | E36: 4300035325 | G36: H 318 | H36: ADAPTER SLEEVE H 318 SKF | I36: 46066 | J36: 46197 | K36: EMWH | L36: 5 | M36: 5 | N36: =IF(L36=0,0,M36/L36) -> 1 | O36: 25.74 | P36: =L36*O36 -> 128.7 | Q36: 12723 | R36: READY FOR COLLECTION | S36: =IF(Y36="✔","✔ OK",IF(OR(J36="",J36=0),"TBA",INT(J36-I36))) -> 131 | T36: =IF(I36="","",TEXT(MONTH(I36),"00")&"/"&YEAR(I36)) -> 02/2026 | U36: =IF(Y36="✔","OK",IF(OR(J36="",J36=0),"",TEXT(MONTH(J36+20),"00")&"/"&TEXT(YEAR(J36+20),"0000"))) -> 07/2026 | V36: =L36-M36 -> 0 | W36: F66050 | X36: 46175 | Y36: 🔮
B37: 0017A | C37: 26Z0000126 | D37: 252911981 | E37: 4300035325 | F37: 13061642 | G37: TXL 518 | H37: SEAL TSN518 TK SKF | I37: 46066 | J37: 46197 | K37: EMWH | L37: 5 | M37: 5 | N37: =IF(L37=0,0,M37/L37) -> 1 | O37: 4.79 | P37: =L37*O37 -> 23.95 | Q37: 12723 | R37: READY FOR COLLECTION | S37: =IF(Y37="✔","✔ OK",IF(OR(J37="",J37=0),"TBA",INT(J37-I37))) -> 131 | T37: =IF(I37="","",TEXT(MONTH(I37),"00")&"/"&YEAR(I37)) -> 02/2026 | U37: =IF(Y37="✔","OK",IF(OR(J37="",J37=0),"",TEXT(MONTH(J37+20),"00")&"/"&TEXT(YEAR(J37+20),"0000"))) -> 07/2026 | V37: =L37-M37 -> 0 | W37: F66050 | X37: 46175 | Y37: 🔮
B38: 0018A | C38: 26Z0000126 | D38: 252911981 | E38: 4300035325 | F38: 13065456 | G38: FRB 12.5/160 | H38: LOCATING RING FRB 12.5/160 | I38: 46066 | J38: 46197 | K38: EMWH | L38: 10 | M38: 10 | N38: =IF(L38=0,0,M38/L38) -> 1 | O38: 3.35 | P38: =L38*O38 -> 33.5 | Q38: 12723 | R38: READY FOR COLLECTION | S38: =IF(Y38="✔","✔ OK",IF(OR(J38="",J38=0),"TBA",INT(J38-I38))) -> 131 | T38: =IF(I38="","",TEXT(MONTH(I38),"00")&"/"&YEAR(I38)) -> 02/2026 | U38: =IF(Y38="✔","OK",IF(OR(J38="",J38=0),"",TEXT(MONTH(J38+20),"00")&"/"&TEXT(YEAR(J38+20),"0000"))) -> 07/2026 | V38: =L38-M38 -> 0 | W38: F66050 | X38: 46175 | Y38: 🔮
B39: 0002A | C39: 26Z0000099 | D39: 252911949 | E39: 4300034814 | F39: 15375351 | G39: 30230 | H39: ROLL BEARING 30230 A FAG | I39: 46057 | J39: 46127 | K39: EMWH | L39: 4 | M39: 4 | N39: =IF(L39=0,0,M39/L39) -> 1 | O39: 419.07 | P39: =L39*O39 -> 1676.28 | Q39: 12568 | R39: COLLECTED | S39: =IF(Y39="✔","✔ OK",IF(OR(J39="",J39=0),"TBA",INT(J39-I39))) -> ✔ OK | T39: =IF(I39="","",TEXT(MONTH(I39),"00")&"/"&YEAR(I39)) -> 02/2026 | U39: =IF(Y39="✔","OK",IF(OR(J39="",J39=0),"",TEXT(MONTH(J39+20),"00")&"/"&TEXT(YEAR(J39+20),"0000"))) -> OK | V39: =L39-M39 -> 0 | W39: F66050 | X39: 46163 | Y39: ✔ | Z39: 46181
B40: 0004A | C40: 26Z0000126 | D40: 252911981 | E40: 4300035325 | F40: 15062560 | G40: 23056 CCK/W33 | H40: BEARING 23056 CCK/W33 SKF | I40: 46066 | J40: 46134 | K40: EMWH | L40: 1 | M40: 1 | N40: =IF(L40=0,0,M40/L40) -> 1 | O40: 1455.7 | P40: =L40*O40 -> 1455.7 | Q40: 12545 | R40: COLLECTED | S40: =IF(Y40="✔","✔ OK",IF(OR(J40="",J40=0),"TBA",INT(J40-I40))) -> 68 | T40: =IF(I40="","",TEXT(MONTH(I40),"00")&"/"&YEAR(I40)) -> 02/2026 | U40: =IF(Y40="✔","OK",IF(OR(J40="",J40=0),"",TEXT(MONTH(J40+20),"00")&"/"&TEXT(YEAR(J40+20),"0000"))) -> 05/2026 | V40: =L40-M40 -> 0 | W40: F66050 | X40: 46132 | Y40: ⚠ | AA40: Gate Pass Issue (Still it is in TATA Stock)
B41: 0005A | C41: 26Z0000126 | D41: 252911981 | E41: 4300035325 | F41: 15652160 | G41: FRB 13/230 | H41: RING FRB 13/230 SKF | I41: 46066 | J41: 46134 | K41: EMWH | L41: 5 | M41: 5 | N41: =IF(L41=0,0,M41/L41) -> 1 | O41: 7.56 | P41: =L41*O41 -> 37.8 | Q41: 12545 | R41: COLLECTED | S41: =IF(Y41="✔","✔ OK",IF(OR(J41="",J41=0),"TBA",INT(J41-I41))) -> 68 | T41: =IF(I41="","",TEXT(MONTH(I41),"00")&"/"&YEAR(I41)) -> 02/2026 | U41: =IF(Y41="✔","OK",IF(OR(J41="",J41=0),"",TEXT(MONTH(J41+20),"00")&"/"&TEXT(YEAR(J41+20),"0000"))) -> 05/2026 | V41: =L41-M41 -> 0 | W41: F66050 | X41: 46132 | Y41: ⚠ | AA41: Gate Pass Issue (Still it is in TATA Stock)
B42: 0006B | C42: 26Z0000126 | D42: 252911981 | E42: 4300035325 | F42: 15134397 | G42: SRV.NU 407 | H42: CYL ROL BEARING | I42: 46066 | J42: 46148 | K42: EMWH | L42: 5 | M42: 5 | N42: =IF(L42=0,0,M42/L42) -> 1 | O42: 69.69 | P42: =L42*O42 -> 348.45 | Q42: 12632 | R42: COLLECTED | S42: =IF(Y42="✔","✔ OK",IF(OR(J42="",J42=0),"TBA",INT(J42-I42))) -> ✔ OK | T42: =IF(I42="","",TEXT(MONTH(I42),"00")&"/"&YEAR(I42)) -> 02/2026 | U42: =IF(Y42="✔","OK",IF(OR(J42="",J42=0),"",TEXT(MONTH(J42+20),"00")&"/"&TEXT(YEAR(J42+20),"0000"))) -> OK | V42: =L42-M42 -> 0 | W42: F66050 | X42: 46163 | Y42: ✔ | Z42: 46181
B43: 0007A | C43: 26Z0000126 | D43: 252911981 | E43: 4300035325 | F43: 15149497 | G43: 32324 | H43: ROLL BEARING 32324J2 SKF | I43: 46066 | J43: 46134 | K43: EMWH | L43: 2 | M43: 2 | N43: =IF(L43=0,0,M43/L43) -> 1 | O43: 712.12 | P43: =L43*O43 -> 1424.24 | Q43: 12545 | R43: COLLECTED | S43: =IF(Y43="✔","✔ OK",IF(OR(J43="",J43=0),"TBA",INT(J43-I43))) -> 68 | T43: =IF(I43="","",TEXT(MONTH(I43),"00")&"/"&YEAR(I43)) -> 02/2026 | U43: =IF(Y43="✔","OK",IF(OR(J43="",J43=0),"",TEXT(MONTH(J43+20),"00")&"/"&TEXT(YEAR(J43+20),"0000"))) -> 05/2026 | V43: =L43-M43 -> 0 | W43: F66050 | X43: 46132 | Y43: ⚠ | AA43: Gate Pass Issue (Still it is in TATA Stock)
B44: 0008A | C44: 26Z0000126 | D44: 252911981 | E44: 4300035325 | F44: 15119748 | G44: 23138 CCK/W33 | H44: BEARING 23138 CC K W33 SKF | I44: 46066 | J44: 46134 | K44: EMWH | L44: 1 | M44: 1 | N44: =IF(L44=0,0,M44/L44) -> 1 | O44: 853.39 | P44: =L44*O44 -> 853.39 | Q44: 12545 | R44: COLLECTED | S44: =IF(Y44="✔","✔ OK",IF(OR(J44="",J44=0),"TBA",INT(J44-I44))) -> 68 | T44: =IF(I44="","",TEXT(MONTH(I44),"00")&"/"&YEAR(I44)) -> 02/2026 | U44: =IF(Y44="✔","OK",IF(OR(J44="",J44=0),"",TEXT(MONTH(J44+20),"00")&"/"&TEXT(YEAR(J44+20),"0000"))) -> 05/2026 | V44: =L44-M44 -> 0 | W44: F66050 | X44: 46132 | Y44: ⚠ | AA44: Gate Pass Issue (Still it is in TATA Stock)
B45: 0009A | C45: 26Z0000126 | D45: 252911981 | E45: 4300035325 | F45: 15505463 | G45: 23140 CCK/W33 | H45: BEARING 23140 CC K W33 SKF | I45: 46066 | J45: 46134 | K45: EMWH | L45: 1 | M45: 1 | N45: =IF(L45=0,0,M45/L45) -> 1 | O45: 1056.59 | P45: =L45*O45 -> 1056.59 | Q45: 12545 | R45: COLLECTED | S45: =IF(Y45="✔","✔ OK",IF(OR(J45="",J45=0),"TBA",INT(J45-I45))) -> 68 | T45: =IF(I45="","",TEXT(MONTH(I45),"00")&"/"&YEAR(I45)) -> 02/2026 | U45: =IF(Y45="✔","OK",IF(OR(J45="",J45=0),"",TEXT(MONTH(J45+20),"00")&"/"&TEXT(YEAR(J45+20),"0000"))) -> 05/2026 | V45: =L45-M45 -> 0 | W45: F66050 | X45: 46132 | Y45: ⚠ | AA45: Gate Pass Issue (Still it is in TATA Stock)
B46: 0010A | C46: 26Z0000126 | D46: 252911981 | E46: 4300035325 | F46: 15055683 | G46: 22240 CC/W33 | H46: BEARING 22240 CC/W33 SKF | I46: 46066 | J46: 46134 | K46: EMWH | L46: 1 | M46: 1 | N46: =IF(L46=0,0,M46/L46) -> 1 | O46: 1044.34 | P46: =L46*O46 -> 1044.34 | Q46: 12545 | R46: COLLECTED | S46: =IF(Y46="✔","✔ OK",IF(OR(J46="",J46=0),"TBA",INT(J46-I46))) -> ✔ OK | T46: =IF(I46="","",TEXT(MONTH(I46),"00")&"/"&YEAR(I46)) -> 02/2026 | U46: =IF(Y46="✔","OK",IF(OR(J46="",J46=0),"",TEXT(MONTH(J46+20),"00")&"/"&TEXT(YEAR(J46+20),"0000"))) -> OK | V46: =L46-M46 -> 0 | W46: F66050 | X46: 46132 | Y46: ✔ | Z46: 46181
B47: 0002A | C47: 26Z0000174 | D47: 252912114 | E47: 4300035558 | F47: 15348604 | G47: 6319/C3 | H47: BALL BRNG 6319/C3 SKF | I47: 46077 | J47: 46148 | K47: EMWH | L47: 4 | M47: 4 | N47: =IF(L47=0,0,M47/L47) -> 1 | O47: 95.8 | P47: =L47*O47 -> 383.2 | Q47: 12622 | R47: COLLECTED | S47: =IF(Y47="✔","✔ OK",IF(OR(J47="",J47=0),"TBA",INT(J47-I47))) -> ✔ OK | T47: =IF(I47="","",TEXT(MONTH(I47),"00")&"/"&YEAR(I47)) -> 02/2026 | U47: =IF(Y47="✔","OK",IF(OR(J47="",J47=0),"",TEXT(MONTH(J47+20),"00")&"/"&TEXT(YEAR(J47+20),"0000"))) -> OK | V47: =L47-M47 -> 0 | W47: F66050 | X47: 46163 | Y47: ✔ | Z47: 46181
B48: 0003A | C48: 26Z0000174 | D48: 252912114 | E48: 4300035558 | F48: 15383260 | G48: NU 234 ECML/C3 | H48: CL RL BRG NU 234 M C3 SKF | I48: 46077 | J48: 46155 | K48: EMWH | L48: 4 | M48: 4 | N48: =IF(L48=0,0,M48/L48) -> 1 | O48: 730.28 | P48: =L48*O48 -> 2921.12 | Q48: 12622 | R48: COLLECTED | S48: =IF(Y48="✔","✔ OK",IF(OR(J48="",J48=0),"TBA",INT(J48-I48))) -> ✔ OK | T48: =IF(I48="","",TEXT(MONTH(I48),"00")&"/"&YEAR(I48)) -> 02/2026 | U48: =IF(Y48="✔","OK",IF(OR(J48="",J48=0),"",TEXT(MONTH(J48+20),"00")&"/"&TEXT(YEAR(J48+20),"0000"))) -> OK | V48: =L48-M48 -> 0 | W48: F66050 | X48: 46163 | Y48: ✔ | Z48: 46181
B49: 0003B | C49: 26Z0000174 | D49: 252912114 | E49: 4300035558 | F49: 15383260 | G49: NU 234 ECML/C3 | H49: CL RL BRG NU 234 M C3 SKF | I49: 46077 | J49: 46155 | K49: EMWH | L49: 3 | M49: 3 | N49: =IF(L49=0,0,M49/L49) -> 1 | O49: 730.28 | P49: =L49*O49 -> 2190.84 | Q49: 12622 | R49: COLLECTED | S49: =IF(Y49="✔","✔ OK",IF(OR(J49="",J49=0),"TBA",INT(J49-I49))) -> ✔ OK | T49: =IF(I49="","",TEXT(MONTH(I49),"00")&"/"&YEAR(I49)) -> 02/2026 | U49: =IF(Y49="✔","OK",IF(OR(J49="",J49=0),"",TEXT(MONTH(J49+20),"00")&"/"&TEXT(YEAR(J49+20),"0000"))) -> OK | V49: =L49-M49 -> 0 | W49: F66050 | X49: 46163 | Y49: ✔ | Z49: 46181
B50: 0004A | C50: 26Z0000174 | D50: 252912114 | E50: 4300035558 | F50: 15153689 | G50: COP.01EB150MGR | H50: CL RL BRG 01 B 150M GR COPPER BEARINGS | I50: 46077 | J50: 46169 | K50: EMWH | L50: 1 | M50: 1 | N50: =IF(L50=0,0,M50/L50) -> 1 | O50: 1379.51 | P50: =L50*O50 -> 1379.51 | Q50: 12661 | R50: COLLECTED | S50: =IF(Y50="✔","✔ OK",IF(OR(J50="",J50=0),"TBA",INT(J50-I50))) -> 92 | T50: =IF(I50="","",TEXT(MONTH(I50),"00")&"/"&YEAR(I50)) -> 02/2026 | U50: =IF(Y50="✔","OK",IF(OR(J50="",J50=0),"",TEXT(MONTH(J50+20),"00")&"/"&TEXT(YEAR(J50+20),"0000"))) -> 06/2026 | V50: =L50-M50 -> 0 | W50: F66050 | X50: 46163 | Y50: ⚠ | AA50: Gate Pass Issue (Still it is in TATA Stock)
B51: 0005A | C51: 26Z0000174 | D51: 252912114 | E51: 4300035558 | F51: 15174197 | G51: 6316/C3 | H51: BALL BRNG 6316 C3 SKF | I51: 46077 | J51: 46080 | K51: QZSS | L51: 2 | M51: 2 | N51: =IF(L51=0,0,M51/L51) -> 1 | O51: 51.82 | P51: =L51*O51 -> 103.64 | Q51: 12431 | R51: COLLECTED | S51: =IF(Y51="✔","✔ OK",IF(OR(J51="",J51=0),"TBA",INT(J51-I51))) -> ✔ OK | T51: =IF(I51="","",TEXT(MONTH(I51),"00")&"/"&YEAR(I51)) -> 02/2026 | U51: =IF(Y51="✔","OK",IF(OR(J51="",J51=0),"",TEXT(MONTH(J51+20),"00")&"/"&TEXT(YEAR(J51+20),"0000"))) -> OK | V51: =L51-M51 -> 0 | W51: F66050 | X51: 46128 | Y51: ✔ | Z51: 46195
B52: 0001A | C52: 26Z0000126 | D52: 252911981 | E52: 4300035325 | F52: 15392508 | G52: 23232 CCK/W33 | H52: BEARING 23232 CCK/W33 SKF | I52: 46066 | J52: 46134 | K52: EMWH | L52: 1 | M52: 1 | N52: =IF(L52=0,0,M52/L52) -> 1 | O52: 659.88 | P52: =L52*O52 -> 659.88 | Q52: 12545 | R52: COLLECTED | S52: =IF(Y52="✔","✔ OK",IF(OR(J52="",J52=0),"TBA",INT(J52-I52))) -> 68 | T52: =IF(I52="","",TEXT(MONTH(I52),"00")&"/"&YEAR(I52)) -> 02/2026 | U52: =IF(Y52="✔","OK",IF(OR(J52="",J52=0),"",TEXT(MONTH(J52+20),"00")&"/"&TEXT(YEAR(J52+20),"0000"))) -> 05/2026 | V52: =L52-M52 -> 0 | W52: F66050 | X52: 46132 | Y52: ⚠ | AA52: Gate Pass Issue (Still it is in TATA Stock)
B53: 0002A | C53: 26Z0000126 | D53: 252911981 | E53: 4300035325 | F53: 15130069 | G53: 6216/C3 | H53: BALL BRNG 6216 - C3 SKF | I53: 46066 | J53: 46134 | K53: EMWH | L53: 1 | M53: 1 | N53: =IF(L53=0,0,M53/L53) -> 1 | O53: 30.44 | P53: =L53*O53 -> 30.44 | Q53: 12545 | R53: COLLECTED | S53: =IF(Y53="✔","✔ OK",IF(OR(J53="",J53=0),"TBA",INT(J53-I53))) -> 68 | T53: =IF(I53="","",TEXT(MONTH(I53),"00")&"/"&YEAR(I53)) -> 02/2026 | U53: =IF(Y53="✔","OK",IF(OR(J53="",J53=0),"",TEXT(MONTH(J53+20),"00")&"/"&TEXT(YEAR(J53+20),"0000"))) -> 05/2026 | V53: =L53-M53 -> 0 | W53: F66050 | X53: 46132 | Y53: ⚠ | AA53: Gate Pass Issue (Still it is in TATA Stock)
B54: 0003A | C54: 26Z0000126 | D54: 252911981 | E54: 4300035325 | F54: 15003876 | G54: 2217 K | H54: BALL BRNG 2217 K SKF | I54: 46066 | J54: 46134 | K54: EMWH | L54: 1 | M54: 1 | N54: =IF(L54=0,0,M54/L54) -> 1 | O54: 120.38 | P54: =L54*O54 -> 120.38 | Q54: 12545 | R54: COLLECTED | S54: =IF(Y54="✔","✔ OK",IF(OR(J54="",J54=0),"TBA",INT(J54-I54))) -> 68 | T54: =IF(I54="","",TEXT(MONTH(I54),"00")&"/"&YEAR(I54)) -> 02/2026 | U54: =IF(Y54="✔","OK",IF(OR(J54="",J54=0),"",TEXT(MONTH(J54+20),"00")&"/"&TEXT(YEAR(J54+20),"0000"))) -> 05/2026 | V54: =L54-M54 -> 0 | W54: F66050 | X54: 46132 | Y54: ⚠ | AA54: Gate Pass Issue (Still it is in TATA Stock)
B55: 0003A | C55: 26Z0000279 | D55: 252912134 | E55: 4300034374 | F55: 15156479 | G55: COP.01EB150MGR | H55: CL RL BRG 01 B150M COOPER | I55: 46113 | J55: 46197 | K55: EMWH | L55: 6 | M55: 6 | N55: =IF(L55=0,0,M55/L55) -> 1 | O55: 1241.56 | P55: =L55*O55 -> 7449.36 | Q55: 12755 | R55: COLLECTED | S55: =IF(Y55="✔","✔ OK",IF(OR(J55="",J55=0),"TBA",INT(J55-I55))) -> ✔ OK | T55: =IF(I55="","",TEXT(MONTH(I55),"00")&"/"&YEAR(I55)) -> 04/2026 | U55: =IF(Y55="✔","OK",IF(OR(J55="",J55=0),"",TEXT(MONTH(J55+20),"00")&"/"&TEXT(YEAR(J55+20),"0000"))) -> OK | V55: =L55-M55 -> 0 | W55: F66050 | X55: 46175 | Y55: ✔ | Z55: 46195
B56: 0004A | C56: 26Z0000279 | D56: 252912134 | E56: 4300034374 | F56: 15056773 | G56: 32230 | H56: BEARING;TAPERED ROLLER;32230JR;KOYO | I56: 46113 | J56: 46183 | K56: EMWH | L56: 2 | M56: 2 | N56: =IF(L56=0,0,M56/L56) -> 1 | O56: 478.59 | P56: =L56*O56 -> 957.18 | Q56: 12755 | R56: COLLECTED | S56: =IF(Y56="✔","✔ OK",IF(OR(J56="",J56=0),"TBA",INT(J56-I56))) -> ✔ OK | T56: =IF(I56="","",TEXT(MONTH(I56),"00")&"/"&YEAR(I56)) -> 04/2026 | U56: =IF(Y56="✔","OK",IF(OR(J56="",J56=0),"",TEXT(MONTH(J56+20),"00")&"/"&TEXT(YEAR(J56+20),"0000"))) -> OK | V56: =L56-M56 -> 0 | W56: F66050 | X56: 46175 | Y56: ✔ | Z56: 46195
B57: 0005A | C57: 26Z0000279 | D57: 252912134 | E57: 4300034374 | F57: 15374830 | G57: NU 2213 ECJ | H57: CL RL BRG NU2213E SKF | I57: 46113 | J57: 46183 | K57: EMWH | L57: 1 | M57: 1 | N57: =IF(L57=0,0,M57/L57) -> 1 | O57: 54.47 | P57: =L57*O57 -> 54.47 | Q57: 12755 | R57: COLLECTED | S57: =IF(Y57="✔","✔ OK",IF(OR(J57="",J57=0),"TBA",INT(J57-I57))) -> ✔ OK | T57: =IF(I57="","",TEXT(MONTH(I57),"00")&"/"&YEAR(I57)) -> 04/2026 | U57: =IF(Y57="✔","OK",IF(OR(J57="",J57=0),"",TEXT(MONTH(J57+20),"00")&"/"&TEXT(YEAR(J57+20),"0000"))) -> OK | V57: =L57-M57 -> 0 | W57: F66050 | X57: 46175 | Y57: ✔ | Z57: 46195
B58: 0006A | C58: 26Z0000279 | D58: 252912134 | E58: 4300034374 | F58: 13061642 | G58: TXL 518 | H58: SEAL TSN518 TK SKF | I58: 46113 | J58: 46183 | K58: EMWH | L58: 19 | M58: 19 | N58: =IF(L58=0,0,M58/L58) -> 1 | O58: 7.65 | P58: =L58*O58 -> 145.35 | Q58: 12755 | R58: COLLECTED | S58: =IF(Y58="✔","✔ OK",IF(OR(J58="",J58=0),"TBA",INT(J58-I58))) -> ✔ OK | T58: =IF(I58="","",TEXT(MONTH(I58),"00")&"/"&YEAR(I58)) -> 04/2026 | U58: =IF(Y58="✔","OK",IF(OR(J58="",J58=0),"",TEXT(MONTH(J58+20),"00")&"/"&TEXT(YEAR(J58+20),"0000"))) -> OK | V58: =L58-M58 -> 0 | W58: F66050 | X58: 46175 | Y58: ✔ | Z58: 46195
B59: 0008A | C59: 26Z0000279 | D59: 252912134 | E59: 4300034374 | F59: 13037709 | G59: FY 1.7/16 TF | H59: BEARING UNIT SQUARE FLANGED | I59: 46113 | J59: 46183 | K59: EMWH | L59: 1 | M59: 1 | N59: =IF(L59=0,0,M59/L59) -> 1 | O59: 21.67 | P59: =L59*O59 -> 21.67 | Q59: 12755 | R59: COLLECTED | S59: =IF(Y59="✔","✔ OK",IF(OR(J59="",J59=0),"TBA",INT(J59-I59))) -> ✔ OK | T59: =IF(I59="","",TEXT(MONTH(I59),"00")&"/"&YEAR(I59)) -> 04/2026 | U59: =IF(Y59="✔","OK",IF(OR(J59="",J59=0),"",TEXT(MONTH(J59+20),"00")&"/"&TEXT(YEAR(J59+20),"0000"))) -> OK | V59: =L59-M59 -> 0 | W59: F66050 | X59: 46175 | Y59: ✔ | Z59: 46195
B60: 0013A | C60: 26Z0000240 | D60: 252912296 | E60: 4300036353 | F60: 15047773 | G60: H 3136 | H60: BRG BUSHING FIXAT 160MM | I60: 46100 | J60: 46225 | K60: EMWH | L60: 4 | M60: 4 | N60: =IF(L60=0,0,M60/L60) -> 1 | O60: 186.13 | P60: =L60*O60 -> 744.52 | Q60: 0000000 | R60: SHS | S60: =IF(Y60="✔","✔ OK",IF(OR(J60="",J60=0),"TBA",INT(J60-I60))) -> 125 | T60: =IF(I60="","",TEXT(MONTH(I60),"00")&"/"&YEAR(I60)) -> 03/2026 | U60: =IF(Y60="✔","OK",IF(OR(J60="",J60=0),"",TEXT(MONTH(J60+20),"00")&"/"&TEXT(YEAR(J60+20),"0000"))) -> 08/2026 | V60: =L60-M60 -> 0 | W60: F66050 | Y60: ✘ | AA60: 25.06.2026 ETA - SANR0409719
B61: 0004B | C61: 26Z0000402 | D61: 262910345 | F61: 16177612 | G61: TSN 526 S | H61: SEAL TSN526S SKF | I61: 46161 | J61: 46225 | K61: EMWH | L61: 1 | M61: 1 | N61: =IF(L61=0,0,M61/L61) -> 1 | O61: 112.33 | P61: =L61*O61 -> 112.33 | Q61: 0000000 | R61: SHS | S61: =IF(Y61="✔","✔ OK",IF(OR(J61="",J61=0),"TBA",INT(J61-I61))) -> 64 | T61: =IF(I61="","",TEXT(MONTH(I61),"00")&"/"&YEAR(I61)) -> 05/2026 | U61: =IF(Y61="✔","OK",IF(OR(J61="",J61=0),"",TEXT(MONTH(J61+20),"00")&"/"&TEXT(YEAR(J61+20),"0000"))) -> 08/2026 | V61: =L61-M61 -> 0 | W61: F66050 | Y61: ✘ | AA61: Checking if factory can assist with stock
B62: 0004C | C62: 26Z0000402 | D62: 262910345 | F62: 16177612 | G62: TSN 526 S | H62: SEAL TSN526S SKF | I62: 46161 | J62: 46225 | K62: EMWH | L62: 3 | M62: 3 | N62: =IF(L62=0,0,M62/L62) -> 1 | O62: 112.33 | P62: =L62*O62 -> 336.99 | Q62: 0000000 | R62: SHS | S62: =IF(Y62="✔","✔ OK",IF(OR(J62="",J62=0),"TBA",INT(J62-I62))) -> 64 | T62: =IF(I62="","",TEXT(MONTH(I62),"00")&"/"&YEAR(I62)) -> 05/2026 | U62: =IF(Y62="✔","OK",IF(OR(J62="",J62=0),"",TEXT(MONTH(J62+20),"00")&"/"&TEXT(YEAR(J62+20),"0000"))) -> 08/2026 | V62: =L62-M62 -> 0 | W62: F66050 | Y62: ✘ | AA62: Checking if factory can assist with stock
B63: 0004D | C63: 26Z0000402 | D63: 262910345 | F63: 16177612 | G63: TSN 526 S | H63: SEAL TSN526S SKF | I63: 46161 | J63: 46260 | K63: EMWH | L63: 6 | M63: 6 | N63: =IF(L63=0,0,M63/L63) -> 1 | O63: 112.33 | P63: =L63*O63 -> 673.98 | Q63: 0000000 | R63: RPI | S63: =IF(Y63="✔","✔ OK",IF(OR(J63="",J63=0),"TBA",INT(J63-I63))) -> 99 | T63: =IF(I63="","",TEXT(MONTH(I63),"00")&"/"&YEAR(I63)) -> 05/2026 | U63: =IF(Y63="✔","OK",IF(OR(J63="",J63=0),"",TEXT(MONTH(J63+20),"00")&"/"&TEXT(YEAR(J63+20),"0000"))) -> 09/2026 | V63: =L63-M63 -> 0 | W63: F66050 | Y63: ✘ | AA63: Checking if factory can assist with stock
B64: 0007A | C64: 26Z0000402 | D64: 262910345 | F64: 16177612 | G64: TSN 526 S | H64: SEAL TSN526S SKF | I64: 46161 | J64: 46260 | K64: EMWH | L64: 16 | M64: 16 | N64: =IF(L64=0,0,M64/L64) -> 1 | O64: 112.33 | P64: =L64*O64 -> 1797.28 | Q64: 0000000 | R64: RPI | S64: =IF(Y64="✔","✔ OK",IF(OR(J64="",J64=0),"TBA",INT(J64-I64))) -> 99 | T64: =IF(I64="","",TEXT(MONTH(I64),"00")&"/"&YEAR(I64)) -> 05/2026 | U64: =IF(Y64="✔","OK",IF(OR(J64="",J64=0),"",TEXT(MONTH(J64+20),"00")&"/"&TEXT(YEAR(J64+20),"0000"))) -> 09/2026 | V64: =L64-M64 -> 0 | W64: F66050 | Y64: ✘ | AA64: Checking if factory can assist with stock
B65: 0002A | C65: 26Z0000381 | D65: 262910321 | E65: 4300037783 | F65: 13188470 | G65: COP.01EB140MGR | H65: CL RL BRG 01 B 140M GR COOPER BEARINGS | I65: 46154 | J65: 46246 | K65: EMWH | L65: 1 | M65: 1 | N65: =IF(L65=0,0,M65/L65) -> 1 | O65: 1490.97 | P65: =L65*O65 -> 1490.97 | Q65: 0000000 | R65: SHS | S65: =IF(Y65="✔","✔ OK",IF(OR(J65="",J65=0),"TBA",INT(J65-I65))) -> 92 | T65: =IF(I65="","",TEXT(MONTH(I65),"00")&"/"&YEAR(I65)) -> 05/2026 | U65: =IF(Y65="✔","OK",IF(OR(J65="",J65=0),"",TEXT(MONTH(J65+20),"00")&"/"&TEXT(YEAR(J65+20),"0000"))) -> 09/2026 | V65: =L65-M65 -> 0 | W65: F66050 | Y65: ✘ | AA65: Stock shipped from EDC - Awaiting shipping details
B66: 0008A | C66: 26Z0000381 | D66: 262910321 | E66: 4300037783 | F66: 13188470 | G66: COP.01EB140MGR | H66: CL RL BRG 01 B 140M GR COOPER BEARINGS | I66: 46154 | J66: 46195 | K66: EMWH | L66: 1 | M66: 1 | N66: =IF(L66=0,0,M66/L66) -> 1 | O66: 1490.97 | P66: =L66*O66 -> 1490.97 | Q66: 0000000 | R66: SHS | S66: =IF(Y66="✔","✔ OK",IF(OR(J66="",J66=0),"TBA",INT(J66-I66))) -> 41 | T66: =IF(I66="","",TEXT(MONTH(I66),"00")&"/"&YEAR(I66)) -> 05/2026 | U66: =IF(Y66="✔","OK",IF(OR(J66="",J66=0),"",TEXT(MONTH(J66+20),"00")&"/"&TEXT(YEAR(J66+20),"0000"))) -> 07/2026 | V66: =L66-M66 -> 0 | W66: F66050 | Y66: 🔮 | AA66: Stock shipped from EDC - Awaiting shipping details
B67: 0001A | C67: 26Z0000383 | D67: 262910319 | E67: 4300037815 | F67: 15011261 | G67: 22326 CCJA/W33VA405 | H67: BEARING 22326 CC JA C4 W33 VA405 SKF | I67: 46154 | J67: 46225 | K67: EMWH | L67: 60 | M67: 60 | N67: =IF(L67=0,0,M67/L67) -> 1 | O67: 678.04 | P67: =L67*O67 -> 40682.4 | Q67: 0000000 | R67: SHS | S67: =IF(Y67="✔","✔ OK",IF(OR(J67="",J67=0),"TBA",INT(J67-I67))) -> 71 | T67: =IF(I67="","",TEXT(MONTH(I67),"00")&"/"&YEAR(I67)) -> 05/2026 | U67: =IF(Y67="✔","OK",IF(OR(J67="",J67=0),"",TEXT(MONTH(J67+20),"00")&"/"&TEXT(YEAR(J67+20),"0000"))) -> 08/2026 | V67: =L67-M67 -> 0 | W67: F66050 | Y67: ✘ | AA67: Stock is in RPI in Belguim , will be shipped out this week
B68: 0003A | C68: 26Z0000383 | D68: 262910319 | E68: 4300037815 | F68: 15011261 | G68: 22326 CCJA/W33VA405 | H68: BEARING 22326 CC JA C4 W33 VA405 SKF | I68: 46154 | J68: 46225 | K68: EMWH | L68: 22 | M68: 22 | N68: =IF(L68=0,0,M68/L68) -> 1 | O68: 678.04 | P68: =L68*O68 -> 14916.88 | Q68: 0000000 | R68: SHS | S68: =IF(Y68="✔","✔ OK",IF(OR(J68="",J68=0),"TBA",INT(J68-I68))) -> 71 | T68: =IF(I68="","",TEXT(MONTH(I68),"00")&"/"&YEAR(I68)) -> 05/2026 | U68: =IF(Y68="✔","OK",IF(OR(J68="",J68=0),"",TEXT(MONTH(J68+20),"00")&"/"&TEXT(YEAR(J68+20),"0000"))) -> 08/2026 | V68: =L68-M68 -> 0 | W68: F66050 | Y68: ✘ | AA68: Stock is in RPI in Belguim , will be shipped out this week
B69: 0001A | C69: 26Z0000422 | D69: 262910469 | E69: 4300037947 | F69: 15055565 | G69: COP.SDQ3140 | H69: BEARING;SANDVIK;01BC SD3140 GR TL | I69: 46169 | J69: 46175 | K69: QZSS | L69: 3 | M69: 0 | N69: =IF(L69=0,0,M69/L69) -> 0 | O69: 3267.67 | P69: =L69*O69 -> 9803.01 | Q69: 0000000 | R69: RPI | S69: =IF(Y69="✔","✔ OK",IF(OR(J69="",J69=0),"TBA",INT(J69-I69))) -> 6 | T69: =IF(I69="","",TEXT(MONTH(I69),"00")&"/"&YEAR(I69)) -> 05/2026 | U69: =IF(Y69="✔","OK",IF(OR(J69="",J69=0),"",TEXT(MONTH(J69+20),"00")&"/"&TEXT(YEAR(J69+20),"0000"))) -> 06/2026 | V69: =L69-M69 -> 3 | W69: F66050 | Y69: 🔮 | AA69: 26L0024238 / LOCAL
B70: 0002A | C70: 26Z0000402 | D70: 262910345 | F70: 16177612 | G70: TSN 526 S | H70: SEAL TSN526S SKF | I70: 46161 | J70: 46225 | K70: EMWH | L70: 6 | M70: 6 | N70: =IF(L70=0,0,M70/L70) -> 1 | O70: 112.33 | P70: =L70*O70 -> 673.98 | Q70: 0000000 | R70: SHS | S70: =IF(Y70="✔","✔ OK",IF(OR(J70="",J70=0),"TBA",INT(J70-I70))) -> 64 | T70: =IF(I70="","",TEXT(MONTH(I70),"00")&"/"&YEAR(I70)) -> 05/2026 | U70: =IF(Y70="✔","OK",IF(OR(J70="",J70=0),"",TEXT(MONTH(J70+20),"00")&"/"&TEXT(YEAR(J70+20),"0000"))) -> 08/2026 | V70: =L70-M70 -> 0 | W70: F66050 | Y70: ✘ | AA70: Will be shipped out today , awaiting shipment details
B71: 0002B | C71: 26Z0000402 | D71: 262910345 | F71: 16177612 | G71: TSN 526 S | H71: SEAL TSN526S SKF | I71: 46161 | J71: 46225 | K71: EMWH | L71: 6 | M71: 6 | N71: =IF(L71=0,0,M71/L71) -> 1 | O71: 112.33 | P71: =L71*O71 -> 673.98 | Q71: 0000000 | R71: SHS | S71: =IF(Y71="✔","✔ OK",IF(OR(J71="",J71=0),"TBA",INT(J71-I71))) -> 64 | T71: =IF(I71="","",TEXT(MONTH(I71),"00")&"/"&YEAR(I71)) -> 05/2026 | U71: =IF(Y71="✔","OK",IF(OR(J71="",J71=0),"",TEXT(MONTH(J71+20),"00")&"/"&TEXT(YEAR(J71+20),"0000"))) -> 08/2026 | V71: =L71-M71 -> 0 | W71: F66050 | Y71: ✘ | AA71: Will be shipped out today , awaiting shipment details
B72: 0003A | C72: 26Z0000402 | D72: 262910345 | F72: 16177612 | G72: TSN 526 S | H72: SEAL TSN526S SKF | I72: 46161 | J72: 46225 | K72: EMWH | L72: 4 | M72: 4 | N72: =IF(L72=0,0,M72/L72) -> 1 | O72: 112.33 | P72: =L72*O72 -> 449.32 | Q72: 0000000 | R72: SHS | S72: =IF(Y72="✔","✔ OK",IF(OR(J72="",J72=0),"TBA",INT(J72-I72))) -> 64 | T72: =IF(I72="","",TEXT(MONTH(I72),"00")&"/"&YEAR(I72)) -> 05/2026 | U72: =IF(Y72="✔","OK",IF(OR(J72="",J72=0),"",TEXT(MONTH(J72+20),"00")&"/"&TEXT(YEAR(J72+20),"0000"))) -> 08/2026 | V72: =L72-M72 -> 0 | W72: F66050 | Y72: ✘ | AA72: Will be shipped out today , awaiting shipment details
B73: 0004A | C73: 26Z0000402 | D73: 262910345 | F73: 16177612 | G73: TSN 526 S | H73: SEAL TSN526S SKF | I73: 46161 | J73: 46225 | K73: EMWH | L73: 6 | M73: 6 | N73: =IF(L73=0,0,M73/L73) -> 1 | O73: 112.33 | P73: =L73*O73 -> 673.98 | Q73: 0000000 | R73: SHS | S73: =IF(Y73="✔","✔ OK",IF(OR(J73="",J73=0),"TBA",INT(J73-I73))) -> 64 | T73: =IF(I73="","",TEXT(MONTH(I73),"00")&"/"&YEAR(I73)) -> 05/2026 | U73: =IF(Y73="✔","OK",IF(OR(J73="",J73=0),"",TEXT(MONTH(J73+20),"00")&"/"&TEXT(YEAR(J73+20),"0000"))) -> 08/2026 | V73: =L73-M73 -> 0 | W73: F66050 | Y73: ✘ | AA73: Will be shipped out today , awaiting shipment details
B74: 0008A | C74: 26Z0000402 | D74: 262910345 | F74: 15055680 | G74: 22226 EK/C3 | H74: BEARING 22226 CCK W33 SKF | I74: 46161 | J74: 46225 | K74: EMWH | L74: 4 | M74: 4 | N74: =IF(L74=0,0,M74/L74) -> 1 | O74: 297.43 | P74: =L74*O74 -> 1189.72 | Q74: 0000000 | R74: SHS | S74: =IF(Y74="✔","✔ OK",IF(OR(J74="",J74=0),"TBA",INT(J74-I74))) -> 64 | T74: =IF(I74="","",TEXT(MONTH(I74),"00")&"/"&YEAR(I74)) -> 05/2026 | U74: =IF(Y74="✔","OK",IF(OR(J74="",J74=0),"",TEXT(MONTH(J74+20),"00")&"/"&TEXT(YEAR(J74+20),"0000"))) -> 08/2026 | V74: =L74-M74 -> 0 | W74: F66050 | Y74: ✘ | AA74: Will be shipped out today , awaiting shipment details
B75: 0010A | C75: 26Z0000402 | D75: 262910345 | F75: 15419258 | G75: H 3140 | H75: BRG BUSHING FIXAT 180MM H 3140 SKF | I75: 46161 | J75: 46225 | K75: EMWH | L75: 2 | M75: 2 | N75: =IF(L75=0,0,M75/L75) -> 1 | O75: 194.06 | P75: =L75*O75 -> 388.12 | Q75: 0000000 | R75: SHS | S75: =IF(Y75="✔","✔ OK",IF(OR(J75="",J75=0),"TBA",INT(J75-I75))) -> 64 | T75: =IF(I75="","",TEXT(MONTH(I75),"00")&"/"&YEAR(I75)) -> 05/2026 | U75: =IF(Y75="✔","OK",IF(OR(J75="",J75=0),"",TEXT(MONTH(J75+20),"00")&"/"&TEXT(YEAR(J75+20),"0000"))) -> 08/2026 | V75: =L75-M75 -> 0 | W75: F66050 | Y75: ✘ | AA75: Will be shipped out today , awaiting shipment details
B76: 0003A | C76: 26Z0000428 | D76: 262910449 | E76: 4300038759 | F76: 13040483 | G76: COP.ATL170M | H76: LABYRINTH SEAL 170MMATL TIMKEN | I76: 46169 | J76: 46288 | K76: EMWH | L76: 50 | M76: 50 | N76: =IF(L76=0,0,M76/L76) -> 1 | O76: 226.14 | P76: =L76*O76 -> 11307 | Q76: 0000000 | R76: RBK | S76: =IF(Y76="✔","✔ OK",IF(OR(J76="",J76=0),"TBA",INT(J76-I76))) -> 119 | T76: =IF(I76="","",TEXT(MONTH(I76),"00")&"/"&YEAR(I76)) -> 05/2026 | U76: =IF(Y76="✔","OK",IF(OR(J76="",J76=0),"",TEXT(MONTH(J76+20),"00")&"/"&TEXT(YEAR(J76+20),"0000"))) -> 10/2026 | V76: =L76-M76 -> 0 | W76: F66050 | Y76: ✘ | AA76: Requested for availability USA
B77: 0004B | C77: 26Z0000428 | D77: 262910449 | E77: 4300038759 | F77: 17545471 | G77: PHF TB5040X100MM | H77: BUSH, TAPER LOCK;5040,100mm,101,6mm,SKF | I77: 46169 | J77: 46407 | K77: EMWH | L77: 1 | M77: 1 | N77: =IF(L77=0,0,M77/L77) -> 1 | O77: 86.1 | P77: =L77*O77 -> 86.1 | Q77: 0000000 | R77: BOK | S77: =IF(Y77="✔","✔ OK",IF(OR(J77="",J77=0),"TBA",INT(J77-I77))) -> 238 | T77: =IF(I77="","",TEXT(MONTH(I77),"00")&"/"&YEAR(I77)) -> 05/2026 | U77: =IF(Y77="✔","OK",IF(OR(J77="",J77=0),"",TEXT(MONTH(J77+20),"00")&"/"&TEXT(YEAR(J77+20),"0000"))) -> 02/2027 | V77: =L77-M77 -> 0 | W77: F66050 | Y77: ✘ | AA77: No Availability - Reached out to factory
B78: 0005A | C78: 26Z0000428 | D78: 262910449 | E78: 4300038759 | F78: 13040483 | G78: COP.ATL170M | H78: LABYRINTH SEAL 170MMATL TIMKEN | I78: 46169 | J78: 46288 | K78: EMWH | L78: 4 | M78: 4 | N78: =IF(L78=0,0,M78/L78) -> 1 | O78: 226.14 | P78: =L78*O78 -> 904.56 | Q78: 0000000 | R78: RBK | S78: =IF(Y78="✔","✔ OK",IF(OR(J78="",J78=0),"TBA",INT(J78-I78))) -> 119 | T78: =IF(I78="","",TEXT(MONTH(I78),"00")&"/"&YEAR(I78)) -> 05/2026 | U78: =IF(Y78="✔","OK",IF(OR(J78="",J78=0),"",TEXT(MONTH(J78+20),"00")&"/"&TEXT(YEAR(J78+20),"0000"))) -> 10/2026 | V78: =L78-M78 -> 0 | W78: F66050 | Y78: ✘ | AA78: Requested for availability USA
B79: 0007A | C79: 26Z0000428 | D79: 262910449 | E79: 4300038759 | F79: 17545471 | G79: PHF TB5040X100MM | H79: BUSH, TAPER LOCK;5040,100mm,101,6mm,SKF | I79: 46169 | J79: 46407 | K79: EMWH | L79: 2 | M79: 2 | N79: =IF(L79=0,0,M79/L79) -> 1 | O79: 86.1 | P79: =L79*O79 -> 172.2 | Q79: 0000000 | R79: BOK | S79: =IF(Y79="✔","✔ OK",IF(OR(J79="",J79=0),"TBA",INT(J79-I79))) -> 238 | T79: =IF(I79="","",TEXT(MONTH(I79),"00")&"/"&YEAR(I79)) -> 05/2026 | U79: =IF(Y79="✔","OK",IF(OR(J79="",J79=0),"",TEXT(MONTH(J79+20),"00")&"/"&TEXT(YEAR(J79+20),"0000"))) -> 02/2027 | V79: =L79-M79 -> 0 | W79: F66050 | Y79: ✘ | AA79: No Availability - Reached out to factory
B80: 0001A | C80: 26Z0000410 | D80: 262910450 | E80: 4300038547 | F80: 17563131 | G80: CMSS 943-LCI-SY-20M | H80: CABLE ASSEMBLY; CMSS 943-LCI-SY-20M; SKF | I80: 46163 | J80: 46225 | K80: EMWH | L80: 130 | M80: 130 | N80: =IF(L80=0,0,M80/L80) -> 1 | O80: 192.03 | P80: =L80*O80 -> 24963.9 | Q80: 0000000 | R80: RBK | S80: =IF(Y80="✔","✔ OK",IF(OR(J80="",J80=0),"TBA",INT(J80-I80))) -> 62 | T80: =IF(I80="","",TEXT(MONTH(I80),"00")&"/"&YEAR(I80)) -> 05/2026 | U80: =IF(Y80="✔","OK",IF(OR(J80="",J80=0),"",TEXT(MONTH(J80+20),"00")&"/"&TEXT(YEAR(J80+20),"0000"))) -> 08/2026 | V80: =L80-M80 -> 0 | W80: F66050 | Y80: ✘ | AA80: No stock availability - Current ETA 04.08.2026 - Requested for improvement
B81: 0002A | C81: 26Z0000382 | D81: 262910320 | E81: 4300037223 | F81: 15134397 | G81: SRV.NU 407 | H81: CYL ROL BEARING | I81: 46154 | K81: EMWH | L81: 27 | M81: 0 | N81: =IF(L81=0,0,M81/L81) -> 0 | O81: 71.7 | P81: =L81*O81 -> 1935.9 | Q81: 0000000 | R81: ENT | S81: =IF(Y81="✔","✔ OK",IF(OR(J81="",J81=0),"TBA",INT(J81-I81))) -> TBA | T81: =IF(I81="","",TEXT(MONTH(I81),"00")&"/"&YEAR(I81)) -> 05/2026 | U81: =IF(Y81="✔","OK",IF(OR(J81="",J81=0),"",TEXT(MONTH(J81+20),"00")&"/"&TEXT(YEAR(J81+20),"0000"))) | V81: =L81-M81 -> 27 | W81: F66050 | Y81: ✘ | AA81: No stock availability - Requested for factory acknowledgement
B82: 0005A | C82: 26Z0000240 | D82: 252912296 | E82: 4300036353 | F82: 15047773 | G82: H 3136 | H82: BRG BUSHING FIXAT 160MM | I82: 46100 | J82: 46237 | K82: QZSS | L82: 4 | M82: 4 | N82: =IF(L82=0,0,M82/L82) -> 1 | O82: 0 | P82: =L82*O82 -> 0 | Q82: 0000000 | R82: BOK | S82: =IF(Y82="✔","✔ OK",IF(OR(J82="",J82=0),"TBA",INT(J82-I82))) -> 137 | T82: =IF(I82="","",TEXT(MONTH(I82),"00")&"/"&YEAR(I82)) -> 03/2026 | U82: =IF(Y82="✔","OK",IF(OR(J82="",J82=0),"",TEXT(MONTH(J82+20),"00")&"/"&TEXT(YEAR(J82+20),"0000"))) -> 08/2026 | V82: =L82-M82 -> 0 | W82: F66050 | Y82: ✘ | AA82: EDC has stock requested for confirmation
B83: 0019A | C83: 26Z0000126 | D83: 252911981 | E83: 4300035325 | F83: 15153689 | G83: COP.01EB150MGR | H83: CL RL BRG 01 B 150M GR COPPER BEARINGS | I83: 46066 | K83: EMWH | L83: 1 | N83: =IF(L83=0,0,M83/L83) -> 0 | O83: 1403.53 | P83: =L83*O83 -> 1403.53 | Q83: 0000000 | R83: ENT | S83: =IF(Y83="✔","✔ OK",IF(OR(J83="",J83=0),"TBA",INT(J83-I83))) -> TBA | T83: =IF(I83="","",TEXT(MONTH(I83),"00")&"/"&YEAR(I83)) -> 02/2026 | U83: =IF(Y83="✔","OK",IF(OR(J83="",J83=0),"",TEXT(MONTH(J83+20),"00")&"/"&TEXT(YEAR(J83+20),"0000"))) | V83: =L83-M83 -> 1 | W83: F66050 | Y83: ✘ | AA83: No global availability - Requested for confirmation
B84: 0001A | C84: 26Z0000386 | D84: 262910319A | E84: 4300037815 | F84: 15011261 | G84: 22326 CCJA/W33VA405 | H84: BEARING 22326 CC JA C4 W33 VA405 SKF | I84: 46155 | J84: 46182 | K84: EMWH | L84: 20 | M84: 20 | N84: =IF(L84=0,0,M84/L84) -> 1 | O84: 678.04 | P84: =L84*O84 -> 13560.8 | Q84: 12675 | R84: COLLECTED | S84: =IF(Y84="✔","✔ OK",IF(OR(J84="",J84=0),"TBA",INT(J84-I84))) -> ✔ OK | T84: =IF(I84="","",TEXT(MONTH(I84),"00")&"/"&YEAR(I84)) -> 05/2026 | U84: =IF(Y84="✔","OK",IF(OR(J84="",J84=0),"",TEXT(MONTH(J84+20),"00")&"/"&TEXT(YEAR(J84+20),"0000"))) -> OK | V84: =L84-M84 -> 0 | W84: F66050 | X84: 46164 | Y84: ✔ | Z84: 46181
B85: 0002A | C85: 26Z0000304 | D85: 262910137 | G85: NU 2228 ECML/C3 | H85: CYLINDRICAL ROLLER BEARING NU 2228 ECML/C3 | I85: 46129 | J85: 46132 | K85: QZSS | L85: 4 | M85: 4 | N85: =IF(L85=0,0,M85/L85) -> 1 | O85: 570.15 | P85: =L85*O85 -> 2280.6 | Q85: 12562 | R85: COLLECTED | S85: =IF(Y85="✔","✔ OK",IF(OR(J85="",J85=0),"TBA",INT(J85-I85))) -> ✔ OK | T85: =IF(I85="","",TEXT(MONTH(I85),"00")&"/"&YEAR(I85)) -> 04/2026 | U85: =IF(Y85="✔","OK",IF(OR(J85="",J85=0),"",TEXT(MONTH(J85+20),"00")&"/"&TEXT(YEAR(J85+20),"0000"))) -> OK | V85: =L85-M85 -> 0 | W85: F66050 | X85: 46132 | Y85: ✔ | Z85: 46140
B86: 0001A | C86: 26Z0000291 | D86: 262910021 | E86: 4300036955 | F86: 16177612 | G86: TSN 526 S | H86: SEAL TSN526S SKF | I86: 46121 | J86: 46190 | K86: EMWH | L86: 4 | M86: 4 | N86: =IF(L86=0,0,M86/L86) -> 1 | O86: 113.22 | P86: =L86*O86 -> 452.88 | Q86: 12720 | R86: COLLECTED | S86: =IF(Y86="✔","✔ OK",IF(OR(J86="",J86=0),"TBA",INT(J86-I86))) -> ✔ OK | T86: =IF(I86="","",TEXT(MONTH(I86),"00")&"/"&YEAR(I86)) -> 04/2026 | U86: =IF(Y86="✔","OK",IF(OR(J86="",J86=0),"",TEXT(MONTH(J86+20),"00")&"/"&TEXT(YEAR(J86+20),"0000"))) -> OK | V86: =L86-M86 -> 0 | W86: F66050 | X86: 46175 | Y86: ✔ | Z86: 46195
B87: 0002B | C87: 26Z0000291 | D87: 262910021 | E87: 4300036955 | F87: 15004591 | G87: 22328 CCJA/W33VA405 | H87: BEARING 22328 CC JA C4 W33 VA405 SKF | I87: 46121 | J87: 46197 | K87: EMWH | L87: 10 | M87: 10 | N87: =IF(L87=0,0,M87/L87) -> 1 | O87: 838.97 | P87: =L87*O87 -> 8389.7 | Q87: 12720 | R87: COLLECTED | S87: =IF(Y87="✔","✔ OK",IF(OR(J87="",J87=0),"TBA",INT(J87-I87))) -> ✔ OK | T87: =IF(I87="","",TEXT(MONTH(I87),"00")&"/"&YEAR(I87)) -> 04/2026 | U87: =IF(Y87="✔","OK",IF(OR(J87="",J87=0),"",TEXT(MONTH(J87+20),"00")&"/"&TEXT(YEAR(J87+20),"0000"))) -> OK | V87: =L87-M87 -> 0 | W87: F66050 | X87: 46175 | Y87: ✔ | Z87: 46195
B88: 0003A | C88: 26Z0000291 | D88: 262910021 | E88: 4300036955 | F88: 17546207 | G88: 6216-2Z/C3 | H88: BEARING, BALL;DEEP GROOVE, 6216-2Z/C3,1 | I88: 46121 | J88: 46190 | K88: EMWH | L88: 10 | M88: 10 | N88: =IF(L88=0,0,M88/L88) -> 1 | O88: 20.2 | P88: =L88*O88 -> 202 | Q88: 12720 | R88: COLLECTED | S88: =IF(Y88="✔","✔ OK",IF(OR(J88="",J88=0),"TBA",INT(J88-I88))) -> ✔ OK | T88: =IF(I88="","",TEXT(MONTH(I88),"00")&"/"&YEAR(I88)) -> 04/2026 | U88: =IF(Y88="✔","OK",IF(OR(J88="",J88=0),"",TEXT(MONTH(J88+20),"00")&"/"&TEXT(YEAR(J88+20),"0000"))) -> OK | V88: =L88-M88 -> 0 | W88: F66050 | X88: 46175 | Y88: ✔ | Z88: 46195
B89: 0004A | C89: 26Z0000291 | D89: 262910021 | E89: 4300036955 | F89: 15374646 | G89: 31310/CL7C | H89: ROLL BEARING 31310 J2 Q CL7C SKF | I89: 46121 | J89: 46190 | K89: TBEW | L89: 10 | M89: 10 | N89: =IF(L89=0,0,M89/L89) -> 1 | O89: 35.31 | P89: =L89*O89 -> 353.1 | Q89: 12720 | R89: COLLECTED | S89: =IF(Y89="✔","✔ OK",IF(OR(J89="",J89=0),"TBA",INT(J89-I89))) -> ✔ OK | T89: =IF(I89="","",TEXT(MONTH(I89),"00")&"/"&YEAR(I89)) -> 04/2026 | U89: =IF(Y89="✔","OK",IF(OR(J89="",J89=0),"",TEXT(MONTH(J89+20),"00")&"/"&TEXT(YEAR(J89+20),"0000"))) -> OK | V89: =L89-M89 -> 0 | W89: F66050 | X89: 46175 | Y89: ✔ | Z89: 46195
B90: 0005A | C90: 26Z0000291 | D90: 262910021 | E90: 4300036955 | F90: 15374409 | G90: 30314 | H90: ROLL BEARING 30314 J2 Q SKF | I90: 46121 | J90: 46190 | K90: TBEW | L90: 4 | M90: 4 | N90: =IF(L90=0,0,M90/L90) -> 1 | O90: 33.17 | P90: =L90*O90 -> 132.68 | Q90: 12720 | R90: COLLECTED | S90: =IF(Y90="✔","✔ OK",IF(OR(J90="",J90=0),"TBA",INT(J90-I90))) -> ✔ OK | T90: =IF(I90="","",TEXT(MONTH(I90),"00")&"/"&YEAR(I90)) -> 04/2026 | U90: =IF(Y90="✔","OK",IF(OR(J90="",J90=0),"",TEXT(MONTH(J90+20),"00")&"/"&TEXT(YEAR(J90+20),"0000"))) -> OK | V90: =L90-M90 -> 0 | W90: F66050 | X90: 46175 | Y90: ✔ | Z90: 46195
B91: 0006A | C91: 26Z0000291 | D91: 262910021 | E91: 4300036955 | F91: 15153017 | G91: 6316/C3 | H91: BEARING 6316-C3;FRAME 250S/M;WEG | I91: 46121 | J91: 46190 | K91: EMWH | L91: 18 | M91: 18 | N91: =IF(L91=0,0,M91/L91) -> 1 | O91: 40.4 | P91: =L91*O91 -> 727.2 | Q91: 12720 | R91: COLLECTED | S91: =IF(Y91="✔","✔ OK",IF(OR(J91="",J91=0),"TBA",INT(J91-I91))) -> ✔ OK | T91: =IF(I91="","",TEXT(MONTH(I91),"00")&"/"&YEAR(I91)) -> 04/2026 | U91: =IF(Y91="✔","OK",IF(OR(J91="",J91=0),"",TEXT(MONTH(J91+20),"00")&"/"&TEXT(YEAR(J91+20),"0000"))) -> OK | V91: =L91-M91 -> 0 | W91: F66050 | X91: 46175 | Y91: ✔ | Z91: 46195
B92: 0007A | C92: 26Z0000291 | D92: 262910021 | E92: 4300036955 | F92: 17563152 | G92: NU 319 ECJ/C3 | H92: CYLIND ROLLER BEARING_NU_319_C3-SKF | I92: 46121 | J92: 46190 | K92: EMWH | L92: 4 | M92: 4 | N92: =IF(L92=0,0,M92/L92) -> 1 | O92: 136.16 | P92: =L92*O92 -> 544.64 | Q92: 12720 | R92: COLLECTED | S92: =IF(Y92="✔","✔ OK",IF(OR(J92="",J92=0),"TBA",INT(J92-I92))) -> ✔ OK | T92: =IF(I92="","",TEXT(MONTH(I92),"00")&"/"&YEAR(I92)) -> 04/2026 | U92: =IF(Y92="✔","OK",IF(OR(J92="",J92=0),"",TEXT(MONTH(J92+20),"00")&"/"&TEXT(YEAR(J92+20),"0000"))) -> OK | V92: =L92-M92 -> 0 | W92: F66050 | X92: 46175 | Y92: ✔ | Z92: 46195
B93: 0008A | C93: 26Z0000291 | D93: 262910021 | E93: 4300036955 | F93: 15055680 | G93: 22226 EK | H93: BEARING 22226 CCK W33 SKF | I93: 46121 | J93: 46190 | K93: EMWH | L93: 10 | M93: 10 | N93: =IF(L93=0,0,M93/L93) -> 1 | O93: 299.81 | P93: =L93*O93 -> 2998.1 | Q93: 12720 | R93: COLLECTED | S93: =IF(Y93="✔","✔ OK",IF(OR(J93="",J93=0),"TBA",INT(J93-I93))) -> ✔ OK | T93: =IF(I93="","",TEXT(MONTH(I93),"00")&"/"&YEAR(I93)) -> 04/2026 | U93: =IF(Y93="✔","OK",IF(OR(J93="",J93=0),"",TEXT(MONTH(J93+20),"00")&"/"&TEXT(YEAR(J93+20),"0000"))) -> OK | V93: =L93-M93 -> 0 | W93: F66050 | X93: 46175 | Y93: ✔ | Z93: 46195
B94: 0002A | C94: 26Z0000280 | D94: 262910001 | E94: 4300036757 | F94: 15475312 | G94: CMPT 2310TX20 | H94: SENSOR INTEGRATED CABLE; CMPT 2310TX20 | I94: 46113 | J94: 46183 | K94: EMWH | L94: 33 | M94: 33 | N94: =IF(L94=0,0,M94/L94) -> 1 | O94: 495 | P94: =L94*O94 -> 16335 | Q94: 12610 | R94: COLLECTED | S94: =IF(Y94="✔","✔ OK",IF(OR(J94="",J94=0),"TBA",INT(J94-I94))) -> ✔ OK | T94: =IF(I94="","",TEXT(MONTH(I94),"00")&"/"&YEAR(I94)) -> 04/2026 | U94: =IF(Y94="✔","OK",IF(OR(J94="",J94=0),"",TEXT(MONTH(J94+20),"00")&"/"&TEXT(YEAR(J94+20),"0000"))) -> OK | V94: =L94-M94 -> 0 | W94: F66050 | X94: 46175 | Y94: ✔ | Z94: 46195
B95: 0002B | C95: 26Z0000280 | D95: 262910001 | E95: 4300036757 | F95: 15475312 | G95: CMPT 2310TX20 | H95: SENSOR INTEGRATED CABLE; CMPT 2310TX20 | I95: 46113 | J95: 46189 | K95: EMWH | L95: 5 | M95: 5 | N95: =IF(L95=0,0,M95/L95) -> 1 | O95: 495 | P95: =L95*O95 -> 2475 | Q95: 12679 | R95: COLLECTED | S95: =IF(Y95="✔","✔ OK",IF(OR(J95="",J95=0),"TBA",INT(J95-I95))) -> ✔ OK | T95: =IF(I95="","",TEXT(MONTH(I95),"00")&"/"&YEAR(I95)) -> 04/2026 | U95: =IF(Y95="✔","OK",IF(OR(J95="",J95=0),"",TEXT(MONTH(J95+20),"00")&"/"&TEXT(YEAR(J95+20),"0000"))) -> OK | V95: =L95-M95 -> 0 | W95: F66050 | X95: 46175 | Y95: ✔ | Z95: 46195
B96: 0003B | C96: 26Z0000280 | D96: 262910001 | E96: 4300036757 | F96: 15475312 | G96: CMPT 2310TX20 | H96: SENSOR INTEGRATED CABLE; CMPT 2310TX20 | I96: 46113 | J96: 46184 | K96: EMWH | L96: 20 | M96: 20 | N96: =IF(L96=0,0,M96/L96) -> 1 | O96: 495 | P96: =L96*O96 -> 9900 | Q96: 12679 | R96: COLLECTED | S96: =IF(Y96="✔","✔ OK",IF(OR(J96="",J96=0),"TBA",INT(J96-I96))) -> ✔ OK | T96: =IF(I96="","",TEXT(MONTH(I96),"00")&"/"&YEAR(I96)) -> 04/2026 | U96: =IF(Y96="✔","OK",IF(OR(J96="",J96=0),"",TEXT(MONTH(J96+20),"00")&"/"&TEXT(YEAR(J96+20),"0000"))) -> OK | V96: =L96-M96 -> 0 | W96: F66050 | X96: 46175 | Y96: ✔ | Z96: 46195
B97: 0001A | C97: 26Z0000240 | D97: 252912296 | E97: 4300036353 | F97: 13048138 | G97: 240X270X15 HMSA10 RG | H97: LIP SEAL FKM 240MM 270MM | I97: 46100 | J97: 46169 | K97: EMWH | L97: 4 | M97: 4 | N97: =IF(L97=0,0,M97/L97) -> 1 | O97: 23.88 | P97: =L97*O97 -> 95.52 | Q97: 12643 | R97: COLLECTED | S97: =IF(Y97="✔","✔ OK",IF(OR(J97="",J97=0),"TBA",INT(J97-I97))) -> ✔ OK | T97: =IF(I97="","",TEXT(MONTH(I97),"00")&"/"&YEAR(I97)) -> 03/2026 | U97: =IF(Y97="✔","OK",IF(OR(J97="",J97=0),"",TEXT(MONTH(J97+20),"00")&"/"&TEXT(YEAR(J97+20),"0000"))) -> OK | V97: =L97-M97 -> 0 | W97: F66050 | X97: 46163 | Y97: ✔ | Z97: 46195
B98: 0003A | C98: 26Z0000240 | D98: 252912296 | E98: 4300036353 | F98: 13119342 | G98: PHF TB2517X50MM | H98: LCKG BUSH 50MM | I98: 46100 | J98: 46211 | K98: EMWH | L98: 4 | M98: 4 | N98: =IF(L98=0,0,M98/L98) -> 1 | O98: 7.95 | P98: =L98*O98 -> 31.8 | Q98: 12643 | R98: COLLECTED | S98: =IF(Y98="✔","✔ OK",IF(OR(J98="",J98=0),"TBA",INT(J98-I98))) -> 111 | T98: =IF(I98="","",TEXT(MONTH(I98),"00")&"/"&YEAR(I98)) -> 03/2026 | U98: =IF(Y98="✔","OK",IF(OR(J98="",J98=0),"",TEXT(MONTH(J98+20),"00")&"/"&TEXT(YEAR(J98+20),"0000"))) -> 07/2026 | V98: =L98-M98 -> 0 | W98: F66050 | X98: 46163 | Y98: ⚠ | AA98: Still waiting for Transporter & SKF to confirm the ETA and Material details.
B99: 0004A | C99: 26Z0000240 | D99: 252912296 | E99: 4300036353 | F99: 13120382 | G99: PHF TB4545X80MM | H99: LOCKING BUSH 80MM | I99: 46100 | J99: 46176 | K99: EMWH | L99: 1 | M99: 1 | N99: =IF(L99=0,0,M99/L99) -> 1 | O99: 49.96 | P99: =L99*O99 -> 49.96 | Q99: 12643 | R99: COLLECTED | S99: =IF(Y99="✔","✔ OK",IF(OR(J99="",J99=0),"TBA",INT(J99-I99))) -> ✔ OK | T99: =IF(I99="","",TEXT(MONTH(I99),"00")&"/"&YEAR(I99)) -> 03/2026 | U99: =IF(Y99="✔","OK",IF(OR(J99="",J99=0),"",TEXT(MONTH(J99+20),"00")&"/"&TEXT(YEAR(J99+20),"0000"))) -> OK | V99: =L99-M99 -> 0 | W99: F66050 | X99: 46163 | Y99: ✔ | Z99: 46195
B100: 0004B | C100: 26Z0000240 | D100: 252912296 | E100: 4300036353 | F100: 13120382 | G100: PHF TB4545X80MM | H100: LOCKING BUSH 80MM | I100: 46100 | J100: 46211 | K100: EMWH | L100: 3 | M100: 3 | N100: =IF(L100=0,0,M100/L100) -> 1 | O100: 49.96 | P100: =L100*O100 -> 149.88 | Q100: 12643 | R100: COLLECTED | S100: =IF(Y100="✔","✔ OK",IF(OR(J100="",J100=0),"TBA",INT(J100-I100))) -> 111 | T100: =IF(I100="","",TEXT(MONTH(I100),"00")&"/"&YEAR(I100)) -> 03/2026 | U100: =IF(Y100="✔","OK",IF(OR(J100="",J100=0),"",TEXT(MONTH(J100+20),"00")&"/"&TEXT(YEAR(J100+20),"0000"))) -> 07/2026 | V100: =L100-M100 -> 0 | W100: F66050 | X100: 46163 | Y100: ⚠ | AA100: Still waiting for Transporter & SKF to confirm the ETA and Material details.
...

Sheet 🔍 LOOKUP
A1: 🔍 QUICK ORDER LOOKUP
B3: SEARCH TYPE | C3: ← CODE / NUMBER (Type here)
B4: SKF Order | C4: 26Z0000386 | K4: =IF($C$4="","",IFERROR(VALUE($C$4),$C$4)) -> 26Z0000386
B6: 📋 ORDER IDENTIFICATION
B7: Line | C7: SKF Order | D7: TATA Order | E7: Vulcan PO | F7: Warehouse | G7: Order Date | H7: SKF Delivery Date | I7: Days
B8: =IFERROR(INDEX('📋 ORDERS'!$B$4:$B$675,MATCH($K$4,IF($B$4="SKF Order",'📋 ORDERS'!$C$4:$C$675,IF($B$4="TATA Order",'📋 ORDERS'!$D$4:$D$675,IF($B$4="Vulcan PO",'📋 ORDERS'!$E$4:$E$675,'📋 ORDERS'!$Q$4:$Q$675))),0)),"") -> 0001A | C8: =IFERROR(INDEX('📋 ORDERS'!$C$4:$C$675,MATCH($K$4,IF($B$4="SKF Order",'📋 ORDERS'!$C$4:$C$675,IF($B$4="TATA Order",'📋 ORDERS'!$D$4:$D$675,IF($B$4="Vulcan PO",'📋 ORDERS'!$E$4:$E$675,'📋 ORDERS'!$Q$4:$Q$675))),0)),"") -> 26Z0000386 | D8: =IFERROR(INDEX('📋 ORDERS'!$D$4:$D$675,MATCH($K$4,IF($B$4="SKF Order",'📋 ORDERS'!$C$4:$C$675,IF($B$4="TATA Order",'📋 ORDERS'!$D$4:$D$675,IF($B$4="Vulcan PO",'📋 ORDERS'!$E$4:$E$675,'📋 ORDERS'!$Q$4:$Q$675))),0)),"") -> 262910319A | E8: =IFERROR(INDEX('📋 ORDERS'!$E$4:$E$675,MATCH($K$4,IF($B$4="SKF Order",'📋 ORDERS'!$C$4:$C$675,IF($B$4="TATA Order",'📋 ORDERS'!$D$4:$D$675,IF($B$4="Vulcan PO",'📋 ORDERS'!$E$4:$E$675,'📋 ORDERS'!$Q$4:$Q$675))),0)),"") -> 4300037815 | F8: =IFERROR(INDEX('📋 ORDERS'!$K$4:$K$675,MATCH($K$4,IF($B$4="SKF Order",'📋 ORDERS'!$C$4:$C$675,IF($B$4="TATA Order",'📋 ORDERS'!$D$4:$D$675,IF($B$4="Vulcan PO",'📋 ORDERS'!$E$4:$E$675,'📋 ORDERS'!$Q$4:$Q$675))),0)),"") -> EMWH | G8: =IFERROR(INDEX('📋 ORDERS'!$I$4:$I$675,MATCH($K$4,IF($B$4="SKF Order",'📋 ORDERS'!$C$4:$C$675,IF($B$4="TATA Order",'📋 ORDERS'!$D$4:$D$675,IF($B$4="Vulcan PO",'📋 ORDERS'!$E$4:$E$675,'📋 ORDERS'!$Q$4:$Q$675))),0)),"") -> 46155 | H8: =IFERROR(INDEX('📋 ORDERS'!$J$4:$J$675,MATCH($K$4,IF($B$4="SKF Order",'📋 ORDERS'!$C$4:$C$675,IF($B$4="TATA Order",'📋 ORDERS'!$D$4:$D$675,IF($B$4="Vulcan PO",'📋 ORDERS'!$E$4:$E$675,'📋 ORDERS'!$Q$4:$Q$675))),0)),"") -> 46182 | I8: =IFERROR(INDEX('📋 ORDERS'!$S$4:$S$675,MATCH($K$4,IF($B$4="SKF Order",'📋 ORDERS'!$C$4:$C$675,IF($B$4="TATA Order",'📋 ORDERS'!$D$4:$D$675,IF($B$4="Vulcan PO",'📋 ORDERS'!$E$4:$E$675,'📋 ORDERS'!$Q$4:$Q$675))),0)),"") -> ✔ OK
B10: Invoice No. | C10: Status | D10: Month/Year | E10: Unit Price | F10: Qty Ordered | G10: Qty Shipped | H10: Qty Pending | I10: SKF Designation
B11: =IFERROR(INDEX('📋 ORDERS'!$Q$4:$Q$675,MATCH($K$4,IF($B$4="SKF Order",'📋 ORDERS'!$C$4:$C$675,IF($B$4="TATA Order",'📋 ORDERS'!$D$4:$D$675,IF($B$4="Vulcan PO",'📋 ORDERS'!$E$4:$E$675,'📋 ORDERS'!$Q$4:$Q$675))),0)),"") -> 12675 | C11: =IFERROR(INDEX('📋 ORDERS'!$R$4:$R$675,MATCH($K$4,IF($B$4="SKF Order",'📋 ORDERS'!$C$4:$C$675,IF($B$4="TATA Order",'📋 ORDERS'!$D$4:$D$675,IF($B$4="Vulcan PO",'📋 ORDERS'!$E$4:$E$675,'📋 ORDERS'!$Q$4:$Q$675))),0)),"") -> COLLECTED | D11: =IFERROR(INDEX('📋 ORDERS'!$T$4:$T$675,MATCH($K$4,IF($B$4="SKF Order",'📋 ORDERS'!$C$4:$C$675,IF($B$4="TATA Order",'📋 ORDERS'!$D$4:$D$675,IF($B$4="Vulcan PO",'📋 ORDERS'!$E$4:$E$675,'📋 ORDERS'!$Q$4:$Q$675))),0)),"") -> 05/2026 | E11: =IFERROR(INDEX('📋 ORDERS'!$O$4:$O$675,MATCH($K$4,IF($B$4="SKF Order",'📋 ORDERS'!$C$4:$C$675,IF($B$4="TATA Order",'📋 ORDERS'!$D$4:$D$675,IF($B$4="Vulcan PO",'📋 ORDERS'!$E$4:$E$675,'📋 ORDERS'!$Q$4:$Q$675))),0)),"") -> 678.04 | F11: =IFERROR(INDEX('📋 ORDERS'!$L$4:$L$675,MATCH($K$4,IF($B$4="SKF Order",'📋 ORDERS'!$C$4:$C$675,IF($B$4="TATA Order",'📋 ORDERS'!$D$4:$D$675,IF($B$4="Vulcan PO",'📋 ORDERS'!$E$4:$E$675,'📋 ORDERS'!$Q$4:$Q$675))),0)),"") -> 20 | G11: =IFERROR(INDEX('📋 ORDERS'!$M$4:$M$675,MATCH($K$4,IF($B$4="SKF Order",'📋 ORDERS'!$C$4:$C$675,IF($B$4="TATA Order",'📋 ORDERS'!$D$4:$D$675,IF($B$4="Vulcan PO",'📋 ORDERS'!$E$4:$E$675,'📋 ORDERS'!$Q$4:$Q$675))),0)),"") -> 20 | H11: =IFERROR(INDEX('📋 ORDERS'!$U$4:$U$675,MATCH($K$4,IF($B$4="SKF Order",'📋 ORDERS'!$C$4:$C$675,IF($B$4="TATA Order",'📋 ORDERS'!$D$4:$D$675,IF($B$4="Vulcan PO",'📋 ORDERS'!$E$4:$E$675,'📋 ORDERS'!$Q$4:$Q$675))),0)),"") -> OK | I11: =IFERROR(INDEX('📋 ORDERS'!$G$4:$G$675,MATCH($K$4,IF($B$4="SKF Order",'📋 ORDERS'!$C$4:$C$675,IF($B$4="TATA Order",'📋 ORDERS'!$D$4:$D$675,IF($B$4="Vulcan PO",'📋 ORDERS'!$E$4:$E$675,'📋 ORDERS'!$Q$4:$Q$675))),0)),"") -> 22326 CCJA/W33VA405
B12: =IFERROR(REPT("█",ROUND((IFERROR(INDEX('📋 ORDERS'!$N$4:$N$675,MATCH($K$4,IF($B$4="SKF Order",'📋 ORDERS'!$C$4:$C$675,IF($B$4="TATA Order",'📋 ORDERS'!$D$4:$D$675,IF($B$4="Vulcan PO",'📋 ORDERS'!$E$4:$E$675,'📋 ORDERS'!$Q$4:$Q$675))),0)),0))*30,0))&REPT("░",30-ROUND((IFERROR(INDEX('📋 ORDERS'!$N$4:$N$675,MATCH($K$4,IF($B$4="SKF Order",'📋 ORDERS'!$C$4:$C$675,IF($B$4="TATA Order",'📋 ORDERS'!$D$4:$D$675,IF($B$4="Vulcan PO",'📋 ORDERS'!$E$4:$E$675,'📋 ORDERS'!$Q$4:$Q$675))),0)),0))*30,0))&" "&TEXT(IFERROR(INDEX('📋 ORDERS'!$N$4:$N$675,MATCH($K$4,IF($B$4="SKF Order",'📋 ORDERS'!$C$4:$C$675,IF($B$4="TATA Order",'📋 ORDERS'!$D$4:$D$675,IF($B$4="Vulcan PO",'📋 ORDERS'!$E$4:$E$675,'📋 ORDERS'!$Q$4:$Q$675))),0)),0),"0%")&" expedido","") -> ██████████████████████████████ 100% expedido
B14: 💰 LINE TOTAL (USD)
B15: =IFERROR(INDEX('📋 ORDERS'!$P$4:$P$675,MATCH($K$4,IF($B$4="SKF Order",'📋 ORDERS'!$C$4:$C$675,IF($B$4="TATA Order",'📋 ORDERS'!$D$4:$D$675,IF($B$4="Vulcan PO",'📋 ORDERS'!$E$4:$E$675,'📋 ORDERS'!$Q$4:$Q$675))),0)),"") -> 13560.8
B17: ✔ CUSTOMER DELIVERY
B18: Delivery Status | C18: SKF Collection Date | E18: Customer Delivery Date | G18: Notes
B19: =IFERROR(INDEX('📋 ORDERS'!$X$4:$X$675,MATCH($K$4,IF($B$4="SKF Order",'📋 ORDERS'!$C$4:$C$675,IF($B$4="TATA Order",'📋 ORDERS'!$D$4:$D$675,IF($B$4="Vulcan PO",'📋 ORDERS'!$E$4:$E$675,'📋 ORDERS'!$Q$4:$Q$675))),0)),"") -> 46164 | C19: =IFERROR(INDEX('📋 ORDERS'!$W$4:$W$675,MATCH($K$4,IF($B$4="SKF Order",'📋 ORDERS'!$C$4:$C$675,IF($B$4="TATA Order",'📋 ORDERS'!$D$4:$D$675,IF($B$4="Vulcan PO",'📋 ORDERS'!$E$4:$E$675,'📋 ORDERS'!$Q$4:$Q$675))),0)),"") -> F66050 | E19: =IFERROR(INDEX('📋 ORDERS'!$Y$4:$Y$675,MATCH($K$4,IF($B$4="SKF Order",'📋 ORDERS'!$C$4:$C$675,IF($B$4="TATA Order",'📋 ORDERS'!$D$4:$D$675,IF($B$4="Vulcan PO",'📋 ORDERS'!$E$4:$E$675,'📋 ORDERS'!$Q$4:$Q$675))),0)),"") -> ✔ | G19: =IFERROR(INDEX('📋 ORDERS'!$Z$4:$Z$675,MATCH($K$4,IF($B$4="SKF Order",'📋 ORDERS'!$C$4:$C$675,IF($B$4="TATA Order",'📋 ORDERS'!$D$4:$D$675,IF($B$4="Vulcan PO",'📋 ORDERS'!$E$4:$E$675,'📋 ORDERS'!$Q$4:$Q$675))),0)),"") -> 46181
B21: 📦 ORDER ITEMS
B22: # | C22: Line | D22: SKF Designation | F22: Warehouse | G22: Qty Ord. | H22: Qty Shp. | I22: Status | J22: Days
B23: =IF(IFERROR(_xludf.aggregate(15,6,(ROW('📋 ORDERS'!$B$4:$B$675)-3)/(IF($B$4="SKF Order",'📋 ORDERS'!$C$4:$C$675,IF($B$4="TATA Order",'📋 ORDERS'!$D$4:$D$675,IF($B$4="Vulcan PO",'📋 ORDERS'!$E$4:$E$675,'📋 ORDERS'!$Q$4:$Q$675)))=$K$4),1),0)=0,"",1) | C23: =IF(IFERROR(_xludf.aggregate(15,6,(ROW('📋 ORDERS'!$B$4:$B$675)-3)/(IF($B$4="SKF Order",'📋 ORDERS'!$C$4:$C$675,IF($B$4="TATA Order",'📋 ORDERS'!$D$4:$D$675,IF($B$4="Vulcan PO",'📋 ORDERS'!$E$4:$E$675,'📋 ORDERS'!$Q$4:$Q$675)))=$K$4),1),0)=0,"",IFERROR(INDEX('📋 ORDERS'!$C$4:$C$675,IFERROR(_xludf.aggregate(15,6,(ROW('📋 ORDERS'!$B$4:$B$675)-3)/(IF($B$4="SKF Order",'📋 ORDERS'!$C$4:$C$675,IF($B$4="TATA Order",'📋 ORDERS'!$D$4:$D$675,IF($B$4="Vulcan PO",'📋 ORDERS'!$E$4:$E$675,'📋 ORDERS'!$Q$4:$Q$675)))=$K$4),1),0)),"")) | D23: =IF(IFERROR(_xludf.aggregate(15,6,(ROW('📋 ORDERS'!$B$4:$B$675)-3)/(IF($B$4="SKF Order",'📋 ORDERS'!$C$4:$C$675,IF($B$4="TATA Order",'📋 ORDERS'!$D$4:$D$675,IF($B$4="Vulcan PO",'📋 ORDERS'!$E$4:$E$675,'📋 ORDERS'!$Q$4:$Q$675)))=$K$4),1),0)=0,"",IFERROR(INDEX('📋 ORDERS'!$G$4:$G$675,IFERROR(_xludf.aggregate(15,6,(ROW('📋 ORDERS'!$B$4:$B$675)-3)/(IF($B$4="SKF Order",'📋 ORDERS'!$C$4:$C$675,IF($B$4="TATA Order",'📋 ORDERS'!$D$4:$D$675,IF($B$4="Vulcan PO",'📋 ORDERS'!$E$4:$E$675,'📋 ORDERS'!$Q$4:$Q$675)))=$K$4),1),0)),"")) | F23: =IF(IFERROR(_xludf.aggregate(15,6,(ROW('📋 ORDERS'!$B$4:$B$675)-3)/(IF($B$4="SKF Order",'📋 ORDERS'!$C$4:$C$675,IF($B$4="TATA Order",'📋 ORDERS'!$D$4:$D$675,IF($B$4="Vulcan PO",'📋 ORDERS'!$E$4:$E$675,'📋 ORDERS'!$Q$4:$Q$675)))=$K$4),1),0)=0,"",IFERROR(INDEX('📋 ORDERS'!$K$4:$K$675,IFERROR(_xludf.aggregate(15,6,(ROW('📋 ORDERS'!$B$4:$B$675)-3)/(IF($B$4="SKF Order",'📋 ORDERS'!$C$4:$C$675,IF($B$4="TATA Order",'📋 ORDERS'!$D$4:$D$675,IF($B$4="Vulcan PO",'📋 ORDERS'!$E$4:$E$675,'📋 ORDERS'!$Q$4:$Q$675)))=$K$4),1),0)),"")) | G23: =IF(IFERROR(_xludf.aggregate(15,6,(ROW('📋 ORDERS'!$B$4:$B$675)-3)/(IF($B$4="SKF Order",'📋 ORDERS'!$C$4:$C$675,IF($B$4="TATA Order",'📋 ORDERS'!$D$4:$D$675,IF($B$4="Vulcan PO",'📋 ORDERS'!$E$4:$E$675,'📋 ORDERS'!$Q$4:$Q$675)))=$K$4),1),0)=0,"",IFERROR(INDEX('📋 ORDERS'!$L$4:$L$675,IFERROR(_xludf.aggregate(15,6,(ROW('📋 ORDERS'!$B$4:$B$675)-3)/(IF($B$4="SKF Order",'📋 ORDERS'!$C$4:$C$675,IF($B$4="TATA Order",'📋 ORDERS'!$D$4:$D$675,IF($B$4="Vulcan PO",'📋 ORDERS'!$E$4:$E$675,'📋 ORDERS'!$Q$4:$Q$675)))=$K$4),1),0)),"")) | H23: =IF(IFERROR(_xludf.aggregate(15,6,(ROW('📋 ORDERS'!$B$4:$B$675)-3)/(IF($B$4="SKF Order",'📋 ORDERS'!$C$4:$C$675,IF($B$4="TATA Order",'📋 ORDERS'!$D$4:$D$675,IF($B$4="Vulcan PO",'📋 ORDERS'!$E$4:$E$675,'📋 ORDERS'!$Q$4:$Q$675)))=$K$4),1),0)=0,"",IFERROR(INDEX('📋 ORDERS'!$M$4:$M$675,IFERROR(_xludf.aggregate(15,6,(ROW('📋 ORDERS'!$B$4:$B$675)-3)/(IF($B$4="SKF Order",'📋 ORDERS'!$C$4:$C$675,IF($B$4="TATA Order",'📋 ORDERS'!$D$4:$D$675,IF($B$4="Vulcan PO",'📋 ORDERS'!$E$4:$E$675,'📋 ORDERS'!$Q$4:$Q$675)))=$K$4),1),0)),"")) | I23: =IF(IFERROR(_xludf.aggregate(15,6,(ROW('📋 ORDERS'!$B$4:$B$675)-3)/(IF($B$4="SKF Order",'📋 ORDERS'!$C$4:$C$675,IF($B$4="TATA Order",'📋 ORDERS'!$D$4:$D$675,IF($B$4="Vulcan PO",'📋 ORDERS'!$E$4:$E$675,'📋 ORDERS'!$Q$4:$Q$675)))=$K$4),1),0)=0,"",IFERROR(INDEX('📋 ORDERS'!$R$4:$R$675,IFERROR(_xludf.aggregate(15,6,(ROW('📋 ORDERS'!$B$4:$B$675)-3)/(IF($B$4="SKF Order",'📋 ORDERS'!$C$4:$C$675,IF($B$4="TATA Order",'📋 ORDERS'!$D$4:$D$675,IF($B$4="Vulcan PO",'📋 ORDERS'!$E$4:$E$675,'📋 ORDERS'!$Q$4:$Q$675)))=$K$4),1),0)),"")) | J23: =IF(IFERROR(_xludf.aggregate(15,6,(ROW('📋 ORDERS'!$B$4:$B$675)-3)/(IF($B$4="SKF Order",'📋 ORDERS'!$C$4:$C$675,IF($B$4="TATA Order",'📋 ORDERS'!$D$4:$D$675,IF($B$4="Vulcan PO",'📋 ORDERS'!$E$4:$E$675,'📋 ORDERS'!$Q$4:$Q$675)))=$K$4),1),0)=0,"",IFERROR(INDEX('📋 ORDERS'!$S$4:$S$675,IFERROR(_xludf.aggregate(15,6,(ROW('📋 ORDERS'!$B$4:$B$675)-3)/(IF($B$4="SKF Order",'📋 ORDERS'!$C$4:$C$675,IF($B$4="TATA Order",'📋 ORDERS'!$D$4:$D$675,IF($B$4="Vulcan PO",'📋 ORDERS'!$E$4:$E$675,'📋 ORDERS'!$Q$4:$Q$675)))=$K$4),1),0)),""))
B24: =IF(IFERROR(_xludf.aggregate(15,6,(ROW('📋 ORDERS'!$B$4:$B$675)-3)/(IF($B$4="SKF Order",'📋 ORDERS'!$C$4:$C$675,IF($B$4="TATA Order",'📋 ORDERS'!$D$4:$D$675,IF($B$4="Vulcan PO",'📋 ORDERS'!$E$4:$E$675,'📋 ORDERS'!$Q$4:$Q$675)))=$K$4),2),0)=0,"",2) | C24: =IF(IFERROR(_xludf.aggregate(15,6,(ROW('📋 ORDERS'!$B$4:$B$675)-3)/(IF($B$4="SKF Order",'📋 ORDERS'!$C$4:$C$675,IF($B$4="TATA Order",'📋 ORDERS'!$D$4:$D$675,IF($B$4="Vulcan PO",'📋 ORDERS'!$E$4:$E$675,'📋 ORDERS'!$Q$4:$Q$675)))=$K$4),2),0)=0,"",IFERROR(INDEX('📋 ORDERS'!$C$4:$C$675,IFERROR(_xludf.aggregate(15,6,(ROW('📋 ORDERS'!$B$4:$B$675)-3)/(IF($B$4="SKF Order",'📋 ORDERS'!$C$4:$C$675,IF($B$4="TATA Order",'📋 ORDERS'!$D$4:$D$675,IF($B$4="Vulcan PO",'📋 ORDERS'!$E$4:$E$675,'📋 ORDERS'!$Q$4:$Q$675)))=$K$4),2),0)),"")) | D24: =IF(IFERROR(_xludf.aggregate(15,6,(ROW('📋 ORDERS'!$B$4:$B$675)-3)/(IF($B$4="SKF Order",'📋 ORDERS'!$C$4:$C$675,IF($B$4="TATA Order",'📋 ORDERS'!$D$4:$D$675,IF($B$4="Vulcan PO",'📋 ORDERS'!$E$4:$E$675,'📋 ORDERS'!$Q$4:$Q$675)))=$K$4),2),0)=0,"",IFERROR(INDEX('📋 ORDERS'!$G$4:$G$675,IFERROR(_xludf.aggregate(15,6,(ROW('📋 ORDERS'!$B$4:$B$675)-3)/(IF($B$4="SKF Order",'📋 ORDERS'!$C$4:$C$675,IF($B$4="TATA Order",'📋 ORDERS'!$D$4:$D$675,IF($B$4="Vulcan PO",'📋 ORDERS'!$E$4:$E$675,'📋 ORDERS'!$Q$4:$Q$675)))=$K$4),2),0)),"")) | F24: =IF(IFERROR(_xludf.aggregate(15,6,(ROW('📋 ORDERS'!$B$4:$B$675)-3)/(IF($B$4="SKF Order",'📋 ORDERS'!$C$4:$C$675,IF($B$4="TATA Order",'📋 ORDERS'!$D$4:$D$675,IF($B$4="Vulcan PO",'📋 ORDERS'!$E$4:$E$675,'📋 ORDERS'!$Q$4:$Q$675)))=$K$4),2),0)=0,"",IFERROR(INDEX('📋 ORDERS'!$K$4:$K$675,IFERROR(_xludf.aggregate(15,6,(ROW('📋 ORDERS'!$B$4:$B$675)-3)/(IF($B$4="SKF Order",'📋 ORDERS'!$C$4:$C$675,IF($B$4="TATA Order",'📋 ORDERS'!$D$4:$D$675,IF($B$4="Vulcan PO",'📋 ORDERS'!$E$4:$E$675,'📋 ORDERS'!$Q$4:$Q$675)))=$K$4),2),0)),"")) | G24: =IF(IFERROR(_xludf.aggregate(15,6,(ROW('📋 ORDERS'!$B$4:$B$675)-3)/(IF($B$4="SKF Order",'📋 ORDERS'!$C$4:$C$675,IF($B$4="TATA Order",'📋 ORDERS'!$D$4:$D$675,IF($B$4="Vulcan PO",'📋 ORDERS'!$E$4:$E$675,'📋 ORDERS'!$Q$4:$Q$675)))=$K$4),2),0)=0,"",IFERROR(INDEX('📋 ORDERS'!$L$4:$L$675,IFERROR(_xludf.aggregate(15,6,(ROW('📋 ORDERS'!$B$4:$B$675)-3)/(IF($B$4="SKF Order",'📋 ORDERS'!$C$4:$C$675,IF($B$4="TATA Order",'📋 ORDERS'!$D$4:$D$675,IF($B$4="Vulcan PO",'📋 ORDERS'!$E$4:$E$675,'📋 ORDERS'!$Q$4:$Q$675)))=$K$4),2),0)),"")) | H24: =IF(IFERROR(_xludf.aggregate(15,6,(ROW('📋 ORDERS'!$B$4:$B$675)-3)/(IF($B$4="SKF Order",'📋 ORDERS'!$C$4:$C$675,IF($B$4="TATA Order",'📋 ORDERS'!$D$4:$D$675,IF($B$4="Vulcan PO",'📋 ORDERS'!$E$4:$E$675,'📋 ORDERS'!$Q$4:$Q$675)))=$K$4),2),0)=0,"",IFERROR(INDEX('📋 ORDERS'!$M$4:$M$675,IFERROR(_xludf.aggregate(15,6,(ROW('📋 ORDERS'!$B$4:$B$675)-3)/(IF($B$4="SKF Order",'📋 ORDERS'!$C$4:$C$675,IF($B$4="TATA Order",'📋 ORDERS'!$D$4:$D$675,IF($B$4="Vulcan PO",'📋 ORDERS'!$E$4:$E$675,'📋 ORDERS'!$Q$4:$Q$675)))=$K$4),2),0)),"")) | I24: =IF(IFERROR(_xludf.aggregate(15,6,(ROW('📋 ORDERS'!$B$4:$B$675)-3)/(IF($B$4="SKF Order",'📋 ORDERS'!$C$4:$C$675,IF($B$4="TATA Order",'📋 ORDERS'!$D$4:$D$675,IF($B$4="Vulcan PO",'📋 ORDERS'!$E$4:$E$675,'📋 ORDERS'!$Q$4:$Q$675)))=$K$4),2),0)=0,"",IFERROR(INDEX('📋 ORDERS'!$R$4:$R$675,IFERROR(_xludf.aggregate(15,6,(ROW('📋 ORDERS'!$B$4:$B$675)-3)/(IF($B$4="SKF Order",'📋 ORDERS'!$C$4:$C$675,IF($B$4="TATA Order",'📋 ORDERS'!$D$4:$D$675,IF($B$4="Vulcan PO",'📋 ORDERS'!$E$4:$E$675,'📋 ORDERS'!$Q$4:$Q$675)))=$K$4),2),0)),"")) | J24: =IF(IFERROR(_xludf.aggregate(15,6,(ROW('📋 ORDERS'!$B$4:$B$675)-3)/(IF($B$4="SKF Order",'📋 ORDERS'!$C$4:$C$675,IF($B$4="TATA Order",'📋 ORDERS'!$D$4:$D$675,IF($B$4="Vulcan PO",'📋 ORDERS'!$E$4:$E$675,'📋 ORDERS'!$Q$4:$Q$675)))=$K$4),2),0)=0,"",IFERROR(INDEX('📋 ORDERS'!$S$4:$S$675,IFERROR(_xludf.aggregate(15,6,(ROW('📋 ORDERS'!$B$4:$B$675)-3)/(IF($B$4="SKF Order",'📋 ORDERS'!$C$4:$C$675,IF($B$4="TATA Order",'📋 ORDERS'!$D$4:$D$675,IF($B$4="Vulcan PO",'📋 ORDERS'!$E$4:$E$675,'📋 ORDERS'!$Q$4:$Q$675)))=$K$4),2),0)),""))
B25: =IF(IFERROR(_xludf.aggregate(15,6,(ROW('📋 ORDERS'!$B$4:$B$675)-3)/(IF($B$4="SKF Order",'📋 ORDERS'!$C$4:$C$675,IF($B$4="TATA Order",'📋 ORDERS'!$D$4:$D$675,IF($B$4="Vulcan PO",'📋 ORDERS'!$E$4:$E$675,'📋 ORDERS'!$Q$4:$Q$675)))=$K$4),3),0)=0,"",3) | C25: =IF(IFERROR(_xludf.aggregate(15,6,(ROW('📋 ORDERS'!$B$4:$B$675)-3)/(IF($B$4="SKF Order",'📋 ORDERS'!$C$4:$C$675,IF($B$4="TATA Order",'📋 ORDERS'!$D$4:$D$675,IF($B$4="Vulcan PO",'📋 ORDERS'!$E$4:$E$675,'📋 ORDERS'!$Q$4:$Q$675)))=$K$4),3),0)=0,"",IFERROR(INDEX('📋 ORDERS'!$C$4:$C$675,IFERROR(_xludf.aggregate(15,6,(ROW('📋 ORDERS'!$B$4:$B$675)-3)/(IF($B$4="SKF Order",'📋 ORDERS'!$C$4:$C$675,IF($B$4="TATA Order",'📋 ORDERS'!$D$4:$D$675,IF($B$4="Vulcan PO",'📋 ORDERS'!$E$4:$E$675,'📋 ORDERS'!$Q$4:$Q$675)))=$K$4),3),0)),"")) | D25: =IF(IFERROR(_xludf.aggregate(15,6,(ROW('📋 ORDERS'!$B$4:$B$675)-3)/(IF($B$4="SKF Order",'📋 ORDERS'!$C$4:$C$675,IF($B$4="TATA Order",'📋 ORDERS'!$D$4:$D$675,IF($B$4="Vulcan PO",'📋 ORDERS'!$E$4:$E$675,'📋 ORDERS'!$Q$4:$Q$675)))=$K$4),3),0)=0,"",IFERROR(INDEX('📋 ORDERS'!$G$4:$G$675,IFERROR(_xludf.aggregate(15,6,(ROW('📋 ORDERS'!$B$4:$B$675)-3)/(IF($B$4="SKF Order",'📋 ORDERS'!$C$4:$C$675,IF($B$4="TATA Order",'📋 ORDERS'!$D$4:$D$675,IF($B$4="Vulcan PO",'📋 ORDERS'!$E$4:$E$675,'📋 ORDERS'!$Q$4:$Q$675)))=$K$4),3),0)),"")) | F25: =IF(IFERROR(_xludf.aggregate(15,6,(ROW('📋 ORDERS'!$B$4:$B$675)-3)/(IF($B$4="SKF Order",'📋 ORDERS'!$C$4:$C$675,IF($B$4="TATA Order",'📋 ORDERS'!$D$4:$D$675,IF($B$4="Vulcan PO",'📋 ORDERS'!$E$4:$E$675,'📋 ORDERS'!$Q$4:$Q$675)))=$K$4),3),0)=0,"",IFERROR(INDEX('📋 ORDERS'!$K$4:$K$675,IFERROR(_xludf.aggregate(15,6,(ROW('📋 ORDERS'!$B$4:$B$675)-3)/(IF($B$4="SKF Order",'📋 ORDERS'!$C$4:$C$675,IF($B$4="TATA Order",'📋 ORDERS'!$D$4:$D$675,IF($B$4="Vulcan PO",'📋 ORDERS'!$E$4:$E$675,'📋 ORDERS'!$Q$4:$Q$675)))=$K$4),3),0)),"")) | G25: =IF(IFERROR(_xludf.aggregate(15,6,(ROW('📋 ORDERS'!$B$4:$B$675)-3)/(IF($B$4="SKF Order",'📋 ORDERS'!$C$4:$C$675,IF($B$4="TATA Order",'📋 ORDERS'!$D$4:$D$675,IF($B$4="Vulcan PO",'📋 ORDERS'!$E$4:$E$675,'📋 ORDERS'!$Q$4:$Q$675)))=$K$4),3),0)=0,"",IFERROR(INDEX('📋 ORDERS'!$L$4:$L$675,IFERROR(_xludf.aggregate(15,6,(ROW('📋 ORDERS'!$B$4:$B$675)-3)/(IF($B$4="SKF Order",'📋 ORDERS'!$C$4:$C$675,IF($B$4="TATA Order",'📋 ORDERS'!$D$4:$D$675,IF($B$4="Vulcan PO",'📋 ORDERS'!$E$4:$E$675,'📋 ORDERS'!$Q$4:$Q$675)))=$K$4),3),0)),"")) | H25: =IF(IFERROR(_xludf.aggregate(15,6,(ROW('📋 ORDERS'!$B$4:$B$675)-3)/(IF($B$4="SKF Order",'📋 ORDERS'!$C$4:$C$675,IF($B$4="TATA Order",'📋 ORDERS'!$D$4:$D$675,IF($B$4="Vulcan PO",'📋 ORDERS'!$E$4:$E$675,'📋 ORDERS'!$Q$4:$Q$675)))=$K$4),3),0)=0,"",IFERROR(INDEX('📋 ORDERS'!$M$4:$M$675,IFERROR(_xludf.aggregate(15,6,(ROW('📋 ORDERS'!$B$4:$B$675)-3)/(IF($B$4="SKF Order",'📋 ORDERS'!$C$4:$C$675,IF($B$4="TATA Order",'📋 ORDERS'!$D$4:$D$675,IF($B$4="Vulcan PO",'📋 ORDERS'!$E$4:$E$675,'📋 ORDERS'!$Q$4:$Q$675)))=$K$4),3),0)),"")) | I25: =IF(IFERROR(_xludf.aggregate(15,6,(ROW('📋 ORDERS'!$B$4:$B$675)-3)/(IF($B$4="SKF Order",'📋 ORDERS'!$C$4:$C$675,IF($B$4="TATA Order",'📋 ORDERS'!$D$4:$D$675,IF($B$4="Vulcan PO",'📋 ORDERS'!$E$4:$E$675,'📋 ORDERS'!$Q$4:$Q$675)))=$K$4),3),0)=0,"",IFERROR(INDEX('📋 ORDERS'!$R$4:$R$675,IFERROR(_xludf.aggregate(15,6,(ROW('📋 ORDERS'!$B$4:$B$675)-3)/(IF($B$4="SKF Order",'📋 ORDERS'!$C$4:$C$675,IF($B$4="TATA Order",'📋 ORDERS'!$D$4:$D$675,IF($B$4="Vulcan PO",'📋 ORDERS'!$E$4:$E$675,'📋 ORDERS'!$Q$4:$Q$675)))=$K$4),3),0)),"")) | J25: =IF(IFERROR(_xludf.aggregate(15,6,(ROW('📋 ORDERS'!$B$4:$B$675)-3)/(IF($B$4="SKF Order",'📋 ORDERS'!$C$4:$C$675,IF($B$4="TATA Order",'📋 ORDERS'!$D$4:$D$675,IF($B$4="Vulcan PO",'📋 ORDERS'!$E$4:$E$675,'📋 ORDERS'!$Q$4:$Q$675)))=$K$4),3),0)=0,"",IFERROR(INDEX('📋 ORDERS'!$S$4:$S$675,IFERROR(_xludf.aggregate(15,6,(ROW('📋 ORDERS'!$B$4:$B$675)-3)/(IF($B$4="SKF Order",'📋 ORDERS'!$C$4:$C$675,IF($B$4="TATA Order",'📋 ORDERS'!$D$4:$D$675,IF($B$4="Vulcan PO",'📋 ORDERS'!$E$4:$E$675,'📋 ORDERS'!$Q$4:$Q$675)))=$K$4),3),0)),""))
B26: =IF(IFERROR(_xludf.aggregate(15,6,(ROW('📋 ORDERS'!$B$4:$B$675)-3)/(IF($B$4="SKF Order",'📋 ORDERS'!$C$4:$C$675,IF($B$4="TATA Order",'📋 ORDERS'!$D$4:$D$675,IF($B$4="Vulcan PO",'📋 ORDERS'!$E$4:$E$675,'📋 ORDERS'!$Q$4:$Q$675)))=$K$4),4),0)=0,"",4) | C26: =IF(IFERROR(_xludf.aggregate(15,6,(ROW('📋 ORDERS'!$B$4:$B$675)-3)/(IF($B$4="SKF Order",'📋 ORDERS'!$C$4:$C$675,IF($B$4="TATA Order",'📋 ORDERS'!$D$4:$D$675,IF($B$4="Vulcan PO",'📋 ORDERS'!$E$4:$E$675,'📋 ORDERS'!$Q$4:$Q$675)))=$K$4),4),0)=0,"",IFERROR(INDEX('📋 ORDERS'!$C$4:$C$675,IFERROR(_xludf.aggregate(15,6,(ROW('📋 ORDERS'!$B$4:$B$675)-3)/(IF($B$4="SKF Order",'📋 ORDERS'!$C$4:$C$675,IF($B$4="TATA Order",'📋 ORDERS'!$D$4:$D$675,IF($B$4="Vulcan PO",'📋 ORDERS'!$E$4:$E$675,'📋 ORDERS'!$Q$4:$Q$675)))=$K$4),4),0)),"")) | D26: =IF(IFERROR(_xludf.aggregate(15,6,(ROW('📋 ORDERS'!$B$4:$B$675)-3)/(IF($B$4="SKF Order",'📋 ORDERS'!$C$4:$C$675,IF($B$4="TATA Order",'📋 ORDERS'!$D$4:$D$675,IF($B$4="Vulcan PO",'📋 ORDERS'!$E$4:$E$675,'📋 ORDERS'!$Q$4:$Q$675)))=$K$4),4),0)=0,"",IFERROR(INDEX('📋 ORDERS'!$G$4:$G$675,IFERROR(_xludf.aggregate(15,6,(ROW('📋 ORDERS'!$B$4:$B$675)-3)/(IF($B$4="SKF Order",'📋 ORDERS'!$C$4:$C$675,IF($B$4="TATA Order",'📋 ORDERS'!$D$4:$D$675,IF($B$4="Vulcan PO",'📋 ORDERS'!$E$4:$E$675,'📋 ORDERS'!$Q$4:$Q$675)))=$K$4),4),0)),"")) | F26: =IF(IFERROR(_xludf.aggregate(15,6,(ROW('📋 ORDERS'!$B$4:$B$675)-3)/(IF($B$4="SKF Order",'📋 ORDERS'!$C$4:$C$675,IF($B$4="TATA Order",'📋 ORDERS'!$D$4:$D$675,IF($B$4="Vulcan PO",'📋 ORDERS'!$E$4:$E$675,'📋 ORDERS'!$Q$4:$Q$675)))=$K$4),4),0)=0,"",IFERROR(INDEX('📋 ORDERS'!$K$4:$K$675,IFERROR(_xludf.aggregate(15,6,(ROW('📋 ORDERS'!$B$4:$B$675)-3)/(IF($B$4="SKF Order",'📋 ORDERS'!$C$4:$C$675,IF($B$4="TATA Order",'📋 ORDERS'!$D$4:$D$675,IF($B$4="Vulcan PO",'📋 ORDERS'!$E$4:$E$675,'📋 ORDERS'!$Q$4:$Q$675)))=$K$4),4),0)),"")) | G26: =IF(IFERROR(_xludf.aggregate(15,6,(ROW('📋 ORDERS'!$B$4:$B$675)-3)/(IF($B$4="SKF Order",'📋 ORDERS'!$C$4:$C$675,IF($B$4="TATA Order",'📋 ORDERS'!$D$4:$D$675,IF($B$4="Vulcan PO",'📋 ORDERS'!$E$4:$E$675,'📋 ORDERS'!$Q$4:$Q$675)))=$K$4),4),0)=0,"",IFERROR(INDEX('📋 ORDERS'!$L$4:$L$675,IFERROR(_xludf.aggregate(15,6,(ROW('📋 ORDERS'!$B$4:$B$675)-3)/(IF($B$4="SKF Order",'📋 ORDERS'!$C$4:$C$675,IF($B$4="TATA Order",'📋 ORDERS'!$D$4:$D$675,IF($B$4="Vulcan PO",'📋 ORDERS'!$E$4:$E$675,'📋 ORDERS'!$Q$4:$Q$675)))=$K$4),4),0)),"")) | H26: =IF(IFERROR(_xludf.aggregate(15,6,(ROW('📋 ORDERS'!$B$4:$B$675)-3)/(IF($B$4="SKF Order",'📋 ORDERS'!$C$4:$C$675,IF($B$4="TATA Order",'📋 ORDERS'!$D$4:$D$675,IF($B$4="Vulcan PO",'📋 ORDERS'!$E$4:$E$675,'📋 ORDERS'!$Q$4:$Q$675)))=$K$4),4),0)=0,"",IFERROR(INDEX('📋 ORDERS'!$M$4:$M$675,IFERROR(_xludf.aggregate(15,6,(ROW('📋 ORDERS'!$B$4:$B$675)-3)/(IF($B$4="SKF Order",'📋 ORDERS'!$C$4:$C$675,IF($B$4="TATA Order",'📋 ORDERS'!$D$4:$D$675,IF($B$4="Vulcan PO",'📋 ORDERS'!$E$4:$E$675,'📋 ORDERS'!$Q$4:$Q$675)))=$K$4),4),0)),"")) | I26: =IF(IFERROR(_xludf.aggregate(15,6,(ROW('📋 ORDERS'!$B$4:$B$675)-3)/(IF($B$4="SKF Order",'📋 ORDERS'!$C$4:$C$675,IF($B$4="TATA Order",'📋 ORDERS'!$D$4:$D$675,IF($B$4="Vulcan PO",'📋 ORDERS'!$E$4:$E$675,'📋 ORDERS'!$Q$4:$Q$675)))=$K$4),4),0)=0,"",IFERROR(INDEX('📋 ORDERS'!$R$4:$R$675,IFERROR(_xludf.aggregate(15,6,(ROW('📋 ORDERS'!$B$4:$B$675)-3)/(IF($B$4="SKF Order",'📋 ORDERS'!$C$4:$C$675,IF($B$4="TATA Order",'📋 ORDERS'!$D$4:$D$675,IF($B$4="Vulcan PO",'📋 ORDERS'!$E$4:$E$675,'📋 ORDERS'!$Q$4:$Q$675)))=$K$4),4),0)),"")) | J26: =IF(IFERROR(_xludf.aggregate(15,6,(ROW('📋 ORDERS'!$B$4:$B$675)-3)/(IF($B$4="SKF Order",'📋 ORDERS'!$C$4:$C$675,IF($B$4="TATA Order",'📋 ORDERS'!$D$4:$D$675,IF($B$4="Vulcan PO",'📋 ORDERS'!$E$4:$E$675,'📋 ORDERS'!$Q$4:$Q$675)))=$K$4),4),0)=0,"",IFERROR(INDEX('📋 ORDERS'!$S$4:$S$675,IFERROR(_xludf.aggregate(15,6,(ROW('📋 ORDERS'!$B$4:$B$675)-3)/(IF($B$4="SKF Order",'📋 ORDERS'!$C$4:$C$675,IF($B$4="TATA Order",'📋 ORDERS'!$D$4:$D$675,IF($B$4="Vulcan PO",'📋 ORDERS'!$E$4:$E$675,'📋 ORDERS'!$Q$4:$Q$675)))=$K$4),4),0)),""))
B27: =IF(IFERROR(_xludf.aggregate(15,6,(ROW('📋 ORDERS'!$B$4:$B$675)-3)/(IF($B$4="SKF Order",'📋 ORDERS'!$C$4:$C$675,IF($B$4="TATA Order",'📋 ORDERS'!$D$4:$D$675,IF($B$4="Vulcan PO",'📋 ORDERS'!$E$4:$E$675,'📋 ORDERS'!$Q$4:$Q$675)))=$K$4),5),0)=0,"",5) | C27: =IF(IFERROR(_xludf.aggregate(15,6,(ROW('📋 ORDERS'!$B$4:$B$675)-3)/(IF($B$4="SKF Order",'📋 ORDERS'!$C$4:$C$675,IF($B$4="TATA Order",'📋 ORDERS'!$D$4:$D$675,IF($B$4="Vulcan PO",'📋 ORDERS'!$E$4:$E$675,'📋 ORDERS'!$Q$4:$Q$675)))=$K$4),5),0)=0,"",IFERROR(INDEX('📋 ORDERS'!$C$4:$C$675,IFERROR(_xludf.aggregate(15,6,(ROW('📋 ORDERS'!$B$4:$B$675)-3)/(IF($B$4="SKF Order",'📋 ORDERS'!$C$4:$C$675,IF($B$4="TATA Order",'📋 ORDERS'!$D$4:$D$675,IF($B$4="Vulcan PO",'📋 ORDERS'!$E$4:$E$675,'📋 ORDERS'!$Q$4:$Q$675)))=$K$4),5),0)),"")) | D27: =IF(IFERROR(_xludf.aggregate(15,6,(ROW('📋 ORDERS'!$B$4:$B$675)-3)/(IF($B$4="SKF Order",'📋 ORDERS'!$C$4:$C$675,IF($B$4="TATA Order",'📋 ORDERS'!$D$4:$D$675,IF($B$4="Vulcan PO",'📋 ORDERS'!$E$4:$E$675,'📋 ORDERS'!$Q$4:$Q$675)))=$K$4),5),0)=0,"",IFERROR(INDEX('📋 ORDERS'!$G$4:$G$675,IFERROR(_xludf.aggregate(15,6,(ROW('📋 ORDERS'!$B$4:$B$675)-3)/(IF($B$4="SKF Order",'📋 ORDERS'!$C$4:$C$675,IF($B$4="TATA Order",'📋 ORDERS'!$D$4:$D$675,IF($B$4="Vulcan PO",'📋 ORDERS'!$E$4:$E$675,'📋 ORDERS'!$Q$4:$Q$675)))=$K$4),5),0)),"")) | F27: =IF(IFERROR(_xludf.aggregate(15,6,(ROW('📋 ORDERS'!$B$4:$B$675)-3)/(IF($B$4="SKF Order",'📋 ORDERS'!$C$4:$C$675,IF($B$4="TATA Order",'📋 ORDERS'!$D$4:$D$675,IF($B$4="Vulcan PO",'📋 ORDERS'!$E$4:$E$675,'📋 ORDERS'!$Q$4:$Q$675)))=$K$4),5),0)=0,"",IFERROR(INDEX('📋 ORDERS'!$K$4:$K$675,IFERROR(_xludf.aggregate(15,6,(ROW('📋 ORDERS'!$B$4:$B$675)-3)/(IF($B$4="SKF Order",'📋 ORDERS'!$C$4:$C$675,IF($B$4="TATA Order",'📋 ORDERS'!$D$4:$D$675,IF($B$4="Vulcan PO",'📋 ORDERS'!$E$4:$E$675,'📋 ORDERS'!$Q$4:$Q$675)))=$K$4),5),0)),"")) | G27: =IF(IFERROR(_xludf.aggregate(15,6,(ROW('📋 ORDERS'!$B$4:$B$675)-3)/(IF($B$4="SKF Order",'📋 ORDERS'!$C$4:$C$675,IF($B$4="TATA Order",'📋 ORDERS'!$D$4:$D$675,IF($B$4="Vulcan PO",'📋 ORDERS'!$E$4:$E$675,'📋 ORDERS'!$Q$4:$Q$675)))=$K$4),5),0)=0,"",IFERROR(INDEX('📋 ORDERS'!$L$4:$L$675,IFERROR(_xludf.aggregate(15,6,(ROW('📋 ORDERS'!$B$4:$B$675)-3)/(IF($B$4="SKF Order",'📋 ORDERS'!$C$4:$C$675,IF($B$4="TATA Order",'📋 ORDERS'!$D$4:$D$675,IF($B$4="Vulcan PO",'📋 ORDERS'!$E$4:$E$675,'📋 ORDERS'!$Q$4:$Q$675)))=$K$4),5),0)),"")) | H27: =IF(IFERROR(_xludf.aggregate(15,6,(ROW('📋 ORDERS'!$B$4:$B$675)-3)/(IF($B$4="SKF Order",'📋 ORDERS'!$C$4:$C$675,IF($B$4="TATA Order",'📋 ORDERS'!$D$4:$D$675,IF($B$4="Vulcan PO",'📋 ORDERS'!$E$4:$E$675,'📋 ORDERS'!$Q$4:$Q$675)))=$K$4),5),0)=0,"",IFERROR(INDEX('📋 ORDERS'!$M$4:$M$675,IFERROR(_xludf.aggregate(15,6,(ROW('📋 ORDERS'!$B$4:$B$675)-3)/(IF($B$4="SKF Order",'📋 ORDERS'!$C$4:$C$675,IF($B$4="TATA Order",'📋 ORDERS'!$D$4:$D$675,IF($B$4="Vulcan PO",'📋 ORDERS'!$E$4:$E$675,'📋 ORDERS'!$Q$4:$Q$675)))=$K$4),5),0)),"")) | I27: =IF(IFERROR(_xludf.aggregate(15,6,(ROW('📋 ORDERS'!$B$4:$B$675)-3)/(IF($B$4="SKF Order",'📋 ORDERS'!$C$4:$C$675,IF($B$4="TATA Order",'📋 ORDERS'!$D$4:$D$675,IF($B$4="Vulcan PO",'📋 ORDERS'!$E$4:$E$675,'📋 ORDERS'!$Q$4:$Q$675)))=$K$4),5),0)=0,"",IFERROR(INDEX('📋 ORDERS'!$R$4:$R$675,IFERROR(_xludf.aggregate(15,6,(ROW('📋 ORDERS'!$B$4:$B$675)-3)/(IF($B$4="SKF Order",'📋 ORDERS'!$C$4:$C$675,IF($B$4="TATA Order",'📋 ORDERS'!$D$4:$D$675,IF($B$4="Vulcan PO",'📋 ORDERS'!$E$4:$E$675,'📋 ORDERS'!$Q$4:$Q$675)))=$K$4),5),0)),"")) | J27: =IF(IFERROR(_xludf.aggregate(15,6,(ROW('📋 ORDERS'!$B$4:$B$675)-3)/(IF($B$4="SKF Order",'📋 ORDERS'!$C$4:$C$675,IF($B$4="TATA Order",'📋 ORDERS'!$D$4:$D$675,IF($B$4="Vulcan PO",'📋 ORDERS'!$E$4:$E$675,'📋 ORDERS'!$Q$4:$Q$675)))=$K$4),5),0)=0,"",IFERROR(INDEX('📋 ORDERS'!$S$4:$S$675,IFERROR(_xludf.aggregate(15,6,(ROW('📋 ORDERS'!$B$4:$B$675)-3)/(IF($B$4="SKF Order",'📋 ORDERS'!$C$4:$C$675,IF($B$4="TATA Order",'📋 ORDERS'!$D$4:$D$675,IF($B$4="Vulcan PO",'📋 ORDERS'!$E$4:$E$675,'📋 ORDERS'!$Q$4:$Q$675)))=$K$4),5),0)),""))
B28: =IF(IFERROR(_xludf.aggregate(15,6,(ROW('📋 ORDERS'!$B$4:$B$675)-3)/(IF($B$4="SKF Order",'📋 ORDERS'!$C$4:$C$675,IF($B$4="TATA Order",'📋 ORDERS'!$D$4:$D$675,IF($B$4="Vulcan PO",'📋 ORDERS'!$E$4:$E$675,'📋 ORDERS'!$Q$4:$Q$675)))=$K$4),6),0)=0,"",6) | C28: =IF(IFERROR(_xludf.aggregate(15,6,(ROW('📋 ORDERS'!$B$4:$B$675)-3)/(IF($B$4="SKF Order",'📋 ORDERS'!$C$4:$C$675,IF($B$4="TATA Order",'📋 ORDERS'!$D$4:$D$675,IF($B$4="Vulcan PO",'📋 ORDERS'!$E$4:$E$675,'📋 ORDERS'!$Q$4:$Q$675)))=$K$4),6),0)=0,"",IFERROR(INDEX('📋 ORDERS'!$C$4:$C$675,IFERROR(_xludf.aggregate(15,6,(ROW('📋 ORDERS'!$B$4:$B$675)-3)/(IF($B$4="SKF Order",'📋 ORDERS'!$C$4:$C$675,IF($B$4="TATA Order",'📋 ORDERS'!$D$4:$D$675,IF($B$4="Vulcan PO",'📋 ORDERS'!$E$4:$E$675,'📋 ORDERS'!$Q$4:$Q$675)))=$K$4),6),0)),"")) | D28: =IF(IFERROR(_xludf.aggregate(15,6,(ROW('📋 ORDERS'!$B$4:$B$675)-3)/(IF($B$4="SKF Order",'📋 ORDERS'!$C$4:$C$675,IF($B$4="TATA Order",'📋 ORDERS'!$D$4:$D$675,IF($B$4="Vulcan PO",'📋 ORDERS'!$E$4:$E$675,'📋 ORDERS'!$Q$4:$Q$675)))=$K$4),6),0)=0,"",IFERROR(INDEX('📋 ORDERS'!$G$4:$G$675,IFERROR(_xludf.aggregate(15,6,(ROW('📋 ORDERS'!$B$4:$B$675)-3)/(IF($B$4="SKF Order",'📋 ORDERS'!$C$4:$C$675,IF($B$4="TATA Order",'📋 ORDERS'!$D$4:$D$675,IF($B$4="Vulcan PO",'📋 ORDERS'!$E$4:$E$675,'📋 ORDERS'!$Q$4:$Q$675)))=$K$4),6),0)),"")) | F28: =IF(IFERROR(_xludf.aggregate(15,6,(ROW('📋 ORDERS'!$B$4:$B$675)-3)/(IF($B$4="SKF Order",'📋 ORDERS'!$C$4:$C$675,IF($B$4="TATA Order",'📋 ORDERS'!$D$4:$D$675,IF($B$4="Vulcan PO",'📋 ORDERS'!$E$4:$E$675,'📋 ORDERS'!$Q$4:$Q$675)))=$K$4),6),0)=0,"",IFERROR(INDEX('📋 ORDERS'!$K$4:$K$675,IFERROR(_xludf.aggregate(15,6,(ROW('📋 ORDERS'!$B$4:$B$675)-3)/(IF($B$4="SKF Order",'📋 ORDERS'!$C$4:$C$675,IF($B$4="TATA Order",'📋 ORDERS'!$D$4:$D$675,IF($B$4="Vulcan PO",'📋 ORDERS'!$E$4:$E$675,'📋 ORDERS'!$Q$4:$Q$675)))=$K$4),6),0)),"")) | G28: =IF(IFERROR(_xludf.aggregate(15,6,(ROW('📋 ORDERS'!$B$4:$B$675)-3)/(IF($B$4="SKF Order",'📋 ORDERS'!$C$4:$C$675,IF($B$4="TATA Order",'📋 ORDERS'!$D$4:$D$675,IF($B$4="Vulcan PO",'📋 ORDERS'!$E$4:$E$675,'📋 ORDERS'!$Q$4:$Q$675)))=$K$4),6),0)=0,"",IFERROR(INDEX('📋 ORDERS'!$L$4:$L$675,IFERROR(_xludf.aggregate(15,6,(ROW('📋 ORDERS'!$B$4:$B$675)-3)/(IF($B$4="SKF Order",'📋 ORDERS'!$C$4:$C$675,IF($B$4="TATA Order",'📋 ORDERS'!$D$4:$D$675,IF($B$4="Vulcan PO",'📋 ORDERS'!$E$4:$E$675,'📋 ORDERS'!$Q$4:$Q$675)))=$K$4),6),0)),"")) | H28: =IF(IFERROR(_xludf.aggregate(15,6,(ROW('📋 ORDERS'!$B$4:$B$675)-3)/(IF($B$4="SKF Order",'📋 ORDERS'!$C$4:$C$675,IF($B$4="TATA Order",'📋 ORDERS'!$D$4:$D$675,IF($B$4="Vulcan PO",'📋 ORDERS'!$E$4:$E$675,'📋 ORDERS'!$Q$4:$Q$675)))=$K$4),6),0)=0,"",IFERROR(INDEX('📋 ORDERS'!$M$4:$M$675,IFERROR(_xludf.aggregate(15,6,(ROW('📋 ORDERS'!$B$4:$B$675)-3)/(IF($B$4="SKF Order",'📋 ORDERS'!$C$4:$C$675,IF($B$4="TATA Order",'📋 ORDERS'!$D$4:$D$675,IF($B$4="Vulcan PO",'📋 ORDERS'!$E$4:$E$675,'📋 ORDERS'!$Q$4:$Q$675)))=$K$4),6),0)),"")) | I28: =IF(IFERROR(_xludf.aggregate(15,6,(ROW('📋 ORDERS'!$B$4:$B$675)-3)/(IF($B$4="SKF Order",'📋 ORDERS'!$C$4:$C$675,IF($B$4="TATA Order",'📋 ORDERS'!$D$4:$D$675,IF($B$4="Vulcan PO",'📋 ORDERS'!$E$4:$E$675,'📋 ORDERS'!$Q$4:$Q$675)))=$K$4),6),0)=0,"",IFERROR(INDEX('📋 ORDERS'!$R$4:$R$675,IFERROR(_xludf.aggregate(15,6,(ROW('📋 ORDERS'!$B$4:$B$675)-3)/(IF($B$4="SKF Order",'📋 ORDERS'!$C$4:$C$675,IF($B$4="TATA Order",'📋 ORDERS'!$D$4:$D$675,IF($B$4="Vulcan PO",'📋 ORDERS'!$E$4:$E$675,'📋 ORDERS'!$Q$4:$Q$675)))=$K$4),6),0)),"")) | J28: =IF(IFERROR(_xludf.aggregate(15,6,(ROW('📋 ORDERS'!$B$4:$B$675)-3)/(IF($B$4="SKF Order",'📋 ORDERS'!$C$4:$C$675,IF($B$4="TATA Order",'📋 ORDERS'!$D$4:$D$675,IF($B$4="Vulcan PO",'📋 ORDERS'!$E$4:$E$675,'📋 ORDERS'!$Q$4:$Q$675)))=$K$4),6),0)=0,"",IFERROR(INDEX('📋 ORDERS'!$S$4:$S$675,IFERROR(_xludf.aggregate(15,6,(ROW('📋 ORDERS'!$B$4:$B$675)-3)/(IF($B$4="SKF Order",'📋 ORDERS'!$C$4:$C$675,IF($B$4="TATA Order",'📋 ORDERS'!$D$4:$D$675,IF($B$4="Vulcan PO",'📋 ORDERS'!$E$4:$E$675,'📋 ORDERS'!$Q$4:$Q$675)))=$K$4),6),0)),""))
B29: =IF(IFERROR(_xludf.aggregate(15,6,(ROW('📋 ORDERS'!$B$4:$B$675)-3)/(IF($B$4="SKF Order",'📋 ORDERS'!$C$4:$C$675,IF($B$4="TATA Order",'📋 ORDERS'!$D$4:$D$675,IF($B$4="Vulcan PO",'📋 ORDERS'!$E$4:$E$675,'📋 ORDERS'!$Q$4:$Q$675)))=$K$4),7),0)=0,"",7) | C29: =IF(IFERROR(_xludf.aggregate(15,6,(ROW('📋 ORDERS'!$B$4:$B$675)-3)/(IF($B$4="SKF Order",'📋 ORDERS'!$C$4:$C$675,IF($B$4="TATA Order",'📋 ORDERS'!$D$4:$D$675,IF($B$4="Vulcan PO",'📋 ORDERS'!$E$4:$E$675,'📋 ORDERS'!$Q$4:$Q$675)))=$K$4),7),0)=0,"",IFERROR(INDEX('📋 ORDERS'!$C$4:$C$675,IFERROR(_xludf.aggregate(15,6,(ROW('📋 ORDERS'!$B$4:$B$675)-3)/(IF($B$4="SKF Order",'📋 ORDERS'!$C$4:$C$675,IF($B$4="TATA Order",'📋 ORDERS'!$D$4:$D$675,IF($B$4="Vulcan PO",'📋 ORDERS'!$E$4:$E$675,'📋 ORDERS'!$Q$4:$Q$675)))=$K$4),7),0)),"")) | D29: =IF(IFERROR(_xludf.aggregate(15,6,(ROW('📋 ORDERS'!$B$4:$B$675)-3)/(IF($B$4="SKF Order",'📋 ORDERS'!$C$4:$C$675,IF($B$4="TATA Order",'📋 ORDERS'!$D$4:$D$675,IF($B$4="Vulcan PO",'📋 ORDERS'!$E$4:$E$675,'📋 ORDERS'!$Q$4:$Q$675)))=$K$4),7),0)=0,"",IFERROR(INDEX('📋 ORDERS'!$G$4:$G$675,IFERROR(_xludf.aggregate(15,6,(ROW('📋 ORDERS'!$B$4:$B$675)-3)/(IF($B$4="SKF Order",'📋 ORDERS'!$C$4:$C$675,IF($B$4="TATA Order",'📋 ORDERS'!$D$4:$D$675,IF($B$4="Vulcan PO",'📋 ORDERS'!$E$4:$E$675,'📋 ORDERS'!$Q$4:$Q$675)))=$K$4),7),0)),"")) | F29: =IF(IFERROR(_xludf.aggregate(15,6,(ROW('📋 ORDERS'!$B$4:$B$675)-3)/(IF($B$4="SKF Order",'📋 ORDERS'!$C$4:$C$675,IF($B$4="TATA Order",'📋 ORDERS'!$D$4:$D$675,IF($B$4="Vulcan PO",'📋 ORDERS'!$E$4:$E$675,'📋 ORDERS'!$Q$4:$Q$675)))=$K$4),7),0)=0,"",IFERROR(INDEX('📋 ORDERS'!$K$4:$K$675,IFERROR(_xludf.aggregate(15,6,(ROW('📋 ORDERS'!$B$4:$B$675)-3)/(IF($B$4="SKF Order",'📋 ORDERS'!$C$4:$C$675,IF($B$4="TATA Order",'📋 ORDERS'!$D$4:$D$675,IF($B$4="Vulcan PO",'📋 ORDERS'!$E$4:$E$675,'📋 ORDERS'!$Q$4:$Q$675)))=$K$4),7),0)),"")) | G29: =IF(IFERROR(_xludf.aggregate(15,6,(ROW('📋 ORDERS'!$B$4:$B$675)-3)/(IF($B$4="SKF Order",'📋 ORDERS'!$C$4:$C$675,IF($B$4="TATA Order",'📋 ORDERS'!$D$4:$D$675,IF($B$4="Vulcan PO",'📋 ORDERS'!$E$4:$E$675,'📋 ORDERS'!$Q$4:$Q$675)))=$K$4),7),0)=0,"",IFERROR(INDEX('📋 ORDERS'!$L$4:$L$675,IFERROR(_xludf.aggregate(15,6,(ROW('📋 ORDERS'!$B$4:$B$675)-3)/(IF($B$4="SKF Order",'📋 ORDERS'!$C$4:$C$675,IF($B$4="TATA Order",'📋 ORDERS'!$D$4:$D$675,IF($B$4="Vulcan PO",'📋 ORDERS'!$E$4:$E$675,'📋 ORDERS'!$Q$4:$Q$675)))=$K$4),7),0)),"")) | H29: =IF(IFERROR(_xludf.aggregate(15,6,(ROW('📋 ORDERS'!$B$4:$B$675)-3)/(IF($B$4="SKF Order",'📋 ORDERS'!$C$4:$C$675,IF($B$4="TATA Order",'📋 ORDERS'!$D$4:$D$675,IF($B$4="Vulcan PO",'📋 ORDERS'!$E$4:$E$675,'📋 ORDERS'!$Q$4:$Q$675)))=$K$4),7),0)=0,"",IFERROR(INDEX('📋 ORDERS'!$M$4:$M$675,IFERROR(_xludf.aggregate(15,6,(ROW('📋 ORDERS'!$B$4:$B$675)-3)/(IF($B$4="SKF Order",'📋 ORDERS'!$C$4:$C$675,IF($B$4="TATA Order",'📋 ORDERS'!$D$4:$D$675,IF($B$4="Vulcan PO",'📋 ORDERS'!$E$4:$E$675,'📋 ORDERS'!$Q$4:$Q$675)))=$K$4),7),0)),"")) | I29: =IF(IFERROR(_xludf.aggregate(15,6,(ROW('📋 ORDERS'!$B$4:$B$675)-3)/(IF($B$4="SKF Order",'📋 ORDERS'!$C$4:$C$675,IF($B$4="TATA Order",'📋 ORDERS'!$D$4:$D$675,IF($B$4="Vulcan PO",'📋 ORDERS'!$E$4:$E$675,'📋 ORDERS'!$Q$4:$Q$675)))=$K$4),7),0)=0,"",IFERROR(INDEX('📋 ORDERS'!$R$4:$R$675,IFERROR(_xludf.aggregate(15,6,(ROW('📋 ORDERS'!$B$4:$B$675)-3)/(IF($B$4="SKF Order",'📋 ORDERS'!$C$4:$C$675,IF($B$4="TATA Order",'📋 ORDERS'!$D$4:$D$675,IF($B$4="Vulcan PO",'📋 ORDERS'!$E$4:$E$675,'📋 ORDERS'!$Q$4:$Q$675)))=$K$4),7),0)),"")) | J29: =IF(IFERROR(_xludf.aggregate(15,6,(ROW('📋 ORDERS'!$B$4:$B$675)-3)/(IF($B$4="SKF Order",'📋 ORDERS'!$C$4:$C$675,IF($B$4="TATA Order",'📋 ORDERS'!$D$4:$D$675,IF($B$4="Vulcan PO",'📋 ORDERS'!$E$4:$E$675,'📋 ORDERS'!$Q$4:$Q$675)))=$K$4),7),0)=0,"",IFERROR(INDEX('📋 ORDERS'!$S$4:$S$675,IFERROR(_xludf.aggregate(15,6,(ROW('📋 ORDERS'!$B$4:$B$675)-3)/(IF($B$4="SKF Order",'📋 ORDERS'!$C$4:$C$675,IF($B$4="TATA Order",'📋 ORDERS'!$D$4:$D$675,IF($B$4="Vulcan PO",'📋 ORDERS'!$E$4:$E$675,'📋 ORDERS'!$Q$4:$Q$675)))=$K$4),7),0)),""))
B30: =IF(IFERROR(_xludf.aggregate(15,6,(ROW('📋 ORDERS'!$B$4:$B$675)-3)/(IF($B$4="SKF Order",'📋 ORDERS'!$C$4:$C$675,IF($B$4="TATA Order",'📋 ORDERS'!$D$4:$D$675,IF($B$4="Vulcan PO",'📋 ORDERS'!$E$4:$E$675,'📋 ORDERS'!$Q$4:$Q$675)))=$K$4),8),0)=0,"",8) | C30: =IF(IFERROR(_xludf.aggregate(15,6,(ROW('📋 ORDERS'!$B$4:$B$675)-3)/(IF($B$4="SKF Order",'📋 ORDERS'!$C$4:$C$675,IF($B$4="TATA Order",'📋 ORDERS'!$D$4:$D$675,IF($B$4="Vulcan PO",'📋 ORDERS'!$E$4:$E$675,'📋 ORDERS'!$Q$4:$Q$675)))=$K$4),8),0)=0,"",IFERROR(INDEX('📋 ORDERS'!$C$4:$C$675,IFERROR(_xludf.aggregate(15,6,(ROW('📋 ORDERS'!$B$4:$B$675)-3)/(IF($B$4="SKF Order",'📋 ORDERS'!$C$4:$C$675,IF($B$4="TATA Order",'📋 ORDERS'!$D$4:$D$675,IF($B$4="Vulcan PO",'📋 ORDERS'!$E$4:$E$675,'📋 ORDERS'!$Q$4:$Q$675)))=$K$4),8),0)),"")) | D30: =IF(IFERROR(_xludf.aggregate(15,6,(ROW('📋 ORDERS'!$B$4:$B$675)-3)/(IF($B$4="SKF Order",'📋 ORDERS'!$C$4:$C$675,IF($B$4="TATA Order",'📋 ORDERS'!$D$4:$D$675,IF($B$4="Vulcan PO",'📋 ORDERS'!$E$4:$E$675,'📋 ORDERS'!$Q$4:$Q$675)))=$K$4),8),0)=0,"",IFERROR(INDEX('📋 ORDERS'!$G$4:$G$675,IFERROR(_xludf.aggregate(15,6,(ROW('📋 ORDERS'!$B$4:$B$675)-3)/(IF($B$4="SKF Order",'📋 ORDERS'!$C$4:$C$675,IF($B$4="TATA Order",'📋 ORDERS'!$D$4:$D$675,IF($B$4="Vulcan PO",'📋 ORDERS'!$E$4:$E$675,'📋 ORDERS'!$Q$4:$Q$675)))=$K$4),8),0)),"")) | F30: =IF(IFERROR(_xludf.aggregate(15,6,(ROW('📋 ORDERS'!$B$4:$B$675)-3)/(IF($B$4="SKF Order",'📋 ORDERS'!$C$4:$C$675,IF($B$4="TATA Order",'📋 ORDERS'!$D$4:$D$675,IF($B$4="Vulcan PO",'📋 ORDERS'!$E$4:$E$675,'📋 ORDERS'!$Q$4:$Q$675)))=$K$4),8),0)=0,"",IFERROR(INDEX('📋 ORDERS'!$K$4:$K$675,IFERROR(_xludf.aggregate(15,6,(ROW('📋 ORDERS'!$B$4:$B$675)-3)/(IF($B$4="SKF Order",'📋 ORDERS'!$C$4:$C$675,IF($B$4="TATA Order",'📋 ORDERS'!$D$4:$D$675,IF($B$4="Vulcan PO",'📋 ORDERS'!$E$4:$E$675,'📋 ORDERS'!$Q$4:$Q$675)))=$K$4),8),0)),"")) | G30: =IF(IFERROR(_xludf.aggregate(15,6,(ROW('📋 ORDERS'!$B$4:$B$675)-3)/(IF($B$4="SKF Order",'📋 ORDERS'!$C$4:$C$675,IF($B$4="TATA Order",'📋 ORDERS'!$D$4:$D$675,IF($B$4="Vulcan PO",'📋 ORDERS'!$E$4:$E$675,'📋 ORDERS'!$Q$4:$Q$675)))=$K$4),8),0)=0,"",IFERROR(INDEX('📋 ORDERS'!$L$4:$L$675,IFERROR(_xludf.aggregate(15,6,(ROW('📋 ORDERS'!$B$4:$B$675)-3)/(IF($B$4="SKF Order",'📋 ORDERS'!$C$4:$C$675,IF($B$4="TATA Order",'📋 ORDERS'!$D$4:$D$675,IF($B$4="Vulcan PO",'📋 ORDERS'!$E$4:$E$675,'📋 ORDERS'!$Q$4:$Q$675)))=$K$4),8),0)),"")) | H30: =IF(IFERROR(_xludf.aggregate(15,6,(ROW('📋 ORDERS'!$B$4:$B$675)-3)/(IF($B$4="SKF Order",'📋 ORDERS'!$C$4:$C$675,IF($B$4="TATA Order",'📋 ORDERS'!$D$4:$D$675,IF($B$4="Vulcan PO",'📋 ORDERS'!$E$4:$E$675,'📋 ORDERS'!$Q$4:$Q$675)))=$K$4),8),0)=0,"",IFERROR(INDEX('📋 ORDERS'!$M$4:$M$675,IFERROR(_xludf.aggregate(15,6,(ROW('📋 ORDERS'!$B$4:$B$675)-3)/(IF($B$4="SKF Order",'📋 ORDERS'!$C$4:$C$675,IF($B$4="TATA Order",'📋 ORDERS'!$D$4:$D$675,IF($B$4="Vulcan PO",'📋 ORDERS'!$E$4:$E$675,'📋 ORDERS'!$Q$4:$Q$675)))=$K$4),8),0)),"")) | I30: =IF(IFERROR(_xludf.aggregate(15,6,(ROW('📋 ORDERS'!$B$4:$B$675)-3)/(IF($B$4="SKF Order",'📋 ORDERS'!$C$4:$C$675,IF($B$4="TATA Order",'📋 ORDERS'!$D$4:$D$675,IF($B$4="Vulcan PO",'📋 ORDERS'!$E$4:$E$675,'📋 ORDERS'!$Q$4:$Q$675)))=$K$4),8),0)=0,"",IFERROR(INDEX('📋 ORDERS'!$R$4:$R$675,IFERROR(_xludf.aggregate(15,6,(ROW('📋 ORDERS'!$B$4:$B$675)-3)/(IF($B$4="SKF Order",'📋 ORDERS'!$C$4:$C$675,IF($B$4="TATA Order",'📋 ORDERS'!$D$4:$D$675,IF($B$4="Vulcan PO",'📋 ORDERS'!$E$4:$E$675,'📋 ORDERS'!$Q$4:$Q$675)))=$K$4),8),0)),"")) | J30: =IF(IFERROR(_xludf.aggregate(15,6,(ROW('📋 ORDERS'!$B$4:$B$675)-3)/(IF($B$4="SKF Order",'📋 ORDERS'!$C$4:$C$675,IF($B$4="TATA Order",'📋 ORDERS'!$D$4:$D$675,IF($B$4="Vulcan PO",'📋 ORDERS'!$E$4:$E$675,'📋 ORDERS'!$Q$4:$Q$675)))=$K$4),8),0)=0,"",IFERROR(INDEX('📋 ORDERS'!$S$4:$S$675,IFERROR(_xludf.aggregate(15,6,(ROW('📋 ORDERS'!$B$4:$B$675)-3)/(IF($B$4="SKF Order",'📋 ORDERS'!$C$4:$C$675,IF($B$4="TATA Order",'📋 ORDERS'!$D$4:$D$675,IF($B$4="Vulcan PO",'📋 ORDERS'!$E$4:$E$675,'📋 ORDERS'!$Q$4:$Q$675)))=$K$4),8),0)),""))
B31: =IF(IFERROR(_xludf.aggregate(15,6,(ROW('📋 ORDERS'!$B$4:$B$675)-3)/(IF($B$4="SKF Order",'📋 ORDERS'!$C$4:$C$675,IF($B$4="TATA Order",'📋 ORDERS'!$D$4:$D$675,IF($B$4="Vulcan PO",'📋 ORDERS'!$E$4:$E$675,'📋 ORDERS'!$Q$4:$Q$675)))=$K$4),9),0)=0,"",9) | C31: =IF(IFERROR(_xludf.aggregate(15,6,(ROW('📋 ORDERS'!$B$4:$B$675)-3)/(IF($B$4="SKF Order",'📋 ORDERS'!$C$4:$C$675,IF($B$4="TATA Order",'📋 ORDERS'!$D$4:$D$675,IF($B$4="Vulcan PO",'📋 ORDERS'!$E$4:$E$675,'📋 ORDERS'!$Q$4:$Q$675)))=$K$4),9),0)=0,"",IFERROR(INDEX('📋 ORDERS'!$C$4:$C$675,IFERROR(_xludf.aggregate(15,6,(ROW('📋 ORDERS'!$B$4:$B$675)-3)/(IF($B$4="SKF Order",'📋 ORDERS'!$C$4:$C$675,IF($B$4="TATA Order",'📋 ORDERS'!$D$4:$D$675,IF($B$4="Vulcan PO",'📋 ORDERS'!$E$4:$E$675,'📋 ORDERS'!$Q$4:$Q$675)))=$K$4),9),0)),"")) | D31: =IF(IFERROR(_xludf.aggregate(15,6,(ROW('📋 ORDERS'!$B$4:$B$675)-3)/(IF($B$4="SKF Order",'📋 ORDERS'!$C$4:$C$675,IF($B$4="TATA Order",'📋 ORDERS'!$D$4:$D$675,IF($B$4="Vulcan PO",'📋 ORDERS'!$E$4:$E$675,'📋 ORDERS'!$Q$4:$Q$675)))=$K$4),9),0)=0,"",IFERROR(INDEX('📋 ORDERS'!$G$4:$G$675,IFERROR(_xludf.aggregate(15,6,(ROW('📋 ORDERS'!$B$4:$B$675)-3)/(IF($B$4="SKF Order",'📋 ORDERS'!$C$4:$C$675,IF($B$4="TATA Order",'📋 ORDERS'!$D$4:$D$675,IF($B$4="Vulcan PO",'📋 ORDERS'!$E$4:$E$675,'📋 ORDERS'!$Q$4:$Q$675)))=$K$4),9),0)),"")) | F31: =IF(IFERROR(_xludf.aggregate(15,6,(ROW('📋 ORDERS'!$B$4:$B$675)-3)/(IF($B$4="SKF Order",'📋 ORDERS'!$C$4:$C$675,IF($B$4="TATA Order",'📋 ORDERS'!$D$4:$D$675,IF($B$4="Vulcan PO",'📋 ORDERS'!$E$4:$E$675,'📋 ORDERS'!$Q$4:$Q$675)))=$K$4),9),0)=0,"",IFERROR(INDEX('📋 ORDERS'!$K$4:$K$675,IFERROR(_xludf.aggregate(15,6,(ROW('📋 ORDERS'!$B$4:$B$675)-3)/(IF($B$4="SKF Order",'📋 ORDERS'!$C$4:$C$675,IF($B$4="TATA Order",'📋 ORDERS'!$D$4:$D$675,IF($B$4="Vulcan PO",'📋 ORDERS'!$E$4:$E$675,'📋 ORDERS'!$Q$4:$Q$675)))=$K$4),9),0)),"")) | G31: =IF(IFERROR(_xludf.aggregate(15,6,(ROW('📋 ORDERS'!$B$4:$B$675)-3)/(IF($B$4="SKF Order",'📋 ORDERS'!$C$4:$C$675,IF($B$4="TATA Order",'📋 ORDERS'!$D$4:$D$675,IF($B$4="Vulcan PO",'📋 ORDERS'!$E$4:$E$675,'📋 ORDERS'!$Q$4:$Q$675)))=$K$4),9),0)=0,"",IFERROR(INDEX('📋 ORDERS'!$L$4:$L$675,IFERROR(_xludf.aggregate(15,6,(ROW('📋 ORDERS'!$B$4:$B$675)-3)/(IF($B$4="SKF Order",'📋 ORDERS'!$C$4:$C$675,IF($B$4="TATA Order",'📋 ORDERS'!$D$4:$D$675,IF($B$4="Vulcan PO",'📋 ORDERS'!$E$4:$E$675,'📋 ORDERS'!$Q$4:$Q$675)))=$K$4),9),0)),"")) | H31: =IF(IFERROR(_xludf.aggregate(15,6,(ROW('📋 ORDERS'!$B$4:$B$675)-3)/(IF($B$4="SKF Order",'📋 ORDERS'!$C$4:$C$675,IF($B$4="TATA Order",'📋 ORDERS'!$D$4:$D$675,IF($B$4="Vulcan PO",'📋 ORDERS'!$E$4:$E$675,'📋 ORDERS'!$Q$4:$Q$675)))=$K$4),9),0)=0,"",IFERROR(INDEX('📋 ORDERS'!$M$4:$M$675,IFERROR(_xludf.aggregate(15,6,(ROW('📋 ORDERS'!$B$4:$B$675)-3)/(IF($B$4="SKF Order",'📋 ORDERS'!$C$4:$C$675,IF($B$4="TATA Order",'📋 ORDERS'!$D$4:$D$675,IF($B$4="Vulcan PO",'📋 ORDERS'!$E$4:$E$675,'📋 ORDERS'!$Q$4:$Q$675)))=$K$4),9),0)),"")) | I31: =IF(IFERROR(_xludf.aggregate(15,6,(ROW('📋 ORDERS'!$B$4:$B$675)-3)/(IF($B$4="SKF Order",'📋 ORDERS'!$C$4:$C$675,IF($B$4="TATA Order",'📋 ORDERS'!$D$4:$D$675,IF($B$4="Vulcan PO",'📋 ORDERS'!$E$4:$E$675,'📋 ORDERS'!$Q$4:$Q$675)))=$K$4),9),0)=0,"",IFERROR(INDEX('📋 ORDERS'!$R$4:$R$675,IFERROR(_xludf.aggregate(15,6,(ROW('📋 ORDERS'!$B$4:$B$675)-3)/(IF($B$4="SKF Order",'📋 ORDERS'!$C$4:$C$675,IF($B$4="TATA Order",'📋 ORDERS'!$D$4:$D$675,IF($B$4="Vulcan PO",'📋 ORDERS'!$E$4:$E$675,'📋 ORDERS'!$Q$4:$Q$675)))=$K$4),9),0)),"")) | J31: =IF(IFERROR(_xludf.aggregate(15,6,(ROW('📋 ORDERS'!$B$4:$B$675)-3)/(IF($B$4="SKF Order",'📋 ORDERS'!$C$4:$C$675,IF($B$4="TATA Order",'📋 ORDERS'!$D$4:$D$675,IF($B$4="Vulcan PO",'📋 ORDERS'!$E$4:$E$675,'📋 ORDERS'!$Q$4:$Q$675)))=$K$4),9),0)=0,"",IFERROR(INDEX('📋 ORDERS'!$S$4:$S$675,IFERROR(_xludf.aggregate(15,6,(ROW('📋 ORDERS'!$B$4:$B$675)-3)/(IF($B$4="SKF Order",'📋 ORDERS'!$C$4:$C$675,IF($B$4="TATA Order",'📋 ORDERS'!$D$4:$D$675,IF($B$4="Vulcan PO",'📋 ORDERS'!$E$4:$E$675,'📋 ORDERS'!$Q$4:$Q$675)))=$K$4),9),0)),""))
B32: =IF(IFERROR(_xludf.aggregate(15,6,(ROW('📋 ORDERS'!$B$4:$B$675)-3)/(IF($B$4="SKF Order",'📋 ORDERS'!$C$4:$C$675,IF($B$4="TATA Order",'📋 ORDERS'!$D$4:$D$675,IF($B$4="Vulcan PO",'📋 ORDERS'!$E$4:$E$675,'📋 ORDERS'!$Q$4:$Q$675)))=$K$4),10),0)=0,"",10) | C32: =IF(IFERROR(_xludf.aggregate(15,6,(ROW('📋 ORDERS'!$B$4:$B$675)-3)/(IF($B$4="SKF Order",'📋 ORDERS'!$C$4:$C$675,IF($B$4="TATA Order",'📋 ORDERS'!$D$4:$D$675,IF($B$4="Vulcan PO",'📋 ORDERS'!$E$4:$E$675,'📋 ORDERS'!$Q$4:$Q$675)))=$K$4),10),0)=0,"",IFERROR(INDEX('📋 ORDERS'!$C$4:$C$675,IFERROR(_xludf.aggregate(15,6,(ROW('📋 ORDERS'!$B$4:$B$675)-3)/(IF($B$4="SKF Order",'📋 ORDERS'!$C$4:$C$675,IF($B$4="TATA Order",'📋 ORDERS'!$D$4:$D$675,IF($B$4="Vulcan PO",'📋 ORDERS'!$E$4:$E$675,'📋 ORDERS'!$Q$4:$Q$675)))=$K$4),10),0)),"")) | D32: =IF(IFERROR(_xludf.aggregate(15,6,(ROW('📋 ORDERS'!$B$4:$B$675)-3)/(IF($B$4="SKF Order",'📋 ORDERS'!$C$4:$C$675,IF($B$4="TATA Order",'📋 ORDERS'!$D$4:$D$675,IF($B$4="Vulcan PO",'📋 ORDERS'!$E$4:$E$675,'📋 ORDERS'!$Q$4:$Q$675)))=$K$4),10),0)=0,"",IFERROR(INDEX('📋 ORDERS'!$G$4:$G$675,IFERROR(_xludf.aggregate(15,6,(ROW('📋 ORDERS'!$B$4:$B$675)-3)/(IF($B$4="SKF Order",'📋 ORDERS'!$C$4:$C$675,IF($B$4="TATA Order",'📋 ORDERS'!$D$4:$D$675,IF($B$4="Vulcan PO",'📋 ORDERS'!$E$4:$E$675,'📋 ORDERS'!$Q$4:$Q$675)))=$K$4),10),0)),"")) | F32: =IF(IFERROR(_xludf.aggregate(15,6,(ROW('📋 ORDERS'!$B$4:$B$675)-3)/(IF($B$4="SKF Order",'📋 ORDERS'!$C$4:$C$675,IF($B$4="TATA Order",'📋 ORDERS'!$D$4:$D$675,IF($B$4="Vulcan PO",'📋 ORDERS'!$E$4:$E$675,'📋 ORDERS'!$Q$4:$Q$675)))=$K$4),10),0)=0,"",IFERROR(INDEX('📋 ORDERS'!$K$4:$K$675,IFERROR(_xludf.aggregate(15,6,(ROW('📋 ORDERS'!$B$4:$B$675)-3)/(IF($B$4="SKF Order",'📋 ORDERS'!$C$4:$C$675,IF($B$4="TATA Order",'📋 ORDERS'!$D$4:$D$675,IF($B$4="Vulcan PO",'📋 ORDERS'!$E$4:$E$675,'📋 ORDERS'!$Q$4:$Q$675)))=$K$4),10),0)),"")) | G32: =IF(IFERROR(_xludf.aggregate(15,6,(ROW('📋 ORDERS'!$B$4:$B$675)-3)/(IF($B$4="SKF Order",'📋 ORDERS'!$C$4:$C$675,IF($B$4="TATA Order",'📋 ORDERS'!$D$4:$D$675,IF($B$4="Vulcan PO",'📋 ORDERS'!$E$4:$E$675,'📋 ORDERS'!$Q$4:$Q$675)))=$K$4),10),0)=0,"",IFERROR(INDEX('📋 ORDERS'!$L$4:$L$675,IFERROR(_xludf.aggregate(15,6,(ROW('📋 ORDERS'!$B$4:$B$675)-3)/(IF($B$4="SKF Order",'📋 ORDERS'!$C$4:$C$675,IF($B$4="TATA Order",'📋 ORDERS'!$D$4:$D$675,IF($B$4="Vulcan PO",'📋 ORDERS'!$E$4:$E$675,'📋 ORDERS'!$Q$4:$Q$675)))=$K$4),10),0)),"")) | H32: =IF(IFERROR(_xludf.aggregate(15,6,(ROW('📋 ORDERS'!$B$4:$B$675)-3)/(IF($B$4="SKF Order",'📋 ORDERS'!$C$4:$C$675,IF($B$4="TATA Order",'📋 ORDERS'!$D$4:$D$675,IF($B$4="Vulcan PO",'📋 ORDERS'!$E$4:$E$675,'📋 ORDERS'!$Q$4:$Q$675)))=$K$4),10),0)=0,"",IFERROR(INDEX('📋 ORDERS'!$M$4:$M$675,IFERROR(_xludf.aggregate(15,6,(ROW('📋 ORDERS'!$B$4:$B$675)-3)/(IF($B$4="SKF Order",'📋 ORDERS'!$C$4:$C$675,IF($B$4="TATA Order",'📋 ORDERS'!$D$4:$D$675,IF($B$4="Vulcan PO",'📋 ORDERS'!$E$4:$E$675,'📋 ORDERS'!$Q$4:$Q$675)))=$K$4),10),0)),"")) | I32: =IF(IFERROR(_xludf.aggregate(15,6,(ROW('📋 ORDERS'!$B$4:$B$675)-3)/(IF($B$4="SKF Order",'📋 ORDERS'!$C$4:$C$675,IF($B$4="TATA Order",'📋 ORDERS'!$D$4:$D$675,IF($B$4="Vulcan PO",'📋 ORDERS'!$E$4:$E$675,'📋 ORDERS'!$Q$4:$Q$675)))=$K$4),10),0)=0,"",IFERROR(INDEX('📋 ORDERS'!$R$4:$R$675,IFERROR(_xludf.aggregate(15,6,(ROW('📋 ORDERS'!$B$4:$B$675)-3)/(IF($B$4="SKF Order",'📋 ORDERS'!$C$4:$C$675,IF($B$4="TATA Order",'📋 ORDERS'!$D$4:$D$675,IF($B$4="Vulcan PO",'📋 ORDERS'!$E$4:$E$675,'📋 ORDERS'!$Q$4:$Q$675)))=$K$4),10),0)),"")) | J32: =IF(IFERROR(_xludf.aggregate(15,6,(ROW('📋 ORDERS'!$B$4:$B$675)-3)/(IF($B$4="SKF Order",'📋 ORDERS'!$C$4:$C$675,IF($B$4="TATA Order",'📋 ORDERS'!$D$4:$D$675,IF($B$4="Vulcan PO",'📋 ORDERS'!$E$4:$E$675,'📋 ORDERS'!$Q$4:$Q$675)))=$K$4),10),0)=0,"",IFERROR(INDEX('📋 ORDERS'!$S$4:$S$675,IFERROR(_xludf.aggregate(15,6,(ROW('📋 ORDERS'!$B$4:$B$675)-3)/(IF($B$4="SKF Order",'📋 ORDERS'!$C$4:$C$675,IF($B$4="TATA Order",'📋 ORDERS'!$D$4:$D$675,IF($B$4="Vulcan PO",'📋 ORDERS'!$E$4:$E$675,'📋 ORDERS'!$Q$4:$Q$675)))=$K$4),10),0)),""))
B33: =IF(IFERROR(_xludf.aggregate(15,6,(ROW('📋 ORDERS'!$B$4:$B$675)-3)/(IF($B$4="SKF Order",'📋 ORDERS'!$C$4:$C$675,IF($B$4="TATA Order",'📋 ORDERS'!$D$4:$D$675,IF($B$4="Vulcan PO",'📋 ORDERS'!$E$4:$E$675,'📋 ORDERS'!$Q$4:$Q$675)))=$K$4),11),0)=0,"",11) | C33: =IF(IFERROR(_xludf.aggregate(15,6,(ROW('📋 ORDERS'!$B$4:$B$675)-3)/(IF($B$4="SKF Order",'📋 ORDERS'!$C$4:$C$675,IF($B$4="TATA Order",'📋 ORDERS'!$D$4:$D$675,IF($B$4="Vulcan PO",'📋 ORDERS'!$E$4:$E$675,'📋 ORDERS'!$Q$4:$Q$675)))=$K$4),11),0)=0,"",IFERROR(INDEX('📋 ORDERS'!$C$4:$C$675,IFERROR(_xludf.aggregate(15,6,(ROW('📋 ORDERS'!$B$4:$B$675)-3)/(IF($B$4="SKF Order",'📋 ORDERS'!$C$4:$C$675,IF($B$4="TATA Order",'📋 ORDERS'!$D$4:$D$675,IF($B$4="Vulcan PO",'📋 ORDERS'!$E$4:$E$675,'📋 ORDERS'!$Q$4:$Q$675)))=$K$4),11),0)),"")) | D33: =IF(IFERROR(_xludf.aggregate(15,6,(ROW('📋 ORDERS'!$B$4:$B$675)-3)/(IF($B$4="SKF Order",'📋 ORDERS'!$C$4:$C$675,IF($B$4="TATA Order",'📋 ORDERS'!$D$4:$D$675,IF($B$4="Vulcan PO",'📋 ORDERS'!$E$4:$E$675,'📋 ORDERS'!$Q$4:$Q$675)))=$K$4),11),0)=0,"",IFERROR(INDEX('📋 ORDERS'!$G$4:$G$675,IFERROR(_xludf.aggregate(15,6,(ROW('📋 ORDERS'!$B$4:$B$675)-3)/(IF($B$4="SKF Order",'📋 ORDERS'!$C$4:$C$675,IF($B$4="TATA Order",'📋 ORDERS'!$D$4:$D$675,IF($B$4="Vulcan PO",'📋 ORDERS'!$E$4:$E$675,'📋 ORDERS'!$Q$4:$Q$675)))=$K$4),11),0)),"")) | F33: =IF(IFERROR(_xludf.aggregate(15,6,(ROW('📋 ORDERS'!$B$4:$B$675)-3)/(IF($B$4="SKF Order",'📋 ORDERS'!$C$4:$C$675,IF($B$4="TATA Order",'📋 ORDERS'!$D$4:$D$675,IF($B$4="Vulcan PO",'📋 ORDERS'!$E$4:$E$675,'📋 ORDERS'!$Q$4:$Q$675)))=$K$4),11),0)=0,"",IFERROR(INDEX('📋 ORDERS'!$K$4:$K$675,IFERROR(_xludf.aggregate(15,6,(ROW('📋 ORDERS'!$B$4:$B$675)-3)/(IF($B$4="SKF Order",'📋 ORDERS'!$C$4:$C$675,IF($B$4="TATA Order",'📋 ORDERS'!$D$4:$D$675,IF($B$4="Vulcan PO",'📋 ORDERS'!$E$4:$E$675,'📋 ORDERS'!$Q$4:$Q$675)))=$K$4),11),0)),"")) | G33: =IF(IFERROR(_xludf.aggregate(15,6,(ROW('📋 ORDERS'!$B$4:$B$675)-3)/(IF($B$4="SKF Order",'📋 ORDERS'!$C$4:$C$675,IF($B$4="TATA Order",'📋 ORDERS'!$D$4:$D$675,IF($B$4="Vulcan PO",'📋 ORDERS'!$E$4:$E$675,'📋 ORDERS'!$Q$4:$Q$675)))=$K$4),11),0)=0,"",IFERROR(INDEX('📋 ORDERS'!$L$4:$L$675,IFERROR(_xludf.aggregate(15,6,(ROW('📋 ORDERS'!$B$4:$B$675)-3)/(IF($B$4="SKF Order",'📋 ORDERS'!$C$4:$C$675,IF($B$4="TATA Order",'📋 ORDERS'!$D$4:$D$675,IF($B$4="Vulcan PO",'📋 ORDERS'!$E$4:$E$675,'📋 ORDERS'!$Q$4:$Q$675)))=$K$4),11),0)),"")) | H33: =IF(IFERROR(_xludf.aggregate(15,6,(ROW('📋 ORDERS'!$B$4:$B$675)-3)/(IF($B$4="SKF Order",'📋 ORDERS'!$C$4:$C$675,IF($B$4="TATA Order",'📋 ORDERS'!$D$4:$D$675,IF($B$4="Vulcan PO",'📋 ORDERS'!$E$4:$E$675,'📋 ORDERS'!$Q$4:$Q$675)))=$K$4),11),0)=0,"",IFERROR(INDEX('📋 ORDERS'!$M$4:$M$675,IFERROR(_xludf.aggregate(15,6,(ROW('📋 ORDERS'!$B$4:$B$675)-3)/(IF($B$4="SKF Order",'📋 ORDERS'!$C$4:$C$675,IF($B$4="TATA Order",'📋 ORDERS'!$D$4:$D$675,IF($B$4="Vulcan PO",'📋 ORDERS'!$E$4:$E$675,'📋 ORDERS'!$Q$4:$Q$675)))=$K$4),11),0)),"")) | I33: =IF(IFERROR(_xludf.aggregate(15,6,(ROW('📋 ORDERS'!$B$4:$B$675)-3)/(IF($B$4="SKF Order",'📋 ORDERS'!$C$4:$C$675,IF($B$4="TATA Order",'📋 ORDERS'!$D$4:$D$675,IF($B$4="Vulcan PO",'📋 ORDERS'!$E$4:$E$675,'📋 ORDERS'!$Q$4:$Q$675)))=$K$4),11),0)=0,"",IFERROR(INDEX('📋 ORDERS'!$R$4:$R$675,IFERROR(_xludf.aggregate(15,6,(ROW('📋 ORDERS'!$B$4:$B$675)-3)/(IF($B$4="SKF Order",'📋 ORDERS'!$C$4:$C$675,IF($B$4="TATA Order",'📋 ORDERS'!$D$4:$D$675,IF($B$4="Vulcan PO",'📋 ORDERS'!$E$4:$E$675,'📋 ORDERS'!$Q$4:$Q$675)))=$K$4),11),0)),"")) | J33: =IF(IFERROR(_xludf.aggregate(15,6,(ROW('📋 ORDERS'!$B$4:$B$675)-3)/(IF($B$4="SKF Order",'📋 ORDERS'!$C$4:$C$675,IF($B$4="TATA Order",'📋 ORDERS'!$D$4:$D$675,IF($B$4="Vulcan PO",'📋 ORDERS'!$E$4:$E$675,'📋 ORDERS'!$Q$4:$Q$675)))=$K$4),11),0)=0,"",IFERROR(INDEX('📋 ORDERS'!$S$4:$S$675,IFERROR(_xludf.aggregate(15,6,(ROW('📋 ORDERS'!$B$4:$B$675)-3)/(IF($B$4="SKF Order",'📋 ORDERS'!$C$4:$C$675,IF($B$4="TATA Order",'📋 ORDERS'!$D$4:$D$675,IF($B$4="Vulcan PO",'📋 ORDERS'!$E$4:$E$675,'📋 ORDERS'!$Q$4:$Q$675)))=$K$4),11),0)),""))
B34: =IF(IFERROR(_xludf.aggregate(15,6,(ROW('📋 ORDERS'!$B$4:$B$675)-3)/(IF($B$4="SKF Order",'📋 ORDERS'!$C$4:$C$675,IF($B$4="TATA Order",'📋 ORDERS'!$D$4:$D$675,IF($B$4="Vulcan PO",'📋 ORDERS'!$E$4:$E$675,'📋 ORDERS'!$Q$4:$Q$675)))=$K$4),12),0)=0,"",12) | C34: =IF(IFERROR(_xludf.aggregate(15,6,(ROW('📋 ORDERS'!$B$4:$B$675)-3)/(IF($B$4="SKF Order",'📋 ORDERS'!$C$4:$C$675,IF($B$4="TATA Order",'📋 ORDERS'!$D$4:$D$675,IF($B$4="Vulcan PO",'📋 ORDERS'!$E$4:$E$675,'📋 ORDERS'!$Q$4:$Q$675)))=$K$4),12),0)=0,"",IFERROR(INDEX('📋 ORDERS'!$C$4:$C$675,IFERROR(_xludf.aggregate(15,6,(ROW('📋 ORDERS'!$B$4:$B$675)-3)/(IF($B$4="SKF Order",'📋 ORDERS'!$C$4:$C$675,IF($B$4="TATA Order",'📋 ORDERS'!$D$4:$D$675,IF($B$4="Vulcan PO",'📋 ORDERS'!$E$4:$E$675,'📋 ORDERS'!$Q$4:$Q$675)))=$K$4),12),0)),"")) | D34: =IF(IFERROR(_xludf.aggregate(15,6,(ROW('📋 ORDERS'!$B$4:$B$675)-3)/(IF($B$4="SKF Order",'📋 ORDERS'!$C$4:$C$675,IF($B$4="TATA Order",'📋 ORDERS'!$D$4:$D$675,IF($B$4="Vulcan PO",'📋 ORDERS'!$E$4:$E$675,'📋 ORDERS'!$Q$4:$Q$675)))=$K$4),12),0)=0,"",IFERROR(INDEX('📋 ORDERS'!$G$4:$G$675,IFERROR(_xludf.aggregate(15,6,(ROW('📋 ORDERS'!$B$4:$B$675)-3)/(IF($B$4="SKF Order",'📋 ORDERS'!$C$4:$C$675,IF($B$4="TATA Order",'📋 ORDERS'!$D$4:$D$675,IF($B$4="Vulcan PO",'📋 ORDERS'!$E$4:$E$675,'📋 ORDERS'!$Q$4:$Q$675)))=$K$4),12),0)),"")) | F34: =IF(IFERROR(_xludf.aggregate(15,6,(ROW('📋 ORDERS'!$B$4:$B$675)-3)/(IF($B$4="SKF Order",'📋 ORDERS'!$C$4:$C$675,IF($B$4="TATA Order",'📋 ORDERS'!$D$4:$D$675,IF($B$4="Vulcan PO",'📋 ORDERS'!$E$4:$E$675,'📋 ORDERS'!$Q$4:$Q$675)))=$K$4),12),0)=0,"",IFERROR(INDEX('📋 ORDERS'!$K$4:$K$675,IFERROR(_xludf.aggregate(15,6,(ROW('📋 ORDERS'!$B$4:$B$675)-3)/(IF($B$4="SKF Order",'📋 ORDERS'!$C$4:$C$675,IF($B$4="TATA Order",'📋 ORDERS'!$D$4:$D$675,IF($B$4="Vulcan PO",'📋 ORDERS'!$E$4:$E$675,'📋 ORDERS'!$Q$4:$Q$675)))=$K$4),12),0)),"")) | G34: =IF(IFERROR(_xludf.aggregate(15,6,(ROW('📋 ORDERS'!$B$4:$B$675)-3)/(IF($B$4="SKF Order",'📋 ORDERS'!$C$4:$C$675,IF($B$4="TATA Order",'📋 ORDERS'!$D$4:$D$675,IF($B$4="Vulcan PO",'📋 ORDERS'!$E$4:$E$675,'📋 ORDERS'!$Q$4:$Q$675)))=$K$4),12),0)=0,"",IFERROR(INDEX('📋 ORDERS'!$L$4:$L$675,IFERROR(_xludf.aggregate(15,6,(ROW('📋 ORDERS'!$B$4:$B$675)-3)/(IF($B$4="SKF Order",'📋 ORDERS'!$C$4:$C$675,IF($B$4="TATA Order",'📋 ORDERS'!$D$4:$D$675,IF($B$4="Vulcan PO",'📋 ORDERS'!$E$4:$E$675,'📋 ORDERS'!$Q$4:$Q$675)))=$K$4),12),0)),"")) | H34: =IF(IFERROR(_xludf.aggregate(15,6,(ROW('📋 ORDERS'!$B$4:$B$675)-3)/(IF($B$4="SKF Order",'📋 ORDERS'!$C$4:$C$675,IF($B$4="TATA Order",'📋 ORDERS'!$D$4:$D$675,IF($B$4="Vulcan PO",'📋 ORDERS'!$E$4:$E$675,'📋 ORDERS'!$Q$4:$Q$675)))=$K$4),12),0)=0,"",IFERROR(INDEX('📋 ORDERS'!$M$4:$M$675,IFERROR(_xludf.aggregate(15,6,(ROW('📋 ORDERS'!$B$4:$B$675)-3)/(IF($B$4="SKF Order",'📋 ORDERS'!$C$4:$C$675,IF($B$4="TATA Order",'📋 ORDERS'!$D$4:$D$675,IF($B$4="Vulcan PO",'📋 ORDERS'!$E$4:$E$675,'📋 ORDERS'!$Q$4:$Q$675)))=$K$4),12),0)),"")) | I34: =IF(IFERROR(_xludf.aggregate(15,6,(ROW('📋 ORDERS'!$B$4:$B$675)-3)/(IF($B$4="SKF Order",'📋 ORDERS'!$C$4:$C$675,IF($B$4="TATA Order",'📋 ORDERS'!$D$4:$D$675,IF($B$4="Vulcan PO",'📋 ORDERS'!$E$4:$E$675,'📋 ORDERS'!$Q$4:$Q$675)))=$K$4),12),0)=0,"",IFERROR(INDEX('📋 ORDERS'!$R$4:$R$675,IFERROR(_xludf.aggregate(15,6,(ROW('📋 ORDERS'!$B$4:$B$675)-3)/(IF($B$4="SKF Order",'📋 ORDERS'!$C$4:$C$675,IF($B$4="TATA Order",'📋 ORDERS'!$D$4:$D$675,IF($B$4="Vulcan PO",'📋 ORDERS'!$E$4:$E$675,'📋 ORDERS'!$Q$4:$Q$675)))=$K$4),12),0)),"")) | J34: =IF(IFERROR(_xludf.aggregate(15,6,(ROW('📋 ORDERS'!$B$4:$B$675)-3)/(IF($B$4="SKF Order",'📋 ORDERS'!$C$4:$C$675,IF($B$4="TATA Order",'📋 ORDERS'!$D$4:$D$675,IF($B$4="Vulcan PO",'📋 ORDERS'!$E$4:$E$675,'📋 ORDERS'!$Q$4:$Q$675)))=$K$4),12),0)=0,"",IFERROR(INDEX('📋 ORDERS'!$S$4:$S$675,IFERROR(_xludf.aggregate(15,6,(ROW('📋 ORDERS'!$B$4:$B$675)-3)/(IF($B$4="SKF Order",'📋 ORDERS'!$C$4:$C$675,IF($B$4="TATA Order",'📋 ORDERS'!$D$4:$D$675,IF($B$4="Vulcan PO",'📋 ORDERS'!$E$4:$E$675,'📋 ORDERS'!$Q$4:$Q$675)))=$K$4),12),0)),""))
B35: =IF(IFERROR(_xludf.aggregate(15,6,(ROW('📋 ORDERS'!$B$4:$B$675)-3)/(IF($B$4="SKF Order",'📋 ORDERS'!$C$4:$C$675,IF($B$4="TATA Order",'📋 ORDERS'!$D$4:$D$675,IF($B$4="Vulcan PO",'📋 ORDERS'!$E$4:$E$675,'📋 ORDERS'!$Q$4:$Q$675)))=$K$4),13),0)=0,"",13) | C35: =IF(IFERROR(_xludf.aggregate(15,6,(ROW('📋 ORDERS'!$B$4:$B$675)-3)/(IF($B$4="SKF Order",'📋 ORDERS'!$C$4:$C$675,IF($B$4="TATA Order",'📋 ORDERS'!$D$4:$D$675,IF($B$4="Vulcan PO",'📋 ORDERS'!$E$4:$E$675,'📋 ORDERS'!$Q$4:$Q$675)))=$K$4),13),0)=0,"",IFERROR(INDEX('📋 ORDERS'!$C$4:$C$675,IFERROR(_xludf.aggregate(15,6,(ROW('📋 ORDERS'!$B$4:$B$675)-3)/(IF($B$4="SKF Order",'📋 ORDERS'!$C$4:$C$675,IF($B$4="TATA Order",'📋 ORDERS'!$D$4:$D$675,IF($B$4="Vulcan PO",'📋 ORDERS'!$E$4:$E$675,'📋 ORDERS'!$Q$4:$Q$675)))=$K$4),13),0)),"")) | D35: =IF(IFERROR(_xludf.aggregate(15,6,(ROW('📋 ORDERS'!$B$4:$B$675)-3)/(IF($B$4="SKF Order",'📋 ORDERS'!$C$4:$C$675,IF($B$4="TATA Order",'📋 ORDERS'!$D$4:$D$675,IF($B$4="Vulcan PO",'📋 ORDERS'!$E$4:$E$675,'📋 ORDERS'!$Q$4:$Q$675)))=$K$4),13),0)=0,"",IFERROR(INDEX('📋 ORDERS'!$G$4:$G$675,IFERROR(_xludf.aggregate(15,6,(ROW('📋 ORDERS'!$B$4:$B$675)-3)/(IF($B$4="SKF Order",'📋 ORDERS'!$C$4:$C$675,IF($B$4="TATA Order",'📋 ORDERS'!$D$4:$D$675,IF($B$4="Vulcan PO",'📋 ORDERS'!$E$4:$E$675,'📋 ORDERS'!$Q$4:$Q$675)))=$K$4),13),0)),"")) | F35: =IF(IFERROR(_xludf.aggregate(15,6,(ROW('📋 ORDERS'!$B$4:$B$675)-3)/(IF($B$4="SKF Order",'📋 ORDERS'!$C$4:$C$675,IF($B$4="TATA Order",'📋 ORDERS'!$D$4:$D$675,IF($B$4="Vulcan PO",'📋 ORDERS'!$E$4:$E$675,'📋 ORDERS'!$Q$4:$Q$675)))=$K$4),13),0)=0,"",IFERROR(INDEX('📋 ORDERS'!$K$4:$K$675,IFERROR(_xludf.aggregate(15,6,(ROW('📋 ORDERS'!$B$4:$B$675)-3)/(IF($B$4="SKF Order",'📋 ORDERS'!$C$4:$C$675,IF($B$4="TATA Order",'📋 ORDERS'!$D$4:$D$675,IF($B$4="Vulcan PO",'📋 ORDERS'!$E$4:$E$675,'📋 ORDERS'!$Q$4:$Q$675)))=$K$4),13),0)),"")) | G35: =IF(IFERROR(_xludf.aggregate(15,6,(ROW('📋 ORDERS'!$B$4:$B$675)-3)/(IF($B$4="SKF Order",'📋 ORDERS'!$C$4:$C$675,IF($B$4="TATA Order",'📋 ORDERS'!$D$4:$D$675,IF($B$4="Vulcan PO",'📋 ORDERS'!$E$4:$E$675,'📋 ORDERS'!$Q$4:$Q$675)))=$K$4),13),0)=0,"",IFERROR(INDEX('📋 ORDERS'!$L$4:$L$675,IFERROR(_xludf.aggregate(15,6,(ROW('📋 ORDERS'!$B$4:$B$675)-3)/(IF($B$4="SKF Order",'📋 ORDERS'!$C$4:$C$675,IF($B$4="TATA Order",'📋 ORDERS'!$D$4:$D$675,IF($B$4="Vulcan PO",'📋 ORDERS'!$E$4:$E$675,'📋 ORDERS'!$Q$4:$Q$675)))=$K$4),13),0)),"")) | H35: =IF(IFERROR(_xludf.aggregate(15,6,(ROW('📋 ORDERS'!$B$4:$B$675)-3)/(IF($B$4="SKF Order",'📋 ORDERS'!$C$4:$C$675,IF($B$4="TATA Order",'📋 ORDERS'!$D$4:$D$675,IF($B$4="Vulcan PO",'📋 ORDERS'!$E$4:$E$675,'📋 ORDERS'!$Q$4:$Q$675)))=$K$4),13),0)=0,"",IFERROR(INDEX('📋 ORDERS'!$M$4:$M$675,IFERROR(_xludf.aggregate(15,6,(ROW('📋 ORDERS'!$B$4:$B$675)-3)/(IF($B$4="SKF Order",'📋 ORDERS'!$C$4:$C$675,IF($B$4="TATA Order",'📋 ORDERS'!$D$4:$D$675,IF($B$4="Vulcan PO",'📋 ORDERS'!$E$4:$E$675,'📋 ORDERS'!$Q$4:$Q$675)))=$K$4),13),0)),"")) | I35: =IF(IFERROR(_xludf.aggregate(15,6,(ROW('📋 ORDERS'!$B$4:$B$675)-3)/(IF($B$4="SKF Order",'📋 ORDERS'!$C$4:$C$675,IF($B$4="TATA Order",'📋 ORDERS'!$D$4:$D$675,IF($B$4="Vulcan PO",'📋 ORDERS'!$E$4:$E$675,'📋 ORDERS'!$Q$4:$Q$675)))=$K$4),13),0)=0,"",IFERROR(INDEX('📋 ORDERS'!$R$4:$R$675,IFERROR(_xludf.aggregate(15,6,(ROW('📋 ORDERS'!$B$4:$B$675)-3)/(IF($B$4="SKF Order",'📋 ORDERS'!$C$4:$C$675,IF($B$4="TATA Order",'📋 ORDERS'!$D$4:$D$675,IF($B$4="Vulcan PO",'📋 ORDERS'!$E$4:$E$675,'📋 ORDERS'!$Q$4:$Q$675)))=$K$4),13),0)),"")) | J35: =IF(IFERROR(_xludf.aggregate(15,6,(ROW('📋 ORDERS'!$B$4:$B$675)-3)/(IF($B$4="SKF Order",'📋 ORDERS'!$C$4:$C$675,IF($B$4="TATA Order",'📋 ORDERS'!$D$4:$D$675,IF($B$4="Vulcan PO",'📋 ORDERS'!$E$4:$E$675,'📋 ORDERS'!$Q$4:$Q$675)))=$K$4),13),0)=0,"",IFERROR(INDEX('📋 ORDERS'!$S$4:$S$675,IFERROR(_xludf.aggregate(15,6,(ROW('📋 ORDERS'!$B$4:$B$675)-3)/(IF($B$4="SKF Order",'📋 ORDERS'!$C$4:$C$675,IF($B$4="TATA Order",'📋 ORDERS'!$D$4:$D$675,IF($B$4="Vulcan PO",'📋 ORDERS'!$E$4:$E$675,'📋 ORDERS'!$Q$4:$Q$675)))=$K$4),13),0)),""))
B36: =IF(IFERROR(_xludf.aggregate(15,6,(ROW('📋 ORDERS'!$B$4:$B$675)-3)/(IF($B$4="SKF Order",'📋 ORDERS'!$C$4:$C$675,IF($B$4="TATA Order",'📋 ORDERS'!$D$4:$D$675,IF($B$4="Vulcan PO",'📋 ORDERS'!$E$4:$E$675,'📋 ORDERS'!$Q$4:$Q$675)))=$K$4),14),0)=0,"",14) | C36: =IF(IFERROR(_xludf.aggregate(15,6,(ROW('📋 ORDERS'!$B$4:$B$675)-3)/(IF($B$4="SKF Order",'📋 ORDERS'!$C$4:$C$675,IF($B$4="TATA Order",'📋 ORDERS'!$D$4:$D$675,IF($B$4="Vulcan PO",'📋 ORDERS'!$E$4:$E$675,'📋 ORDERS'!$Q$4:$Q$675)))=$K$4),14),0)=0,"",IFERROR(INDEX('📋 ORDERS'!$C$4:$C$675,IFERROR(_xludf.aggregate(15,6,(ROW('📋 ORDERS'!$B$4:$B$675)-3)/(IF($B$4="SKF Order",'📋 ORDERS'!$C$4:$C$675,IF($B$4="TATA Order",'📋 ORDERS'!$D$4:$D$675,IF($B$4="Vulcan PO",'📋 ORDERS'!$E$4:$E$675,'📋 ORDERS'!$Q$4:$Q$675)))=$K$4),14),0)),"")) | D36: =IF(IFERROR(_xludf.aggregate(15,6,(ROW('📋 ORDERS'!$B$4:$B$675)-3)/(IF($B$4="SKF Order",'📋 ORDERS'!$C$4:$C$675,IF($B$4="TATA Order",'📋 ORDERS'!$D$4:$D$675,IF($B$4="Vulcan PO",'📋 ORDERS'!$E$4:$E$675,'📋 ORDERS'!$Q$4:$Q$675)))=$K$4),14),0)=0,"",IFERROR(INDEX('📋 ORDERS'!$G$4:$G$675,IFERROR(_xludf.aggregate(15,6,(ROW('📋 ORDERS'!$B$4:$B$675)-3)/(IF($B$4="SKF Order",'📋 ORDERS'!$C$4:$C$675,IF($B$4="TATA Order",'📋 ORDERS'!$D$4:$D$675,IF($B$4="Vulcan PO",'📋 ORDERS'!$E$4:$E$675,'📋 ORDERS'!$Q$4:$Q$675)))=$K$4),14),0)),"")) | F36: =IF(IFERROR(_xludf.aggregate(15,6,(ROW('📋 ORDERS'!$B$4:$B$675)-3)/(IF($B$4="SKF Order",'📋 ORDERS'!$C$4:$C$675,IF($B$4="TATA Order",'📋 ORDERS'!$D$4:$D$675,IF($B$4="Vulcan PO",'📋 ORDERS'!$E$4:$E$675,'📋 ORDERS'!$Q$4:$Q$675)))=$K$4),14),0)=0,"",IFERROR(INDEX('📋 ORDERS'!$K$4:$K$675,IFERROR(_xludf.aggregate(15,6,(ROW('📋 ORDERS'!$B$4:$B$675)-3)/(IF($B$4="SKF Order",'📋 ORDERS'!$C$4:$C$675,IF($B$4="TATA Order",'📋 ORDERS'!$D$4:$D$675,IF($B$4="Vulcan PO",'📋 ORDERS'!$E$4:$E$675,'📋 ORDERS'!$Q$4:$Q$675)))=$K$4),14),0)),"")) | G36: =IF(IFERROR(_xludf.aggregate(15,6,(ROW('📋 ORDERS'!$B$4:$B$675)-3)/(IF($B$4="SKF Order",'📋 ORDERS'!$C$4:$C$675,IF($B$4="TATA Order",'📋 ORDERS'!$D$4:$D$675,IF($B$4="Vulcan PO",'📋 ORDERS'!$E$4:$E$675,'📋 ORDERS'!$Q$4:$Q$675)))=$K$4),14),0)=0,"",IFERROR(INDEX('📋 ORDERS'!$L$4:$L$675,IFERROR(_xludf.aggregate(15,6,(ROW('📋 ORDERS'!$B$4:$B$675)-3)/(IF($B$4="SKF Order",'📋 ORDERS'!$C$4:$C$675,IF($B$4="TATA Order",'📋 ORDERS'!$D$4:$D$675,IF($B$4="Vulcan PO",'📋 ORDERS'!$E$4:$E$675,'📋 ORDERS'!$Q$4:$Q$675)))=$K$4),14),0)),"")) | H36: =IF(IFERROR(_xludf.aggregate(15,6,(ROW('📋 ORDERS'!$B$4:$B$675)-3)/(IF($B$4="SKF Order",'📋 ORDERS'!$C$4:$C$675,IF($B$4="TATA Order",'📋 ORDERS'!$D$4:$D$675,IF($B$4="Vulcan PO",'📋 ORDERS'!$E$4:$E$675,'📋 ORDERS'!$Q$4:$Q$675)))=$K$4),14),0)=0,"",IFERROR(INDEX('📋 ORDERS'!$M$4:$M$675,IFERROR(_xludf.aggregate(15,6,(ROW('📋 ORDERS'!$B$4:$B$675)-3)/(IF($B$4="SKF Order",'📋 ORDERS'!$C$4:$C$675,IF($B$4="TATA Order",'📋 ORDERS'!$D$4:$D$675,IF($B$4="Vulcan PO",'📋 ORDERS'!$E$4:$E$675,'📋 ORDERS'!$Q$4:$Q$675)))=$K$4),14),0)),"")) | I36: =IF(IFERROR(_xludf.aggregate(15,6,(ROW('📋 ORDERS'!$B$4:$B$675)-3)/(IF($B$4="SKF Order",'📋 ORDERS'!$C$4:$C$675,IF($B$4="TATA Order",'📋 ORDERS'!$D$4:$D$675,IF($B$4="Vulcan PO",'📋 ORDERS'!$E$4:$E$675,'📋 ORDERS'!$Q$4:$Q$675)))=$K$4),14),0)=0,"",IFERROR(INDEX('📋 ORDERS'!$R$4:$R$675,IFERROR(_xludf.aggregate(15,6,(ROW('📋 ORDERS'!$B$4:$B$675)-3)/(IF($B$4="SKF Order",'📋 ORDERS'!$C$4:$C$675,IF($B$4="TATA Order",'📋 ORDERS'!$D$4:$D$675,IF($B$4="Vulcan PO",'📋 ORDERS'!$E$4:$E$675,'📋 ORDERS'!$Q$4:$Q$675)))=$K$4),14),0)),"")) | J36: =IF(IFERROR(_xludf.aggregate(15,6,(ROW('📋 ORDERS'!$B$4:$B$675)-3)/(IF($B$4="SKF Order",'📋 ORDERS'!$C$4:$C$675,IF($B$4="TATA Order",'📋 ORDERS'!$D$4:$D$675,IF($B$4="Vulcan PO",'📋 ORDERS'!$E$4:$E$675,'📋 ORDERS'!$Q$4:$Q$675)))=$K$4),14),0)=0,"",IFERROR(INDEX('📋 ORDERS'!$S$4:$S$675,IFERROR(_xludf.aggregate(15,6,(ROW('📋 ORDERS'!$B$4:$B$675)-3)/(IF($B$4="SKF Order",'📋 ORDERS'!$C$4:$C$675,IF($B$4="TATA Order",'📋 ORDERS'!$D$4:$D$675,IF($B$4="Vulcan PO",'📋 ORDERS'!$E$4:$E$675,'📋 ORDERS'!$Q$4:$Q$675)))=$K$4),14),0)),""))
B37: =IF(IFERROR(_xludf.aggregate(15,6,(ROW('📋 ORDERS'!$B$4:$B$675)-3)/(IF($B$4="SKF Order",'📋 ORDERS'!$C$4:$C$675,IF($B$4="TATA Order",'📋 ORDERS'!$D$4:$D$675,IF($B$4="Vulcan PO",'📋 ORDERS'!$E$4:$E$675,'📋 ORDERS'!$Q$4:$Q$675)))=$K$4),15),0)=0,"",15) | C37: =IF(IFERROR(_xludf.aggregate(15,6,(ROW('📋 ORDERS'!$B$4:$B$675)-3)/(IF($B$4="SKF Order",'📋 ORDERS'!$C$4:$C$675,IF($B$4="TATA Order",'📋 ORDERS'!$D$4:$D$675,IF($B$4="Vulcan PO",'📋 ORDERS'!$E$4:$E$675,'📋 ORDERS'!$Q$4:$Q$675)))=$K$4),15),0)=0,"",IFERROR(INDEX('📋 ORDERS'!$C$4:$C$675,IFERROR(_xludf.aggregate(15,6,(ROW('📋 ORDERS'!$B$4:$B$675)-3)/(IF($B$4="SKF Order",'📋 ORDERS'!$C$4:$C$675,IF($B$4="TATA Order",'📋 ORDERS'!$D$4:$D$675,IF($B$4="Vulcan PO",'📋 ORDERS'!$E$4:$E$675,'📋 ORDERS'!$Q$4:$Q$675)))=$K$4),15),0)),"")) | D37: =IF(IFERROR(_xludf.aggregate(15,6,(ROW('📋 ORDERS'!$B$4:$B$675)-3)/(IF($B$4="SKF Order",'📋 ORDERS'!$C$4:$C$675,IF($B$4="TATA Order",'📋 ORDERS'!$D$4:$D$675,IF($B$4="Vulcan PO",'📋 ORDERS'!$E$4:$E$675,'📋 ORDERS'!$Q$4:$Q$675)))=$K$4),15),0)=0,"",IFERROR(INDEX('📋 ORDERS'!$G$4:$G$675,IFERROR(_xludf.aggregate(15,6,(ROW('📋 ORDERS'!$B$4:$B$675)-3)/(IF($B$4="SKF Order",'📋 ORDERS'!$C$4:$C$675,IF($B$4="TATA Order",'📋 ORDERS'!$D$4:$D$675,IF($B$4="Vulcan PO",'📋 ORDERS'!$E$4:$E$675,'📋 ORDERS'!$Q$4:$Q$675)))=$K$4),15),0)),"")) | F37: =IF(IFERROR(_xludf.aggregate(15,6,(ROW('📋 ORDERS'!$B$4:$B$675)-3)/(IF($B$4="SKF Order",'📋 ORDERS'!$C$4:$C$675,IF($B$4="TATA Order",'📋 ORDERS'!$D$4:$D$675,IF($B$4="Vulcan PO",'📋 ORDERS'!$E$4:$E$675,'📋 ORDERS'!$Q$4:$Q$675)))=$K$4),15),0)=0,"",IFERROR(INDEX('📋 ORDERS'!$K$4:$K$675,IFERROR(_xludf.aggregate(15,6,(ROW('📋 ORDERS'!$B$4:$B$675)-3)/(IF($B$4="SKF Order",'📋 ORDERS'!$C$4:$C$675,IF($B$4="TATA Order",'📋 ORDERS'!$D$4:$D$675,IF($B$4="Vulcan PO",'📋 ORDERS'!$E$4:$E$675,'📋 ORDERS'!$Q$4:$Q$675)))=$K$4),15),0)),"")) | G37: =IF(IFERROR(_xludf.aggregate(15,6,(ROW('📋 ORDERS'!$B$4:$B$675)-3)/(IF($B$4="SKF Order",'📋 ORDERS'!$C$4:$C$675,IF($B$4="TATA Order",'📋 ORDERS'!$D$4:$D$675,IF($B$4="Vulcan PO",'📋 ORDERS'!$E$4:$E$675,'📋 ORDERS'!$Q$4:$Q$675)))=$K$4),15),0)=0,"",IFERROR(INDEX('📋 ORDERS'!$L$4:$L$675,IFERROR(_xludf.aggregate(15,6,(ROW('📋 ORDERS'!$B$4:$B$675)-3)/(IF($B$4="SKF Order",'📋 ORDERS'!$C$4:$C$675,IF($B$4="TATA Order",'📋 ORDERS'!$D$4:$D$675,IF($B$4="Vulcan PO",'📋 ORDERS'!$E$4:$E$675,'📋 ORDERS'!$Q$4:$Q$675)))=$K$4),15),0)),"")) | H37: =IF(IFERROR(_xludf.aggregate(15,6,(ROW('📋 ORDERS'!$B$4:$B$675)-3)/(IF($B$4="SKF Order",'📋 ORDERS'!$C$4:$C$675,IF($B$4="TATA Order",'📋 ORDERS'!$D$4:$D$675,IF($B$4="Vulcan PO",'📋 ORDERS'!$E$4:$E$675,'📋 ORDERS'!$Q$4:$Q$675)))=$K$4),15),0)=0,"",IFERROR(INDEX('📋 ORDERS'!$M$4:$M$675,IFERROR(_xludf.aggregate(15,6,(ROW('📋 ORDERS'!$B$4:$B$675)-3)/(IF($B$4="SKF Order",'📋 ORDERS'!$C$4:$C$675,IF($B$4="TATA Order",'📋 ORDERS'!$D$4:$D$675,IF($B$4="Vulcan PO",'📋 ORDERS'!$E$4:$E$675,'📋 ORDERS'!$Q$4:$Q$675)))=$K$4),15),0)),"")) | I37: =IF(IFERROR(_xludf.aggregate(15,6,(ROW('📋 ORDERS'!$B$4:$B$675)-3)/(IF($B$4="SKF Order",'📋 ORDERS'!$C$4:$C$675,IF($B$4="TATA Order",'📋 ORDERS'!$D$4:$D$675,IF($B$4="Vulcan PO",'📋 ORDERS'!$E$4:$E$675,'📋 ORDERS'!$Q$4:$Q$675)))=$K$4),15),0)=0,"",IFERROR(INDEX('📋 ORDERS'!$R$4:$R$675,IFERROR(_xludf.aggregate(15,6,(ROW('📋 ORDERS'!$B$4:$B$675)-3)/(IF($B$4="SKF Order",'📋 ORDERS'!$C$4:$C$675,IF($B$4="TATA Order",'📋 ORDERS'!$D$4:$D$675,IF($B$4="Vulcan PO",'📋 ORDERS'!$E$4:$E$675,'📋 ORDERS'!$Q$4:$Q$675)))=$K$4),15),0)),"")) | J37: =IF(IFERROR(_xludf.aggregate(15,6,(ROW('📋 ORDERS'!$B$4:$B$675)-3)/(IF($B$4="SKF Order",'📋 ORDERS'!$C$4:$C$675,IF($B$4="TATA Order",'📋 ORDERS'!$D$4:$D$675,IF($B$4="Vulcan PO",'📋 ORDERS'!$E$4:$E$675,'📋 ORDERS'!$Q$4:$Q$675)))=$K$4),15),0)=0,"",IFERROR(INDEX('📋 ORDERS'!$S$4:$S$675,IFERROR(_xludf.aggregate(15,6,(ROW('📋 ORDERS'!$B$4:$B$675)-3)/(IF($B$4="SKF Order",'📋 ORDERS'!$C$4:$C$675,IF($B$4="TATA Order",'📋 ORDERS'!$D$4:$D$675,IF($B$4="Vulcan PO",'📋 ORDERS'!$E$4:$E$675,'📋 ORDERS'!$Q$4:$Q$675)))=$K$4),15),0)),""))
B38: =IF(IFERROR(_xludf.aggregate(15,6,(ROW('📋 ORDERS'!$B$4:$B$675)-3)/(IF($B$4="SKF Order",'📋 ORDERS'!$C$4:$C$675,IF($B$4="TATA Order",'📋 ORDERS'!$D$4:$D$675,IF($B$4="Vulcan PO",'📋 ORDERS'!$E$4:$E$675,'📋 ORDERS'!$Q$4:$Q$675)))=$K$4),16),0)=0,"",16) | C38: =IF(IFERROR(_xludf.aggregate(15,6,(ROW('📋 ORDERS'!$B$4:$B$675)-3)/(IF($B$4="SKF Order",'📋 ORDERS'!$C$4:$C$675,IF($B$4="TATA Order",'📋 ORDERS'!$D$4:$D$675,IF($B$4="Vulcan PO",'📋 ORDERS'!$E$4:$E$675,'📋 ORDERS'!$Q$4:$Q$675)))=$K$4),16),0)=0,"",IFERROR(INDEX('📋 ORDERS'!$C$4:$C$675,IFERROR(_xludf.aggregate(15,6,(ROW('📋 ORDERS'!$B$4:$B$675)-3)/(IF($B$4="SKF Order",'📋 ORDERS'!$C$4:$C$675,IF($B$4="TATA Order",'📋 ORDERS'!$D$4:$D$675,IF($B$4="Vulcan PO",'📋 ORDERS'!$E$4:$E$675,'📋 ORDERS'!$Q$4:$Q$675)))=$K$4),16),0)),"")) | D38: =IF(IFERROR(_xludf.aggregate(15,6,(ROW('📋 ORDERS'!$B$4:$B$675)-3)/(IF($B$4="SKF Order",'📋 ORDERS'!$C$4:$C$675,IF($B$4="TATA Order",'📋 ORDERS'!$D$4:$D$675,IF($B$4="Vulcan PO",'📋 ORDERS'!$E$4:$E$675,'📋 ORDERS'!$Q$4:$Q$675)))=$K$4),16),0)=0,"",IFERROR(INDEX('📋 ORDERS'!$G$4:$G$675,IFERROR(_xludf.aggregate(15,6,(ROW('📋 ORDERS'!$B$4:$B$675)-3)/(IF($B$4="SKF Order",'📋 ORDERS'!$C$4:$C$675,IF($B$4="TATA Order",'📋 ORDERS'!$D$4:$D$675,IF($B$4="Vulcan PO",'📋 ORDERS'!$E$4:$E$675,'📋 ORDERS'!$Q$4:$Q$675)))=$K$4),16),0)),"")) | F38: =IF(IFERROR(_xludf.aggregate(15,6,(ROW('📋 ORDERS'!$B$4:$B$675)-3)/(IF($B$4="SKF Order",'📋 ORDERS'!$C$4:$C$675,IF($B$4="TATA Order",'📋 ORDERS'!$D$4:$D$675,IF($B$4="Vulcan PO",'📋 ORDERS'!$E$4:$E$675,'📋 ORDERS'!$Q$4:$Q$675)))=$K$4),16),0)=0,"",IFERROR(INDEX('📋 ORDERS'!$K$4:$K$675,IFERROR(_xludf.aggregate(15,6,(ROW('📋 ORDERS'!$B$4:$B$675)-3)/(IF($B$4="SKF Order",'📋 ORDERS'!$C$4:$C$675,IF($B$4="TATA Order",'📋 ORDERS'!$D$4:$D$675,IF($B$4="Vulcan PO",'📋 ORDERS'!$E$4:$E$675,'📋 ORDERS'!$Q$4:$Q$675)))=$K$4),16),0)),"")) | G38: =IF(IFERROR(_xludf.aggregate(15,6,(ROW('📋 ORDERS'!$B$4:$B$675)-3)/(IF($B$4="SKF Order",'📋 ORDERS'!$C$4:$C$675,IF($B$4="TATA Order",'📋 ORDERS'!$D$4:$D$675,IF($B$4="Vulcan PO",'📋 ORDERS'!$E$4:$E$675,'📋 ORDERS'!$Q$4:$Q$675)))=$K$4),16),0)=0,"",IFERROR(INDEX('📋 ORDERS'!$L$4:$L$675,IFERROR(_xludf.aggregate(15,6,(ROW('📋 ORDERS'!$B$4:$B$675)-3)/(IF($B$4="SKF Order",'📋 ORDERS'!$C$4:$C$675,IF($B$4="TATA Order",'📋 ORDERS'!$D$4:$D$675,IF($B$4="Vulcan PO",'📋 ORDERS'!$E$4:$E$675,'📋 ORDERS'!$Q$4:$Q$675)))=$K$4),16),0)),"")) | H38: =IF(IFERROR(_xludf.aggregate(15,6,(ROW('📋 ORDERS'!$B$4:$B$675)-3)/(IF($B$4="SKF Order",'📋 ORDERS'!$C$4:$C$675,IF($B$4="TATA Order",'📋 ORDERS'!$D$4:$D$675,IF($B$4="Vulcan PO",'📋 ORDERS'!$E$4:$E$675,'📋 ORDERS'!$Q$4:$Q$675)))=$K$4),16),0)=0,"",IFERROR(INDEX('📋 ORDERS'!$M$4:$M$675,IFERROR(_xludf.aggregate(15,6,(ROW('📋 ORDERS'!$B$4:$B$675)-3)/(IF($B$4="SKF Order",'📋 ORDERS'!$C$4:$C$675,IF($B$4="TATA Order",'📋 ORDERS'!$D$4:$D$675,IF($B$4="Vulcan PO",'📋 ORDERS'!$E$4:$E$675,'📋 ORDERS'!$Q$4:$Q$675)))=$K$4),16),0)),"")) | I38: =IF(IFERROR(_xludf.aggregate(15,6,(ROW('📋 ORDERS'!$B$4:$B$675)-3)/(IF($B$4="SKF Order",'📋 ORDERS'!$C$4:$C$675,IF($B$4="TATA Order",'📋 ORDERS'!$D$4:$D$675,IF($B$4="Vulcan PO",'📋 ORDERS'!$E$4:$E$675,'📋 ORDERS'!$Q$4:$Q$675)))=$K$4),16),0)=0,"",IFERROR(INDEX('📋 ORDERS'!$R$4:$R$675,IFERROR(_xludf.aggregate(15,6,(ROW('📋 ORDERS'!$B$4:$B$675)-3)/(IF($B$4="SKF Order",'📋 ORDERS'!$C$4:$C$675,IF($B$4="TATA Order",'📋 ORDERS'!$D$4:$D$675,IF($B$4="Vulcan PO",'📋 ORDERS'!$E$4:$E$675,'📋 ORDERS'!$Q$4:$Q$675)))=$K$4),16),0)),"")) | J38: =IF(IFERROR(_xludf.aggregate(15,6,(ROW('📋 ORDERS'!$B$4:$B$675)-3)/(IF($B$4="SKF Order",'📋 ORDERS'!$C$4:$C$675,IF($B$4="TATA Order",'📋 ORDERS'!$D$4:$D$675,IF($B$4="Vulcan PO",'📋 ORDERS'!$E$4:$E$675,'📋 ORDERS'!$Q$4:$Q$675)))=$K$4),16),0)=0,"",IFERROR(INDEX('📋 ORDERS'!$S$4:$S$675,IFERROR(_xludf.aggregate(15,6,(ROW('📋 ORDERS'!$B$4:$B$675)-3)/(IF($B$4="SKF Order",'📋 ORDERS'!$C$4:$C$675,IF($B$4="TATA Order",'📋 ORDERS'!$D$4:$D$675,IF($B$4="Vulcan PO",'📋 ORDERS'!$E$4:$E$675,'📋 ORDERS'!$Q$4:$Q$675)))=$K$4),16),0)),""))
B39: =IF(IFERROR(_xludf.aggregate(15,6,(ROW('📋 ORDERS'!$B$4:$B$675)-3)/(IF($B$4="SKF Order",'📋 ORDERS'!$C$4:$C$675,IF($B$4="TATA Order",'📋 ORDERS'!$D$4:$D$675,IF($B$4="Vulcan PO",'📋 ORDERS'!$E$4:$E$675,'📋 ORDERS'!$Q$4:$Q$675)))=$K$4),17),0)=0,"",17) | C39: =IF(IFERROR(_xludf.aggregate(15,6,(ROW('📋 ORDERS'!$B$4:$B$675)-3)/(IF($B$4="SKF Order",'📋 ORDERS'!$C$4:$C$675,IF($B$4="TATA Order",'📋 ORDERS'!$D$4:$D$675,IF($B$4="Vulcan PO",'📋 ORDERS'!$E$4:$E$675,'📋 ORDERS'!$Q$4:$Q$675)))=$K$4),17),0)=0,"",IFERROR(INDEX('📋 ORDERS'!$C$4:$C$675,IFERROR(_xludf.aggregate(15,6,(ROW('📋 ORDERS'!$B$4:$B$675)-3)/(IF($B$4="SKF Order",'📋 ORDERS'!$C$4:$C$675,IF($B$4="TATA Order",'📋 ORDERS'!$D$4:$D$675,IF($B$4="Vulcan PO",'📋 ORDERS'!$E$4:$E$675,'📋 ORDERS'!$Q$4:$Q$675)))=$K$4),17),0)),"")) | D39: =IF(IFERROR(_xludf.aggregate(15,6,(ROW('📋 ORDERS'!$B$4:$B$675)-3)/(IF($B$4="SKF Order",'📋 ORDERS'!$C$4:$C$675,IF($B$4="TATA Order",'📋 ORDERS'!$D$4:$D$675,IF($B$4="Vulcan PO",'📋 ORDERS'!$E$4:$E$675,'📋 ORDERS'!$Q$4:$Q$675)))=$K$4),17),0)=0,"",IFERROR(INDEX('📋 ORDERS'!$G$4:$G$675,IFERROR(_xludf.aggregate(15,6,(ROW('📋 ORDERS'!$B$4:$B$675)-3)/(IF($B$4="SKF Order",'📋 ORDERS'!$C$4:$C$675,IF($B$4="TATA Order",'📋 ORDERS'!$D$4:$D$675,IF($B$4="Vulcan PO",'📋 ORDERS'!$E$4:$E$675,'📋 ORDERS'!$Q$4:$Q$675)))=$K$4),17),0)),"")) | F39: =IF(IFERROR(_xludf.aggregate(15,6,(ROW('📋 ORDERS'!$B$4:$B$675)-3)/(IF($B$4="SKF Order",'📋 ORDERS'!$C$4:$C$675,IF($B$4="TATA Order",'📋 ORDERS'!$D$4:$D$675,IF($B$4="Vulcan PO",'📋 ORDERS'!$E$4:$E$675,'📋 ORDERS'!$Q$4:$Q$675)))=$K$4),17),0)=0,"",IFERROR(INDEX('📋 ORDERS'!$K$4:$K$675,IFERROR(_xludf.aggregate(15,6,(ROW('📋 ORDERS'!$B$4:$B$675)-3)/(IF($B$4="SKF Order",'📋 ORDERS'!$C$4:$C$675,IF($B$4="TATA Order",'📋 ORDERS'!$D$4:$D$675,IF($B$4="Vulcan PO",'📋 ORDERS'!$E$4:$E$675,'📋 ORDERS'!$Q$4:$Q$675)))=$K$4),17),0)),"")) | G39: =IF(IFERROR(_xludf.aggregate(15,6,(ROW('📋 ORDERS'!$B$4:$B$675)-3)/(IF($B$4="SKF Order",'📋 ORDERS'!$C$4:$C$675,IF($B$4="TATA Order",'📋 ORDERS'!$D$4:$D$675,IF($B$4="Vulcan PO",'📋 ORDERS'!$E$4:$E$675,'📋 ORDERS'!$Q$4:$Q$675)))=$K$4),17),0)=0,"",IFERROR(INDEX('📋 ORDERS'!$L$4:$L$675,IFERROR(_xludf.aggregate(15,6,(ROW('📋 ORDERS'!$B$4:$B$675)-3)/(IF($B$4="SKF Order",'📋 ORDERS'!$C$4:$C$675,IF($B$4="TATA Order",'📋 ORDERS'!$D$4:$D$675,IF($B$4="Vulcan PO",'📋 ORDERS'!$E$4:$E$675,'📋 ORDERS'!$Q$4:$Q$675)))=$K$4),17),0)),"")) | H39: =IF(IFERROR(_xludf.aggregate(15,6,(ROW('📋 ORDERS'!$B$4:$B$675)-3)/(IF($B$4="SKF Order",'📋 ORDERS'!$C$4:$C$675,IF($B$4="TATA Order",'📋 ORDERS'!$D$4:$D$675,IF($B$4="Vulcan PO",'📋 ORDERS'!$E$4:$E$675,'📋 ORDERS'!$Q$4:$Q$675)))=$K$4),17),0)=0,"",IFERROR(INDEX('📋 ORDERS'!$M$4:$M$675,IFERROR(_xludf.aggregate(15,6,(ROW('📋 ORDERS'!$B$4:$B$675)-3)/(IF($B$4="SKF Order",'📋 ORDERS'!$C$4:$C$675,IF($B$4="TATA Order",'📋 ORDERS'!$D$4:$D$675,IF($B$4="Vulcan PO",'📋 ORDERS'!$E$4:$E$675,'📋 ORDERS'!$Q$4:$Q$675)))=$K$4),17),0)),"")) | I39: =IF(IFERROR(_xludf.aggregate(15,6,(ROW('📋 ORDERS'!$B$4:$B$675)-3)/(IF($B$4="SKF Order",'📋 ORDERS'!$C$4:$C$675,IF($B$4="TATA Order",'📋 ORDERS'!$D$4:$D$675,IF($B$4="Vulcan PO",'📋 ORDERS'!$E$4:$E$675,'📋 ORDERS'!$Q$4:$Q$675)))=$K$4),17),0)=0,"",IFERROR(INDEX('📋 ORDERS'!$R$4:$R$675,IFERROR(_xludf.aggregate(15,6,(ROW('📋 ORDERS'!$B$4:$B$675)-3)/(IF($B$4="SKF Order",'📋 ORDERS'!$C$4:$C$675,IF($B$4="TATA Order",'📋 ORDERS'!$D$4:$D$675,IF($B$4="Vulcan PO",'📋 ORDERS'!$E$4:$E$675,'📋 ORDERS'!$Q$4:$Q$675)))=$K$4),17),0)),"")) | J39: =IF(IFERROR(_xludf.aggregate(15,6,(ROW('📋 ORDERS'!$B$4:$B$675)-3)/(IF($B$4="SKF Order",'📋 ORDERS'!$C$4:$C$675,IF($B$4="TATA Order",'📋 ORDERS'!$D$4:$D$675,IF($B$4="Vulcan PO",'📋 ORDERS'!$E$4:$E$675,'📋 ORDERS'!$Q$4:$Q$675)))=$K$4),17),0)=0,"",IFERROR(INDEX('📋 ORDERS'!$S$4:$S$675,IFERROR(_xludf.aggregate(15,6,(ROW('📋 ORDERS'!$B$4:$B$675)-3)/(IF($B$4="SKF Order",'📋 ORDERS'!$C$4:$C$675,IF($B$4="TATA Order",'📋 ORDERS'!$D$4:$D$675,IF($B$4="Vulcan PO",'📋 ORDERS'!$E$4:$E$675,'📋 ORDERS'!$Q$4:$Q$675)))=$K$4),17),0)),""))
B40: =IF(IFERROR(_xludf.aggregate(15,6,(ROW('📋 ORDERS'!$B$4:$B$675)-3)/(IF($B$4="SKF Order",'📋 ORDERS'!$C$4:$C$675,IF($B$4="TATA Order",'📋 ORDERS'!$D$4:$D$675,IF($B$4="Vulcan PO",'📋 ORDERS'!$E$4:$E$675,'📋 ORDERS'!$Q$4:$Q$675)))=$K$4),18),0)=0,"",18) | C40: =IF(IFERROR(_xludf.aggregate(15,6,(ROW('📋 ORDERS'!$B$4:$B$675)-3)/(IF($B$4="SKF Order",'📋 ORDERS'!$C$4:$C$675,IF($B$4="TATA Order",'📋 ORDERS'!$D$4:$D$675,IF($B$4="Vulcan PO",'📋 ORDERS'!$E$4:$E$675,'📋 ORDERS'!$Q$4:$Q$675)))=$K$4),18),0)=0,"",IFERROR(INDEX('📋 ORDERS'!$C$4:$C$675,IFERROR(_xludf.aggregate(15,6,(ROW('📋 ORDERS'!$B$4:$B$675)-3)/(IF($B$4="SKF Order",'📋 ORDERS'!$C$4:$C$675,IF($B$4="TATA Order",'📋 ORDERS'!$D$4:$D$675,IF($B$4="Vulcan PO",'📋 ORDERS'!$E$4:$E$675,'📋 ORDERS'!$Q$4:$Q$675)))=$K$4),18),0)),"")) | D40: =IF(IFERROR(_xludf.aggregate(15,6,(ROW('📋 ORDERS'!$B$4:$B$675)-3)/(IF($B$4="SKF Order",'📋 ORDERS'!$C$4:$C$675,IF($B$4="TATA Order",'📋 ORDERS'!$D$4:$D$675,IF($B$4="Vulcan PO",'📋 ORDERS'!$E$4:$E$675,'📋 ORDERS'!$Q$4:$Q$675)))=$K$4),18),0)=0,"",IFERROR(INDEX('📋 ORDERS'!$G$4:$G$675,IFERROR(_xludf.aggregate(15,6,(ROW('📋 ORDERS'!$B$4:$B$675)-3)/(IF($B$4="SKF Order",'📋 ORDERS'!$C$4:$C$675,IF($B$4="TATA Order",'📋 ORDERS'!$D$4:$D$675,IF($B$4="Vulcan PO",'📋 ORDERS'!$E$4:$E$675,'📋 ORDERS'!$Q$4:$Q$675)))=$K$4),18),0)),"")) | F40: =IF(IFERROR(_xludf.aggregate(15,6,(ROW('📋 ORDERS'!$B$4:$B$675)-3)/(IF($B$4="SKF Order",'📋 ORDERS'!$C$4:$C$675,IF($B$4="TATA Order",'📋 ORDERS'!$D$4:$D$675,IF($B$4="Vulcan PO",'📋 ORDERS'!$E$4:$E$675,'📋 ORDERS'!$Q$4:$Q$675)))=$K$4),18),0)=0,"",IFERROR(INDEX('📋 ORDERS'!$K$4:$K$675,IFERROR(_xludf.aggregate(15,6,(ROW('📋 ORDERS'!$B$4:$B$675)-3)/(IF($B$4="SKF Order",'📋 ORDERS'!$C$4:$C$675,IF($B$4="TATA Order",'📋 ORDERS'!$D$4:$D$675,IF($B$4="Vulcan PO",'📋 ORDERS'!$E$4:$E$675,'📋 ORDERS'!$Q$4:$Q$675)))=$K$4),18),0)),"")) | G40: =IF(IFERROR(_xludf.aggregate(15,6,(ROW('📋 ORDERS'!$B$4:$B$675)-3)/(IF($B$4="SKF Order",'📋 ORDERS'!$C$4:$C$675,IF($B$4="TATA Order",'📋 ORDERS'!$D$4:$D$675,IF($B$4="Vulcan PO",'📋 ORDERS'!$E$4:$E$675,'📋 ORDERS'!$Q$4:$Q$675)))=$K$4),18),0)=0,"",IFERROR(INDEX('📋 ORDERS'!$L$4:$L$675,IFERROR(_xludf.aggregate(15,6,(ROW('📋 ORDERS'!$B$4:$B$675)-3)/(IF($B$4="SKF Order",'📋 ORDERS'!$C$4:$C$675,IF($B$4="TATA Order",'📋 ORDERS'!$D$4:$D$675,IF($B$4="Vulcan PO",'📋 ORDERS'!$E$4:$E$675,'📋 ORDERS'!$Q$4:$Q$675)))=$K$4),18),0)),"")) | H40: =IF(IFERROR(_xludf.aggregate(15,6,(ROW('📋 ORDERS'!$B$4:$B$675)-3)/(IF($B$4="SKF Order",'📋 ORDERS'!$C$4:$C$675,IF($B$4="TATA Order",'📋 ORDERS'!$D$4:$D$675,IF($B$4="Vulcan PO",'📋 ORDERS'!$E$4:$E$675,'📋 ORDERS'!$Q$4:$Q$675)))=$K$4),18),0)=0,"",IFERROR(INDEX('📋 ORDERS'!$M$4:$M$675,IFERROR(_xludf.aggregate(15,6,(ROW('📋 ORDERS'!$B$4:$B$675)-3)/(IF($B$4="SKF Order",'📋 ORDERS'!$C$4:$C$675,IF($B$4="TATA Order",'📋 ORDERS'!$D$4:$D$675,IF($B$4="Vulcan PO",'📋 ORDERS'!$E$4:$E$675,'📋 ORDERS'!$Q$4:$Q$675)))=$K$4),18),0)),"")) | I40: =IF(IFERROR(_xludf.aggregate(15,6,(ROW('📋 ORDERS'!$B$4:$B$675)-3)/(IF($B$4="SKF Order",'📋 ORDERS'!$C$4:$C$675,IF($B$4="TATA Order",'📋 ORDERS'!$D$4:$D$675,IF($B$4="Vulcan PO",'📋 ORDERS'!$E$4:$E$675,'📋 ORDERS'!$Q$4:$Q$675)))=$K$4),18),0)=0,"",IFERROR(INDEX('📋 ORDERS'!$R$4:$R$675,IFERROR(_xludf.aggregate(15,6,(ROW('📋 ORDERS'!$B$4:$B$675)-3)/(IF($B$4="SKF Order",'📋 ORDERS'!$C$4:$C$675,IF($B$4="TATA Order",'📋 ORDERS'!$D$4:$D$675,IF($B$4="Vulcan PO",'📋 ORDERS'!$E$4:$E$675,'📋 ORDERS'!$Q$4:$Q$675)))=$K$4),18),0)),"")) | J40: =IF(IFERROR(_xludf.aggregate(15,6,(ROW('📋 ORDERS'!$B$4:$B$675)-3)/(IF($B$4="SKF Order",'📋 ORDERS'!$C$4:$C$675,IF($B$4="TATA Order",'📋 ORDERS'!$D$4:$D$675,IF($B$4="Vulcan PO",'📋 ORDERS'!$E$4:$E$675,'📋 ORDERS'!$Q$4:$Q$675)))=$K$4),18),0)=0,"",IFERROR(INDEX('📋 ORDERS'!$S$4:$S$675,IFERROR(_xludf.aggregate(15,6,(ROW('📋 ORDERS'!$B$4:$B$675)-3)/(IF($B$4="SKF Order",'📋 ORDERS'!$C$4:$C$675,IF($B$4="TATA Order",'📋 ORDERS'!$D$4:$D$675,IF($B$4="Vulcan PO",'📋 ORDERS'!$E$4:$E$675,'📋 ORDERS'!$Q$4:$Q$675)))=$K$4),18),0)),""))
B41: =IF(IFERROR(_xludf.aggregate(15,6,(ROW('📋 ORDERS'!$B$4:$B$675)-3)/(IF($B$4="SKF Order",'📋 ORDERS'!$C$4:$C$675,IF($B$4="TATA Order",'📋 ORDERS'!$D$4:$D$675,IF($B$4="Vulcan PO",'📋 ORDERS'!$E$4:$E$675,'📋 ORDERS'!$Q$4:$Q$675)))=$K$4),19),0)=0,"",19) | C41: =IF(IFERROR(_xludf.aggregate(15,6,(ROW('📋 ORDERS'!$B$4:$B$675)-3)/(IF($B$4="SKF Order",'📋 ORDERS'!$C$4:$C$675,IF($B$4="TATA Order",'📋 ORDERS'!$D$4:$D$675,IF($B$4="Vulcan PO",'📋 ORDERS'!$E$4:$E$675,'📋 ORDERS'!$Q$4:$Q$675)))=$K$4),19),0)=0,"",IFERROR(INDEX('📋 ORDERS'!$C$4:$C$675,IFERROR(_xludf.aggregate(15,6,(ROW('📋 ORDERS'!$B$4:$B$675)-3)/(IF($B$4="SKF Order",'📋 ORDERS'!$C$4:$C$675,IF($B$4="TATA Order",'📋 ORDERS'!$D$4:$D$675,IF($B$4="Vulcan PO",'📋 ORDERS'!$E$4:$E$675,'📋 ORDERS'!$Q$4:$Q$675)))=$K$4),19),0)),"")) | D41: =IF(IFERROR(_xludf.aggregate(15,6,(ROW('📋 ORDERS'!$B$4:$B$675)-3)/(IF($B$4="SKF Order",'📋 ORDERS'!$C$4:$C$675,IF($B$4="TATA Order",'📋 ORDERS'!$D$4:$D$675,IF($B$4="Vulcan PO",'📋 ORDERS'!$E$4:$E$675,'📋 ORDERS'!$Q$4:$Q$675)))=$K$4),19),0)=0,"",IFERROR(INDEX('📋 ORDERS'!$G$4:$G$675,IFERROR(_xludf.aggregate(15,6,(ROW('📋 ORDERS'!$B$4:$B$675)-3)/(IF($B$4="SKF Order",'📋 ORDERS'!$C$4:$C$675,IF($B$4="TATA Order",'📋 ORDERS'!$D$4:$D$675,IF($B$4="Vulcan PO",'📋 ORDERS'!$E$4:$E$675,'📋 ORDERS'!$Q$4:$Q$675)))=$K$4),19),0)),"")) | F41: =IF(IFERROR(_xludf.aggregate(15,6,(ROW('📋 ORDERS'!$B$4:$B$675)-3)/(IF($B$4="SKF Order",'📋 ORDERS'!$C$4:$C$675,IF($B$4="TATA Order",'📋 ORDERS'!$D$4:$D$675,IF($B$4="Vulcan PO",'📋 ORDERS'!$E$4:$E$675,'📋 ORDERS'!$Q$4:$Q$675)))=$K$4),19),0)=0,"",IFERROR(INDEX('📋 ORDERS'!$K$4:$K$675,IFERROR(_xludf.aggregate(15,6,(ROW('📋 ORDERS'!$B$4:$B$675)-3)/(IF($B$4="SKF Order",'📋 ORDERS'!$C$4:$C$675,IF($B$4="TATA Order",'📋 ORDERS'!$D$4:$D$675,IF($B$4="Vulcan PO",'📋 ORDERS'!$E$4:$E$675,'📋 ORDERS'!$Q$4:$Q$675)))=$K$4),19),0)),"")) | G41: =IF(IFERROR(_xludf.aggregate(15,6,(ROW('📋 ORDERS'!$B$4:$B$675)-3)/(IF($B$4="SKF Order",'📋 ORDERS'!$C$4:$C$675,IF($B$4="TATA Order",'📋 ORDERS'!$D$4:$D$675,IF($B$4="Vulcan PO",'📋 ORDERS'!$E$4:$E$675,'📋 ORDERS'!$Q$4:$Q$675)))=$K$4),19),0)=0,"",IFERROR(INDEX('📋 ORDERS'!$L$4:$L$675,IFERROR(_xludf.aggregate(15,6,(ROW('📋 ORDERS'!$B$4:$B$675)-3)/(IF($B$4="SKF Order",'📋 ORDERS'!$C$4:$C$675,IF($B$4="TATA Order",'📋 ORDERS'!$D$4:$D$675,IF($B$4="Vulcan PO",'📋 ORDERS'!$E$4:$E$675,'📋 ORDERS'!$Q$4:$Q$675)))=$K$4),19),0)),"")) | H41: =IF(IFERROR(_xludf.aggregate(15,6,(ROW('📋 ORDERS'!$B$4:$B$675)-3)/(IF($B$4="SKF Order",'📋 ORDERS'!$C$4:$C$675,IF($B$4="TATA Order",'📋 ORDERS'!$D$4:$D$675,IF($B$4="Vulcan PO",'📋 ORDERS'!$E$4:$E$675,'📋 ORDERS'!$Q$4:$Q$675)))=$K$4),19),0)=0,"",IFERROR(INDEX('📋 ORDERS'!$M$4:$M$675,IFERROR(_xludf.aggregate(15,6,(ROW('📋 ORDERS'!$B$4:$B$675)-3)/(IF($B$4="SKF Order",'📋 ORDERS'!$C$4:$C$675,IF($B$4="TATA Order",'📋 ORDERS'!$D$4:$D$675,IF($B$4="Vulcan PO",'📋 ORDERS'!$E$4:$E$675,'📋 ORDERS'!$Q$4:$Q$675)))=$K$4),19),0)),"")) | I41: =IF(IFERROR(_xludf.aggregate(15,6,(ROW('📋 ORDERS'!$B$4:$B$675)-3)/(IF($B$4="SKF Order",'📋 ORDERS'!$C$4:$C$675,IF($B$4="TATA Order",'📋 ORDERS'!$D$4:$D$675,IF($B$4="Vulcan PO",'📋 ORDERS'!$E$4:$E$675,'📋 ORDERS'!$Q$4:$Q$675)))=$K$4),19),0)=0,"",IFERROR(INDEX('📋 ORDERS'!$R$4:$R$675,IFERROR(_xludf.aggregate(15,6,(ROW('📋 ORDERS'!$B$4:$B$675)-3)/(IF($B$4="SKF Order",'📋 ORDERS'!$C$4:$C$675,IF($B$4="TATA Order",'📋 ORDERS'!$D$4:$D$675,IF($B$4="Vulcan PO",'📋 ORDERS'!$E$4:$E$675,'📋 ORDERS'!$Q$4:$Q$675)))=$K$4),19),0)),"")) | J41: =IF(IFERROR(_xludf.aggregate(15,6,(ROW('📋 ORDERS'!$B$4:$B$675)-3)/(IF($B$4="SKF Order",'📋 ORDERS'!$C$4:$C$675,IF($B$4="TATA Order",'📋 ORDERS'!$D$4:$D$675,IF($B$4="Vulcan PO",'📋 ORDERS'!$E$4:$E$675,'📋 ORDERS'!$Q$4:$Q$675)))=$K$4),19),0)=0,"",IFERROR(INDEX('📋 ORDERS'!$S$4:$S$675,IFERROR(_xludf.aggregate(15,6,(ROW('📋 ORDERS'!$B$4:$B$675)-3)/(IF($B$4="SKF Order",'📋 ORDERS'!$C$4:$C$675,IF($B$4="TATA Order",'📋 ORDERS'!$D$4:$D$675,IF($B$4="Vulcan PO",'📋 ORDERS'!$E$4:$E$675,'📋 ORDERS'!$Q$4:$Q$675)))=$K$4),19),0)),""))
B42: =IF(IFERROR(_xludf.aggregate(15,6,(ROW('📋 ORDERS'!$B$4:$B$675)-3)/(IF($B$4="SKF Order",'📋 ORDERS'!$C$4:$C$675,IF($B$4="TATA Order",'📋 ORDERS'!$D$4:$D$675,IF($B$4="Vulcan PO",'📋 ORDERS'!$E$4:$E$675,'📋 ORDERS'!$Q$4:$Q$675)))=$K$4),20),0)=0,"",20) | C42: =IF(IFERROR(_xludf.aggregate(15,6,(ROW('📋 ORDERS'!$B$4:$B$675)-3)/(IF($B$4="SKF Order",'📋 ORDERS'!$C$4:$C$675,IF($B$4="TATA Order",'📋 ORDERS'!$D$4:$D$675,IF($B$4="Vulcan PO",'📋 ORDERS'!$E$4:$E$675,'📋 ORDERS'!$Q$4:$Q$675)))=$K$4),20),0)=0,"",IFERROR(INDEX('📋 ORDERS'!$C$4:$C$675,IFERROR(_xludf.aggregate(15,6,(ROW('📋 ORDERS'!$B$4:$B$675)-3)/(IF($B$4="SKF Order",'📋 ORDERS'!$C$4:$C$675,IF($B$4="TATA Order",'📋 ORDERS'!$D$4:$D$675,IF($B$4="Vulcan PO",'📋 ORDERS'!$E$4:$E$675,'📋 ORDERS'!$Q$4:$Q$675)))=$K$4),20),0)),"")) | D42: =IF(IFERROR(_xludf.aggregate(15,6,(ROW('📋 ORDERS'!$B$4:$B$675)-3)/(IF($B$4="SKF Order",'📋 ORDERS'!$C$4:$C$675,IF($B$4="TATA Order",'📋 ORDERS'!$D$4:$D$675,IF($B$4="Vulcan PO",'📋 ORDERS'!$E$4:$E$675,'📋 ORDERS'!$Q$4:$Q$675)))=$K$4),20),0)=0,"",IFERROR(INDEX('📋 ORDERS'!$G$4:$G$675,IFERROR(_xludf.aggregate(15,6,(ROW('📋 ORDERS'!$B$4:$B$675)-3)/(IF($B$4="SKF Order",'📋 ORDERS'!$C$4:$C$675,IF($B$4="TATA Order",'📋 ORDERS'!$D$4:$D$675,IF($B$4="Vulcan PO",'📋 ORDERS'!$E$4:$E$675,'📋 ORDERS'!$Q$4:$Q$675)))=$K$4),20),0)),"")) | F42: =IF(IFERROR(_xludf.aggregate(15,6,(ROW('📋 ORDERS'!$B$4:$B$675)-3)/(IF($B$4="SKF Order",'📋 ORDERS'!$C$4:$C$675,IF($B$4="TATA Order",'📋 ORDERS'!$D$4:$D$675,IF($B$4="Vulcan PO",'📋 ORDERS'!$E$4:$E$675,'📋 ORDERS'!$Q$4:$Q$675)))=$K$4),20),0)=0,"",IFERROR(INDEX('📋 ORDERS'!$K$4:$K$675,IFERROR(_xludf.aggregate(15,6,(ROW('📋 ORDERS'!$B$4:$B$675)-3)/(IF($B$4="SKF Order",'📋 ORDERS'!$C$4:$C$675,IF($B$4="TATA Order",'📋 ORDERS'!$D$4:$D$675,IF($B$4="Vulcan PO",'📋 ORDERS'!$E$4:$E$675,'📋 ORDERS'!$Q$4:$Q$675)))=$K$4),20),0)),"")) | G42: =IF(IFERROR(_xludf.aggregate(15,6,(ROW('📋 ORDERS'!$B$4:$B$675)-3)/(IF($B$4="SKF Order",'📋 ORDERS'!$C$4:$C$675,IF($B$4="TATA Order",'📋 ORDERS'!$D$4:$D$675,IF($B$4="Vulcan PO",'📋 ORDERS'!$E$4:$E$675,'📋 ORDERS'!$Q$4:$Q$675)))=$K$4),20),0)=0,"",IFERROR(INDEX('📋 ORDERS'!$L$4:$L$675,IFERROR(_xludf.aggregate(15,6,(ROW('📋 ORDERS'!$B$4:$B$675)-3)/(IF($B$4="SKF Order",'📋 ORDERS'!$C$4:$C$675,IF($B$4="TATA Order",'📋 ORDERS'!$D$4:$D$675,IF($B$4="Vulcan PO",'📋 ORDERS'!$E$4:$E$675,'📋 ORDERS'!$Q$4:$Q$675)))=$K$4),20),0)),"")) | H42: =IF(IFERROR(_xludf.aggregate(15,6,(ROW('📋 ORDERS'!$B$4:$B$675)-3)/(IF($B$4="SKF Order",'📋 ORDERS'!$C$4:$C$675,IF($B$4="TATA Order",'📋 ORDERS'!$D$4:$D$675,IF($B$4="Vulcan PO",'📋 ORDERS'!$E$4:$E$675,'📋 ORDERS'!$Q$4:$Q$675)))=$K$4),20),0)=0,"",IFERROR(INDEX('📋 ORDERS'!$M$4:$M$675,IFERROR(_xludf.aggregate(15,6,(ROW('📋 ORDERS'!$B$4:$B$675)-3)/(IF($B$4="SKF Order",'📋 ORDERS'!$C$4:$C$675,IF($B$4="TATA Order",'📋 ORDERS'!$D$4:$D$675,IF($B$4="Vulcan PO",'📋 ORDERS'!$E$4:$E$675,'📋 ORDERS'!$Q$4:$Q$675)))=$K$4),20),0)),"")) | I42: =IF(IFERROR(_xludf.aggregate(15,6,(ROW('📋 ORDERS'!$B$4:$B$675)-3)/(IF($B$4="SKF Order",'📋 ORDERS'!$C$4:$C$675,IF($B$4="TATA Order",'📋 ORDERS'!$D$4:$D$675,IF($B$4="Vulcan PO",'📋 ORDERS'!$E$4:$E$675,'📋 ORDERS'!$Q$4:$Q$675)))=$K$4),20),0)=0,"",IFERROR(INDEX('📋 ORDERS'!$R$4:$R$675,IFERROR(_xludf.aggregate(15,6,(ROW('📋 ORDERS'!$B$4:$B$675)-3)/(IF($B$4="SKF Order",'📋 ORDERS'!$C$4:$C$675,IF($B$4="TATA Order",'📋 ORDERS'!$D$4:$D$675,IF($B$4="Vulcan PO",'📋 ORDERS'!$E$4:$E$675,'📋 ORDERS'!$Q$4:$Q$675)))=$K$4),20),0)),"")) | J42: =IF(IFERROR(_xludf.aggregate(15,6,(ROW('📋 ORDERS'!$B$4:$B$675)-3)/(IF($B$4="SKF Order",'📋 ORDERS'!$C$4:$C$675,IF($B$4="TATA Order",'📋 ORDERS'!$D$4:$D$675,IF($B$4="Vulcan PO",'📋 ORDERS'!$E$4:$E$675,'📋 ORDERS'!$Q$4:$Q$675)))=$K$4),20),0)=0,"",IFERROR(INDEX('📋 ORDERS'!$S$4:$S$675,IFERROR(_xludf.aggregate(15,6,(ROW('📋 ORDERS'!$B$4:$B$675)-3)/(IF($B$4="SKF Order",'📋 ORDERS'!$C$4:$C$675,IF($B$4="TATA Order",'📋 ORDERS'!$D$4:$D$675,IF($B$4="Vulcan PO",'📋 ORDERS'!$E$4:$E$675,'📋 ORDERS'!$Q$4:$Q$675)))=$K$4),20),0)),""))
B43: =IF(IFERROR(_xludf.aggregate(15,6,(ROW('📋 ORDERS'!$B$4:$B$675)-3)/(IF($B$4="SKF Order",'📋 ORDERS'!$C$4:$C$675,IF($B$4="TATA Order",'📋 ORDERS'!$D$4:$D$675,IF($B$4="Vulcan PO",'📋 ORDERS'!$E$4:$E$675,'📋 ORDERS'!$Q$4:$Q$675)))=$K$4),21),0)=0,"",21) | C43: =IF(IFERROR(_xludf.aggregate(15,6,(ROW('📋 ORDERS'!$B$4:$B$675)-3)/(IF($B$4="SKF Order",'📋 ORDERS'!$C$4:$C$675,IF($B$4="TATA Order",'📋 ORDERS'!$D$4:$D$675,IF($B$4="Vulcan PO",'📋 ORDERS'!$E$4:$E$675,'📋 ORDERS'!$Q$4:$Q$675)))=$K$4),21),0)=0,"",IFERROR(INDEX('📋 ORDERS'!$C$4:$C$675,IFERROR(_xludf.aggregate(15,6,(ROW('📋 ORDERS'!$B$4:$B$675)-3)/(IF($B$4="SKF Order",'📋 ORDERS'!$C$4:$C$675,IF($B$4="TATA Order",'📋 ORDERS'!$D$4:$D$675,IF($B$4="Vulcan PO",'📋 ORDERS'!$E$4:$E$675,'📋 ORDERS'!$Q$4:$Q$675)))=$K$4),21),0)),"")) | D43: =IF(IFERROR(_xludf.aggregate(15,6,(ROW('📋 ORDERS'!$B$4:$B$675)-3)/(IF($B$4="SKF Order",'📋 ORDERS'!$C$4:$C$675,IF($B$4="TATA Order",'📋 ORDERS'!$D$4:$D$675,IF($B$4="Vulcan PO",'📋 ORDERS'!$E$4:$E$675,'📋 ORDERS'!$Q$4:$Q$675)))=$K$4),21),0)=0,"",IFERROR(INDEX('📋 ORDERS'!$G$4:$G$675,IFERROR(_xludf.aggregate(15,6,(ROW('📋 ORDERS'!$B$4:$B$675)-3)/(IF($B$4="SKF Order",'📋 ORDERS'!$C$4:$C$675,IF($B$4="TATA Order",'📋 ORDERS'!$D$4:$D$675,IF($B$4="Vulcan PO",'📋 ORDERS'!$E$4:$E$675,'📋 ORDERS'!$Q$4:$Q$675)))=$K$4),21),0)),"")) | F43: =IF(IFERROR(_xludf.aggregate(15,6,(ROW('📋 ORDERS'!$B$4:$B$675)-3)/(IF($B$4="SKF Order",'📋 ORDERS'!$C$4:$C$675,IF($B$4="TATA Order",'📋 ORDERS'!$D$4:$D$675,IF($B$4="Vulcan PO",'📋 ORDERS'!$E$4:$E$675,'📋 ORDERS'!$Q$4:$Q$675)))=$K$4),21),0)=0,"",IFERROR(INDEX('📋 ORDERS'!$K$4:$K$675,IFERROR(_xludf.aggregate(15,6,(ROW('📋 ORDERS'!$B$4:$B$675)-3)/(IF($B$4="SKF Order",'📋 ORDERS'!$C$4:$C$675,IF($B$4="TATA Order",'📋 ORDERS'!$D$4:$D$675,IF($B$4="Vulcan PO",'📋 ORDERS'!$E$4:$E$675,'📋 ORDERS'!$Q$4:$Q$675)))=$K$4),21),0)),"")) | G43: =IF(IFERROR(_xludf.aggregate(15,6,(ROW('📋 ORDERS'!$B$4:$B$675)-3)/(IF($B$4="SKF Order",'📋 ORDERS'!$C$4:$C$675,IF($B$4="TATA Order",'📋 ORDERS'!$D$4:$D$675,IF($B$4="Vulcan PO",'📋 ORDERS'!$E$4:$E$675,'📋 ORDERS'!$Q$4:$Q$675)))=$K$4),21),0)=0,"",IFERROR(INDEX('📋 ORDERS'!$L$4:$L$675,IFERROR(_xludf.aggregate(15,6,(ROW('📋 ORDERS'!$B$4:$B$675)-3)/(IF($B$4="SKF Order",'📋 ORDERS'!$C$4:$C$675,IF($B$4="TATA Order",'📋 ORDERS'!$D$4:$D$675,IF($B$4="Vulcan PO",'📋 ORDERS'!$E$4:$E$675,'📋 ORDERS'!$Q$4:$Q$675)))=$K$4),21),0)),"")) | H43: =IF(IFERROR(_xludf.aggregate(15,6,(ROW('📋 ORDERS'!$B$4:$B$675)-3)/(IF($B$4="SKF Order",'📋 ORDERS'!$C$4:$C$675,IF($B$4="TATA Order",'📋 ORDERS'!$D$4:$D$675,IF($B$4="Vulcan PO",'📋 ORDERS'!$E$4:$E$675,'📋 ORDERS'!$Q$4:$Q$675)))=$K$4),21),0)=0,"",IFERROR(INDEX('📋 ORDERS'!$M$4:$M$675,IFERROR(_xludf.aggregate(15,6,(ROW('📋 ORDERS'!$B$4:$B$675)-3)/(IF($B$4="SKF Order",'📋 ORDERS'!$C$4:$C$675,IF($B$4="TATA Order",'📋 ORDERS'!$D$4:$D$675,IF($B$4="Vulcan PO",'📋 ORDERS'!$E$4:$E$675,'📋 ORDERS'!$Q$4:$Q$675)))=$K$4),21),0)),"")) | I43: =IF(IFERROR(_xludf.aggregate(15,6,(ROW('📋 ORDERS'!$B$4:$B$675)-3)/(IF($B$4="SKF Order",'📋 ORDERS'!$C$4:$C$675,IF($B$4="TATA Order",'📋 ORDERS'!$D$4:$D$675,IF($B$4="Vulcan PO",'📋 ORDERS'!$E$4:$E$675,'📋 ORDERS'!$Q$4:$Q$675)))=$K$4),21),0)=0,"",IFERROR(INDEX('📋 ORDERS'!$R$4:$R$675,IFERROR(_xludf.aggregate(15,6,(ROW('📋 ORDERS'!$B$4:$B$675)-3)/(IF($B$4="SKF Order",'📋 ORDERS'!$C$4:$C$675,IF($B$4="TATA Order",'📋 ORDERS'!$D$4:$D$675,IF($B$4="Vulcan PO",'📋 ORDERS'!$E$4:$E$675,'📋 ORDERS'!$Q$4:$Q$675)))=$K$4),21),0)),"")) | J43: =IF(IFERROR(_xludf.aggregate(15,6,(ROW('📋 ORDERS'!$B$4:$B$675)-3)/(IF($B$4="SKF Order",'📋 ORDERS'!$C$4:$C$675,IF($B$4="TATA Order",'📋 ORDERS'!$D$4:$D$675,IF($B$4="Vulcan PO",'📋 ORDERS'!$E$4:$E$675,'📋 ORDERS'!$Q$4:$Q$675)))=$K$4),21),0)=0,"",IFERROR(INDEX('📋 ORDERS'!$S$4:$S$675,IFERROR(_xludf.aggregate(15,6,(ROW('📋 ORDERS'!$B$4:$B$675)-3)/(IF($B$4="SKF Order",'📋 ORDERS'!$C$4:$C$675,IF($B$4="TATA Order",'📋 ORDERS'!$D$4:$D$675,IF($B$4="Vulcan PO",'📋 ORDERS'!$E$4:$E$675,'📋 ORDERS'!$Q$4:$Q$675)))=$K$4),21),0)),""))
B44: =IF(IFERROR(_xludf.aggregate(15,6,(ROW('📋 ORDERS'!$B$4:$B$675)-3)/(IF($B$4="SKF Order",'📋 ORDERS'!$C$4:$C$675,IF($B$4="TATA Order",'📋 ORDERS'!$D$4:$D$675,IF($B$4="Vulcan PO",'📋 ORDERS'!$E$4:$E$675,'📋 ORDERS'!$Q$4:$Q$675)))=$K$4),22),0)=0,"",22) | C44: =IF(IFERROR(_xludf.aggregate(15,6,(ROW('📋 ORDERS'!$B$4:$B$675)-3)/(IF($B$4="SKF Order",'📋 ORDERS'!$C$4:$C$675,IF($B$4="TATA Order",'📋 ORDERS'!$D$4:$D$675,IF($B$4="Vulcan PO",'📋 ORDERS'!$E$4:$E$675,'📋 ORDERS'!$Q$4:$Q$675)))=$K$4),22),0)=0,"",IFERROR(INDEX('📋 ORDERS'!$C$4:$C$675,IFERROR(_xludf.aggregate(15,6,(ROW('📋 ORDERS'!$B$4:$B$675)-3)/(IF($B$4="SKF Order",'📋 ORDERS'!$C$4:$C$675,IF($B$4="TATA Order",'📋 ORDERS'!$D$4:$D$675,IF($B$4="Vulcan PO",'📋 ORDERS'!$E$4:$E$675,'📋 ORDERS'!$Q$4:$Q$675)))=$K$4),22),0)),"")) | D44: =IF(IFERROR(_xludf.aggregate(15,6,(ROW('📋 ORDERS'!$B$4:$B$675)-3)/(IF($B$4="SKF Order",'📋 ORDERS'!$C$4:$C$675,IF($B$4="TATA Order",'📋 ORDERS'!$D$4:$D$675,IF($B$4="Vulcan PO",'📋 ORDERS'!$E$4:$E$675,'📋 ORDERS'!$Q$4:$Q$675)))=$K$4),22),0)=0,"",IFERROR(INDEX('📋 ORDERS'!$G$4:$G$675,IFERROR(_xludf.aggregate(15,6,(ROW('📋 ORDERS'!$B$4:$B$675)-3)/(IF($B$4="SKF Order",'📋 ORDERS'!$C$4:$C$675,IF($B$4="TATA Order",'📋 ORDERS'!$D$4:$D$675,IF($B$4="Vulcan PO",'📋 ORDERS'!$E$4:$E$675,'📋 ORDERS'!$Q$4:$Q$675)))=$K$4),22),0)),"")) | F44: =IF(IFERROR(_xludf.aggregate(15,6,(ROW('📋 ORDERS'!$B$4:$B$675)-3)/(IF($B$4="SKF Order",'📋 ORDERS'!$C$4:$C$675,IF($B$4="TATA Order",'📋 ORDERS'!$D$4:$D$675,IF($B$4="Vulcan PO",'📋 ORDERS'!$E$4:$E$675,'📋 ORDERS'!$Q$4:$Q$675)))=$K$4),22),0)=0,"",IFERROR(INDEX('📋 ORDERS'!$K$4:$K$675,IFERROR(_xludf.aggregate(15,6,(ROW('📋 ORDERS'!$B$4:$B$675)-3)/(IF($B$4="SKF Order",'📋 ORDERS'!$C$4:$C$675,IF($B$4="TATA Order",'📋 ORDERS'!$D$4:$D$675,IF($B$4="Vulcan PO",'📋 ORDERS'!$E$4:$E$675,'📋 ORDERS'!$Q$4:$Q$675)))=$K$4),22),0)),"")) | G44: =IF(IFERROR(_xludf.aggregate(15,6,(ROW('📋 ORDERS'!$B$4:$B$675)-3)/(IF($B$4="SKF Order",'📋 ORDERS'!$C$4:$C$675,IF($B$4="TATA Order",'📋 ORDERS'!$D$4:$D$675,IF($B$4="Vulcan PO",'📋 ORDERS'!$E$4:$E$675,'📋 ORDERS'!$Q$4:$Q$675)))=$K$4),22),0)=0,"",IFERROR(INDEX('📋 ORDERS'!$L$4:$L$675,IFERROR(_xludf.aggregate(15,6,(ROW('📋 ORDERS'!$B$4:$B$675)-3)/(IF($B$4="SKF Order",'📋 ORDERS'!$C$4:$C$675,IF($B$4="TATA Order",'📋 ORDERS'!$D$4:$D$675,IF($B$4="Vulcan PO",'📋 ORDERS'!$E$4:$E$675,'📋 ORDERS'!$Q$4:$Q$675)))=$K$4),22),0)),"")) | H44: =IF(IFERROR(_xludf.aggregate(15,6,(ROW('📋 ORDERS'!$B$4:$B$675)-3)/(IF($B$4="SKF Order",'📋 ORDERS'!$C$4:$C$675,IF($B$4="TATA Order",'📋 ORDERS'!$D$4:$D$675,IF($B$4="Vulcan PO",'📋 ORDERS'!$E$4:$E$675,'📋 ORDERS'!$Q$4:$Q$675)))=$K$4),22),0)=0,"",IFERROR(INDEX('📋 ORDERS'!$M$4:$M$675,IFERROR(_xludf.aggregate(15,6,(ROW('📋 ORDERS'!$B$4:$B$675)-3)/(IF($B$4="SKF Order",'📋 ORDERS'!$C$4:$C$675,IF($B$4="TATA Order",'📋 ORDERS'!$D$4:$D$675,IF($B$4="Vulcan PO",'📋 ORDERS'!$E$4:$E$675,'📋 ORDERS'!$Q$4:$Q$675)))=$K$4),22),0)),"")) | I44: =IF(IFERROR(_xludf.aggregate(15,6,(ROW('📋 ORDERS'!$B$4:$B$675)-3)/(IF($B$4="SKF Order",'📋 ORDERS'!$C$4:$C$675,IF($B$4="TATA Order",'📋 ORDERS'!$D$4:$D$675,IF($B$4="Vulcan PO",'📋 ORDERS'!$E$4:$E$675,'📋 ORDERS'!$Q$4:$Q$675)))=$K$4),22),0)=0,"",IFERROR(INDEX('📋 ORDERS'!$R$4:$R$675,IFERROR(_xludf.aggregate(15,6,(ROW('📋 ORDERS'!$B$4:$B$675)-3)/(IF($B$4="SKF Order",'📋 ORDERS'!$C$4:$C$675,IF($B$4="TATA Order",'📋 ORDERS'!$D$4:$D$675,IF($B$4="Vulcan PO",'📋 ORDERS'!$E$4:$E$675,'📋 ORDERS'!$Q$4:$Q$675)))=$K$4),22),0)),"")) | J44: =IF(IFERROR(_xludf.aggregate(15,6,(ROW('📋 ORDERS'!$B$4:$B$675)-3)/(IF($B$4="SKF Order",'📋 ORDERS'!$C$4:$C$675,IF($B$4="TATA Order",'📋 ORDERS'!$D$4:$D$675,IF($B$4="Vulcan PO",'📋 ORDERS'!$E$4:$E$675,'📋 ORDERS'!$Q$4:$Q$675)))=$K$4),22),0)=0,"",IFERROR(INDEX('📋 ORDERS'!$S$4:$S$675,IFERROR(_xludf.aggregate(15,6,(ROW('📋 ORDERS'!$B$4:$B$675)-3)/(IF($B$4="SKF Order",'📋 ORDERS'!$C$4:$C$675,IF($B$4="TATA Order",'📋 ORDERS'!$D$4:$D$675,IF($B$4="Vulcan PO",'📋 ORDERS'!$E$4:$E$675,'📋 ORDERS'!$Q$4:$Q$675)))=$K$4),22),0)),""))
B45: =IF(IFERROR(_xludf.aggregate(15,6,(ROW('📋 ORDERS'!$B$4:$B$675)-3)/(IF($B$4="SKF Order",'📋 ORDERS'!$C$4:$C$675,IF($B$4="TATA Order",'📋 ORDERS'!$D$4:$D$675,IF($B$4="Vulcan PO",'📋 ORDERS'!$E$4:$E$675,'📋 ORDERS'!$Q$4:$Q$675)))=$K$4),23),0)=0,"",23) | C45: =IF(IFERROR(_xludf.aggregate(15,6,(ROW('📋 ORDERS'!$B$4:$B$675)-3)/(IF($B$4="SKF Order",'📋 ORDERS'!$C$4:$C$675,IF($B$4="TATA Order",'📋 ORDERS'!$D$4:$D$675,IF($B$4="Vulcan PO",'📋 ORDERS'!$E$4:$E$675,'📋 ORDERS'!$Q$4:$Q$675)))=$K$4),23),0)=0,"",IFERROR(INDEX('📋 ORDERS'!$C$4:$C$675,IFERROR(_xludf.aggregate(15,6,(ROW('📋 ORDERS'!$B$4:$B$675)-3)/(IF($B$4="SKF Order",'📋 ORDERS'!$C$4:$C$675,IF($B$4="TATA Order",'📋 ORDERS'!$D$4:$D$675,IF($B$4="Vulcan PO",'📋 ORDERS'!$E$4:$E$675,'📋 ORDERS'!$Q$4:$Q$675)))=$K$4),23),0)),"")) | D45: =IF(IFERROR(_xludf.aggregate(15,6,(ROW('📋 ORDERS'!$B$4:$B$675)-3)/(IF($B$4="SKF Order",'📋 ORDERS'!$C$4:$C$675,IF($B$4="TATA Order",'📋 ORDERS'!$D$4:$D$675,IF($B$4="Vulcan PO",'📋 ORDERS'!$E$4:$E$675,'📋 ORDERS'!$Q$4:$Q$675)))=$K$4),23),0)=0,"",IFERROR(INDEX('📋 ORDERS'!$G$4:$G$675,IFERROR(_xludf.aggregate(15,6,(ROW('📋 ORDERS'!$B$4:$B$675)-3)/(IF($B$4="SKF Order",'📋 ORDERS'!$C$4:$C$675,IF($B$4="TATA Order",'📋 ORDERS'!$D$4:$D$675,IF($B$4="Vulcan PO",'📋 ORDERS'!$E$4:$E$675,'📋 ORDERS'!$Q$4:$Q$675)))=$K$4),23),0)),"")) | F45: =IF(IFERROR(_xludf.aggregate(15,6,(ROW('📋 ORDERS'!$B$4:$B$675)-3)/(IF($B$4="SKF Order",'📋 ORDERS'!$C$4:$C$675,IF($B$4="TATA Order",'📋 ORDERS'!$D$4:$D$675,IF($B$4="Vulcan PO",'📋 ORDERS'!$E$4:$E$675,'📋 ORDERS'!$Q$4:$Q$675)))=$K$4),23),0)=0,"",IFERROR(INDEX('📋 ORDERS'!$K$4:$K$675,IFERROR(_xludf.aggregate(15,6,(ROW('📋 ORDERS'!$B$4:$B$675)-3)/(IF($B$4="SKF Order",'📋 ORDERS'!$C$4:$C$675,IF($B$4="TATA Order",'📋 ORDERS'!$D$4:$D$675,IF($B$4="Vulcan PO",'📋 ORDERS'!$E$4:$E$675,'📋 ORDERS'!$Q$4:$Q$675)))=$K$4),23),0)),"")) | G45: =IF(IFERROR(_xludf.aggregate(15,6,(ROW('📋 ORDERS'!$B$4:$B$675)-3)/(IF($B$4="SKF Order",'📋 ORDERS'!$C$4:$C$675,IF($B$4="TATA Order",'📋 ORDERS'!$D$4:$D$675,IF($B$4="Vulcan PO",'📋 ORDERS'!$E$4:$E$675,'📋 ORDERS'!$Q$4:$Q$675)))=$K$4),23),0)=0,"",IFERROR(INDEX('📋 ORDERS'!$L$4:$L$675,IFERROR(_xludf.aggregate(15,6,(ROW('📋 ORDERS'!$B$4:$B$675)-3)/(IF($B$4="SKF Order",'📋 ORDERS'!$C$4:$C$675,IF($B$4="TATA Order",'📋 ORDERS'!$D$4:$D$675,IF($B$4="Vulcan PO",'📋 ORDERS'!$E$4:$E$675,'📋 ORDERS'!$Q$4:$Q$675)))=$K$4),23),0)),"")) | H45: =IF(IFERROR(_xludf.aggregate(15,6,(ROW('📋 ORDERS'!$B$4:$B$675)-3)/(IF($B$4="SKF Order",'📋 ORDERS'!$C$4:$C$675,IF($B$4="TATA Order",'📋 ORDERS'!$D$4:$D$675,IF($B$4="Vulcan PO",'📋 ORDERS'!$E$4:$E$675,'📋 ORDERS'!$Q$4:$Q$675)))=$K$4),23),0)=0,"",IFERROR(INDEX('📋 ORDERS'!$M$4:$M$675,IFERROR(_xludf.aggregate(15,6,(ROW('📋 ORDERS'!$B$4:$B$675)-3)/(IF($B$4="SKF Order",'📋 ORDERS'!$C$4:$C$675,IF($B$4="TATA Order",'📋 ORDERS'!$D$4:$D$675,IF($B$4="Vulcan PO",'📋 ORDERS'!$E$4:$E$675,'📋 ORDERS'!$Q$4:$Q$675)))=$K$4),23),0)),"")) | I45: =IF(IFERROR(_xludf.aggregate(15,6,(ROW('📋 ORDERS'!$B$4:$B$675)-3)/(IF($B$4="SKF Order",'📋 ORDERS'!$C$4:$C$675,IF($B$4="TATA Order",'📋 ORDERS'!$D$4:$D$675,IF($B$4="Vulcan PO",'📋 ORDERS'!$E$4:$E$675,'📋 ORDERS'!$Q$4:$Q$675)))=$K$4),23),0)=0,"",IFERROR(INDEX('📋 ORDERS'!$R$4:$R$675,IFERROR(_xludf.aggregate(15,6,(ROW('📋 ORDERS'!$B$4:$B$675)-3)/(IF($B$4="SKF Order",'📋 ORDERS'!$C$4:$C$675,IF($B$4="TATA Order",'📋 ORDERS'!$D$4:$D$675,IF($B$4="Vulcan PO",'📋 ORDERS'!$E$4:$E$675,'📋 ORDERS'!$Q$4:$Q$675)))=$K$4),23),0)),"")) | J45: =IF(IFERROR(_xludf.aggregate(15,6,(ROW('📋 ORDERS'!$B$4:$B$675)-3)/(IF($B$4="SKF Order",'📋 ORDERS'!$C$4:$C$675,IF($B$4="TATA Order",'📋 ORDERS'!$D$4:$D$675,IF($B$4="Vulcan PO",'📋 ORDERS'!$E$4:$E$675,'📋 ORDERS'!$Q$4:$Q$675)))=$K$4),23),0)=0,"",IFERROR(INDEX('📋 ORDERS'!$S$4:$S$675,IFERROR(_xludf.aggregate(15,6,(ROW('📋 ORDERS'!$B$4:$B$675)-3)/(IF($B$4="SKF Order",'📋 ORDERS'!$C$4:$C$675,IF($B$4="TATA Order",'📋 ORDERS'!$D$4:$D$675,IF($B$4="Vulcan PO",'📋 ORDERS'!$E$4:$E$675,'📋 ORDERS'!$Q$4:$Q$675)))=$K$4),23),0)),""))
B46: =IF(IFERROR(_xludf.aggregate(15,6,(ROW('📋 ORDERS'!$B$4:$B$675)-3)/(IF($B$4="SKF Order",'📋 ORDERS'!$C$4:$C$675,IF($B$4="TATA Order",'📋 ORDERS'!$D$4:$D$675,IF($B$4="Vulcan PO",'📋 ORDERS'!$E$4:$E$675,'📋 ORDERS'!$Q$4:$Q$675)))=$K$4),24),0)=0,"",24) | C46: =IF(IFERROR(_xludf.aggregate(15,6,(ROW('📋 ORDERS'!$B$4:$B$675)-3)/(IF($B$4="SKF Order",'📋 ORDERS'!$C$4:$C$675,IF($B$4="TATA Order",'📋 ORDERS'!$D$4:$D$675,IF($B$4="Vulcan PO",'📋 ORDERS'!$E$4:$E$675,'📋 ORDERS'!$Q$4:$Q$675)))=$K$4),24),0)=0,"",IFERROR(INDEX('📋 ORDERS'!$C$4:$C$675,IFERROR(_xludf.aggregate(15,6,(ROW('📋 ORDERS'!$B$4:$B$675)-3)/(IF($B$4="SKF Order",'📋 ORDERS'!$C$4:$C$675,IF($B$4="TATA Order",'📋 ORDERS'!$D$4:$D$675,IF($B$4="Vulcan PO",'📋 ORDERS'!$E$4:$E$675,'📋 ORDERS'!$Q$4:$Q$675)))=$K$4),24),0)),"")) | D46: =IF(IFERROR(_xludf.aggregate(15,6,(ROW('📋 ORDERS'!$B$4:$B$675)-3)/(IF($B$4="SKF Order",'📋 ORDERS'!$C$4:$C$675,IF($B$4="TATA Order",'📋 ORDERS'!$D$4:$D$675,IF($B$4="Vulcan PO",'📋 ORDERS'!$E$4:$E$675,'📋 ORDERS'!$Q$4:$Q$675)))=$K$4),24),0)=0,"",IFERROR(INDEX('📋 ORDERS'!$G$4:$G$675,IFERROR(_xludf.aggregate(15,6,(ROW('📋 ORDERS'!$B$4:$B$675)-3)/(IF($B$4="SKF Order",'📋 ORDERS'!$C$4:$C$675,IF($B$4="TATA Order",'📋 ORDERS'!$D$4:$D$675,IF($B$4="Vulcan PO",'📋 ORDERS'!$E$4:$E$675,'📋 ORDERS'!$Q$4:$Q$675)))=$K$4),24),0)),"")) | F46: =IF(IFERROR(_xludf.aggregate(15,6,(ROW('📋 ORDERS'!$B$4:$B$675)-3)/(IF($B$4="SKF Order",'📋 ORDERS'!$C$4:$C$675,IF($B$4="TATA Order",'📋 ORDERS'!$D$4:$D$675,IF($B$4="Vulcan PO",'📋 ORDERS'!$E$4:$E$675,'📋 ORDERS'!$Q$4:$Q$675)))=$K$4),24),0)=0,"",IFERROR(INDEX('📋 ORDERS'!$K$4:$K$675,IFERROR(_xludf.aggregate(15,6,(ROW('📋 ORDERS'!$B$4:$B$675)-3)/(IF($B$4="SKF Order",'📋 ORDERS'!$C$4:$C$675,IF($B$4="TATA Order",'📋 ORDERS'!$D$4:$D$675,IF($B$4="Vulcan PO",'📋 ORDERS'!$E$4:$E$675,'📋 ORDERS'!$Q$4:$Q$675)))=$K$4),24),0)),"")) | G46: =IF(IFERROR(_xludf.aggregate(15,6,(ROW('📋 ORDERS'!$B$4:$B$675)-3)/(IF($B$4="SKF Order",'📋 ORDERS'!$C$4:$C$675,IF($B$4="TATA Order",'📋 ORDERS'!$D$4:$D$675,IF($B$4="Vulcan PO",'📋 ORDERS'!$E$4:$E$675,'📋 ORDERS'!$Q$4:$Q$675)))=$K$4),24),0)=0,"",IFERROR(INDEX('📋 ORDERS'!$L$4:$L$675,IFERROR(_xludf.aggregate(15,6,(ROW('📋 ORDERS'!$B$4:$B$675)-3)/(IF($B$4="SKF Order",'📋 ORDERS'!$C$4:$C$675,IF($B$4="TATA Order",'📋 ORDERS'!$D$4:$D$675,IF($B$4="Vulcan PO",'📋 ORDERS'!$E$4:$E$675,'📋 ORDERS'!$Q$4:$Q$675)))=$K$4),24),0)),"")) | H46: =IF(IFERROR(_xludf.aggregate(15,6,(ROW('📋 ORDERS'!$B$4:$B$675)-3)/(IF($B$4="SKF Order",'📋 ORDERS'!$C$4:$C$675,IF($B$4="TATA Order",'📋 ORDERS'!$D$4:$D$675,IF($B$4="Vulcan PO",'📋 ORDERS'!$E$4:$E$675,'📋 ORDERS'!$Q$4:$Q$675)))=$K$4),24),0)=0,"",IFERROR(INDEX('📋 ORDERS'!$M$4:$M$675,IFERROR(_xludf.aggregate(15,6,(ROW('📋 ORDERS'!$B$4:$B$675)-3)/(IF($B$4="SKF Order",'📋 ORDERS'!$C$4:$C$675,IF($B$4="TATA Order",'📋 ORDERS'!$D$4:$D$675,IF($B$4="Vulcan PO",'📋 ORDERS'!$E$4:$E$675,'📋 ORDERS'!$Q$4:$Q$675)))=$K$4),24),0)),"")) | I46: =IF(IFERROR(_xludf.aggregate(15,6,(ROW('📋 ORDERS'!$B$4:$B$675)-3)/(IF($B$4="SKF Order",'📋 ORDERS'!$C$4:$C$675,IF($B$4="TATA Order",'📋 ORDERS'!$D$4:$D$675,IF($B$4="Vulcan PO",'📋 ORDERS'!$E$4:$E$675,'📋 ORDERS'!$Q$4:$Q$675)))=$K$4),24),0)=0,"",IFERROR(INDEX('📋 ORDERS'!$R$4:$R$675,IFERROR(_xludf.aggregate(15,6,(ROW('📋 ORDERS'!$B$4:$B$675)-3)/(IF($B$4="SKF Order",'📋 ORDERS'!$C$4:$C$675,IF($B$4="TATA Order",'📋 ORDERS'!$D$4:$D$675,IF($B$4="Vulcan PO",'📋 ORDERS'!$E$4:$E$675,'📋 ORDERS'!$Q$4:$Q$675)))=$K$4),24),0)),"")) | J46: =IF(IFERROR(_xludf.aggregate(15,6,(ROW('📋 ORDERS'!$B$4:$B$675)-3)/(IF($B$4="SKF Order",'📋 ORDERS'!$C$4:$C$675,IF($B$4="TATA Order",'📋 ORDERS'!$D$4:$D$675,IF($B$4="Vulcan PO",'📋 ORDERS'!$E$4:$E$675,'📋 ORDERS'!$Q$4:$Q$675)))=$K$4),24),0)=0,"",IFERROR(INDEX('📋 ORDERS'!$S$4:$S$675,IFERROR(_xludf.aggregate(15,6,(ROW('📋 ORDERS'!$B$4:$B$675)-3)/(IF($B$4="SKF Order",'📋 ORDERS'!$C$4:$C$675,IF($B$4="TATA Order",'📋 ORDERS'!$D$4:$D$675,IF($B$4="Vulcan PO",'📋 ORDERS'!$E$4:$E$675,'📋 ORDERS'!$Q$4:$Q$675)))=$K$4),24),0)),""))
B47: =IF(IFERROR(_xludf.aggregate(15,6,(ROW('📋 ORDERS'!$B$4:$B$675)-3)/(IF($B$4="SKF Order",'📋 ORDERS'!$C$4:$C$675,IF($B$4="TATA Order",'📋 ORDERS'!$D$4:$D$675,IF($B$4="Vulcan PO",'📋 ORDERS'!$E$4:$E$675,'📋 ORDERS'!$Q$4:$Q$675)))=$K$4),25),0)=0,"",25) | C47: =IF(IFERROR(_xludf.aggregate(15,6,(ROW('📋 ORDERS'!$B$4:$B$675)-3)/(IF($B$4="SKF Order",'📋 ORDERS'!$C$4:$C$675,IF($B$4="TATA Order",'📋 ORDERS'!$D$4:$D$675,IF($B$4="Vulcan PO",'📋 ORDERS'!$E$4:$E$675,'📋 ORDERS'!$Q$4:$Q$675)))=$K$4),25),0)=0,"",IFERROR(INDEX('📋 ORDERS'!$C$4:$C$675,IFERROR(_xludf.aggregate(15,6,(ROW('📋 ORDERS'!$B$4:$B$675)-3)/(IF($B$4="SKF Order",'📋 ORDERS'!$C$4:$C$675,IF($B$4="TATA Order",'📋 ORDERS'!$D$4:$D$675,IF($B$4="Vulcan PO",'📋 ORDERS'!$E$4:$E$675,'📋 ORDERS'!$Q$4:$Q$675)))=$K$4),25),0)),"")) | D47: =IF(IFERROR(_xludf.aggregate(15,6,(ROW('📋 ORDERS'!$B$4:$B$675)-3)/(IF($B$4="SKF Order",'📋 ORDERS'!$C$4:$C$675,IF($B$4="TATA Order",'📋 ORDERS'!$D$4:$D$675,IF($B$4="Vulcan PO",'📋 ORDERS'!$E$4:$E$675,'📋 ORDERS'!$Q$4:$Q$675)))=$K$4),25),0)=0,"",IFERROR(INDEX('📋 ORDERS'!$G$4:$G$675,IFERROR(_xludf.aggregate(15,6,(ROW('📋 ORDERS'!$B$4:$B$675)-3)/(IF($B$4="SKF Order",'📋 ORDERS'!$C$4:$C$675,IF($B$4="TATA Order",'📋 ORDERS'!$D$4:$D$675,IF($B$4="Vulcan PO",'📋 ORDERS'!$E$4:$E$675,'📋 ORDERS'!$Q$4:$Q$675)))=$K$4),25),0)),"")) | F47: =IF(IFERROR(_xludf.aggregate(15,6,(ROW('📋 ORDERS'!$B$4:$B$675)-3)/(IF($B$4="SKF Order",'📋 ORDERS'!$C$4:$C$675,IF($B$4="TATA Order",'📋 ORDERS'!$D$4:$D$675,IF($B$4="Vulcan PO",'📋 ORDERS'!$E$4:$E$675,'📋 ORDERS'!$Q$4:$Q$675)))=$K$4),25),0)=0,"",IFERROR(INDEX('📋 ORDERS'!$K$4:$K$675,IFERROR(_xludf.aggregate(15,6,(ROW('📋 ORDERS'!$B$4:$B$675)-3)/(IF($B$4="SKF Order",'📋 ORDERS'!$C$4:$C$675,IF($B$4="TATA Order",'📋 ORDERS'!$D$4:$D$675,IF($B$4="Vulcan PO",'📋 ORDERS'!$E$4:$E$675,'📋 ORDERS'!$Q$4:$Q$675)))=$K$4),25),0)),"")) | G47: =IF(IFERROR(_xludf.aggregate(15,6,(ROW('📋 ORDERS'!$B$4:$B$675)-3)/(IF($B$4="SKF Order",'📋 ORDERS'!$C$4:$C$675,IF($B$4="TATA Order",'📋 ORDERS'!$D$4:$D$675,IF($B$4="Vulcan PO",'📋 ORDERS'!$E$4:$E$675,'📋 ORDERS'!$Q$4:$Q$675)))=$K$4),25),0)=0,"",IFERROR(INDEX('📋 ORDERS'!$L$4:$L$675,IFERROR(_xludf.aggregate(15,6,(ROW('📋 ORDERS'!$B$4:$B$675)-3)/(IF($B$4="SKF Order",'📋 ORDERS'!$C$4:$C$675,IF($B$4="TATA Order",'📋 ORDERS'!$D$4:$D$675,IF($B$4="Vulcan PO",'📋 ORDERS'!$E$4:$E$675,'📋 ORDERS'!$Q$4:$Q$675)))=$K$4),25),0)),"")) | H47: =IF(IFERROR(_xludf.aggregate(15,6,(ROW('📋 ORDERS'!$B$4:$B$675)-3)/(IF($B$4="SKF Order",'📋 ORDERS'!$C$4:$C$675,IF($B$4="TATA Order",'📋 ORDERS'!$D$4:$D$675,IF($B$4="Vulcan PO",'📋 ORDERS'!$E$4:$E$675,'📋 ORDERS'!$Q$4:$Q$675)))=$K$4),25),0)=0,"",IFERROR(INDEX('📋 ORDERS'!$M$4:$M$675,IFERROR(_xludf.aggregate(15,6,(ROW('📋 ORDERS'!$B$4:$B$675)-3)/(IF($B$4="SKF Order",'📋 ORDERS'!$C$4:$C$675,IF($B$4="TATA Order",'📋 ORDERS'!$D$4:$D$675,IF($B$4="Vulcan PO",'📋 ORDERS'!$E$4:$E$675,'📋 ORDERS'!$Q$4:$Q$675)))=$K$4),25),0)),"")) | I47: =IF(IFERROR(_xludf.aggregate(15,6,(ROW('📋 ORDERS'!$B$4:$B$675)-3)/(IF($B$4="SKF Order",'📋 ORDERS'!$C$4:$C$675,IF($B$4="TATA Order",'📋 ORDERS'!$D$4:$D$675,IF($B$4="Vulcan PO",'📋 ORDERS'!$E$4:$E$675,'📋 ORDERS'!$Q$4:$Q$675)))=$K$4),25),0)=0,"",IFERROR(INDEX('📋 ORDERS'!$R$4:$R$675,IFERROR(_xludf.aggregate(15,6,(ROW('📋 ORDERS'!$B$4:$B$675)-3)/(IF($B$4="SKF Order",'📋 ORDERS'!$C$4:$C$675,IF($B$4="TATA Order",'📋 ORDERS'!$D$4:$D$675,IF($B$4="Vulcan PO",'📋 ORDERS'!$E$4:$E$675,'📋 ORDERS'!$Q$4:$Q$675)))=$K$4),25),0)),"")) | J47: =IF(IFERROR(_xludf.aggregate(15,6,(ROW('📋 ORDERS'!$B$4:$B$675)-3)/(IF($B$4="SKF Order",'📋 ORDERS'!$C$4:$C$675,IF($B$4="TATA Order",'📋 ORDERS'!$D$4:$D$675,IF($B$4="Vulcan PO",'📋 ORDERS'!$E$4:$E$675,'📋 ORDERS'!$Q$4:$Q$675)))=$K$4),25),0)=0,"",IFERROR(INDEX('📋 ORDERS'!$S$4:$S$675,IFERROR(_xludf.aggregate(15,6,(ROW('📋 ORDERS'!$B$4:$B$675)-3)/(IF($B$4="SKF Order",'📋 ORDERS'!$C$4:$C$675,IF($B$4="TATA Order",'📋 ORDERS'!$D$4:$D$675,IF($B$4="Vulcan PO",'📋 ORDERS'!$E$4:$E$675,'📋 ORDERS'!$Q$4:$Q$675)))=$K$4),25),0)),""))
B48: =IF(IFERROR(_xludf.aggregate(15,6,(ROW('📋 ORDERS'!$B$4:$B$675)-3)/(IF($B$4="SKF Order",'📋 ORDERS'!$C$4:$C$675,IF($B$4="TATA Order",'📋 ORDERS'!$D$4:$D$675,IF($B$4="Vulcan PO",'📋 ORDERS'!$E$4:$E$675,'📋 ORDERS'!$Q$4:$Q$675)))=$K$4),26),0)=0,"",26) | C48: =IF(IFERROR(_xludf.aggregate(15,6,(ROW('📋 ORDERS'!$B$4:$B$675)-3)/(IF($B$4="SKF Order",'📋 ORDERS'!$C$4:$C$675,IF($B$4="TATA Order",'📋 ORDERS'!$D$4:$D$675,IF($B$4="Vulcan PO",'📋 ORDERS'!$E$4:$E$675,'📋 ORDERS'!$Q$4:$Q$675)))=$K$4),26),0)=0,"",IFERROR(INDEX('📋 ORDERS'!$C$4:$C$675,IFERROR(_xludf.aggregate(15,6,(ROW('📋 ORDERS'!$B$4:$B$675)-3)/(IF($B$4="SKF Order",'📋 ORDERS'!$C$4:$C$675,IF($B$4="TATA Order",'📋 ORDERS'!$D$4:$D$675,IF($B$4="Vulcan PO",'📋 ORDERS'!$E$4:$E$675,'📋 ORDERS'!$Q$4:$Q$675)))=$K$4),26),0)),"")) | D48: =IF(IFERROR(_xludf.aggregate(15,6,(ROW('📋 ORDERS'!$B$4:$B$675)-3)/(IF($B$4="SKF Order",'📋 ORDERS'!$C$4:$C$675,IF($B$4="TATA Order",'📋 ORDERS'!$D$4:$D$675,IF($B$4="Vulcan PO",'📋 ORDERS'!$E$4:$E$675,'📋 ORDERS'!$Q$4:$Q$675)))=$K$4),26),0)=0,"",IFERROR(INDEX('📋 ORDERS'!$G$4:$G$675,IFERROR(_xludf.aggregate(15,6,(ROW('📋 ORDERS'!$B$4:$B$675)-3)/(IF($B$4="SKF Order",'📋 ORDERS'!$C$4:$C$675,IF($B$4="TATA Order",'📋 ORDERS'!$D$4:$D$675,IF($B$4="Vulcan PO",'📋 ORDERS'!$E$4:$E$675,'📋 ORDERS'!$Q$4:$Q$675)))=$K$4),26),0)),"")) | F48: =IF(IFERROR(_xludf.aggregate(15,6,(ROW('📋 ORDERS'!$B$4:$B$675)-3)/(IF($B$4="SKF Order",'📋 ORDERS'!$C$4:$C$675,IF($B$4="TATA Order",'📋 ORDERS'!$D$4:$D$675,IF($B$4="Vulcan PO",'📋 ORDERS'!$E$4:$E$675,'📋 ORDERS'!$Q$4:$Q$675)))=$K$4),26),0)=0,"",IFERROR(INDEX('📋 ORDERS'!$K$4:$K$675,IFERROR(_xludf.aggregate(15,6,(ROW('📋 ORDERS'!$B$4:$B$675)-3)/(IF($B$4="SKF Order",'📋 ORDERS'!$C$4:$C$675,IF($B$4="TATA Order",'📋 ORDERS'!$D$4:$D$675,IF($B$4="Vulcan PO",'📋 ORDERS'!$E$4:$E$675,'📋 ORDERS'!$Q$4:$Q$675)))=$K$4),26),0)),"")) | G48: =IF(IFERROR(_xludf.aggregate(15,6,(ROW('📋 ORDERS'!$B$4:$B$675)-3)/(IF($B$4="SKF Order",'📋 ORDERS'!$C$4:$C$675,IF($B$4="TATA Order",'📋 ORDERS'!$D$4:$D$675,IF($B$4="Vulcan PO",'📋 ORDERS'!$E$4:$E$675,'📋 ORDERS'!$Q$4:$Q$675)))=$K$4),26),0)=0,"",IFERROR(INDEX('📋 ORDERS'!$L$4:$L$675,IFERROR(_xludf.aggregate(15,6,(ROW('📋 ORDERS'!$B$4:$B$675)-3)/(IF($B$4="SKF Order",'📋 ORDERS'!$C$4:$C$675,IF($B$4="TATA Order",'📋 ORDERS'!$D$4:$D$675,IF($B$4="Vulcan PO",'📋 ORDERS'!$E$4:$E$675,'📋 ORDERS'!$Q$4:$Q$675)))=$K$4),26),0)),"")) | H48: =IF(IFERROR(_xludf.aggregate(15,6,(ROW('📋 ORDERS'!$B$4:$B$675)-3)/(IF($B$4="SKF Order",'📋 ORDERS'!$C$4:$C$675,IF($B$4="TATA Order",'📋 ORDERS'!$D$4:$D$675,IF($B$4="Vulcan PO",'📋 ORDERS'!$E$4:$E$675,'📋 ORDERS'!$Q$4:$Q$675)))=$K$4),26),0)=0,"",IFERROR(INDEX('📋 ORDERS'!$M$4:$M$675,IFERROR(_xludf.aggregate(15,6,(ROW('📋 ORDERS'!$B$4:$B$675)-3)/(IF($B$4="SKF Order",'📋 ORDERS'!$C$4:$C$675,IF($B$4="TATA Order",'📋 ORDERS'!$D$4:$D$675,IF($B$4="Vulcan PO",'📋 ORDERS'!$E$4:$E$675,'📋 ORDERS'!$Q$4:$Q$675)))=$K$4),26),0)),"")) | I48: =IF(IFERROR(_xludf.aggregate(15,6,(ROW('📋 ORDERS'!$B$4:$B$675)-3)/(IF($B$4="SKF Order",'📋 ORDERS'!$C$4:$C$675,IF($B$4="TATA Order",'📋 ORDERS'!$D$4:$D$675,IF($B$4="Vulcan PO",'📋 ORDERS'!$E$4:$E$675,'📋 ORDERS'!$Q$4:$Q$675)))=$K$4),26),0)=0,"",IFERROR(INDEX('📋 ORDERS'!$R$4:$R$675,IFERROR(_xludf.aggregate(15,6,(ROW('📋 ORDERS'!$B$4:$B$675)-3)/(IF($B$4="SKF Order",'📋 ORDERS'!$C$4:$C$675,IF($B$4="TATA Order",'📋 ORDERS'!$D$4:$D$675,IF($B$4="Vulcan PO",'📋 ORDERS'!$E$4:$E$675,'📋 ORDERS'!$Q$4:$Q$675)))=$K$4),26),0)),"")) | J48: =IF(IFERROR(_xludf.aggregate(15,6,(ROW('📋 ORDERS'!$B$4:$B$675)-3)/(IF($B$4="SKF Order",'📋 ORDERS'!$C$4:$C$675,IF($B$4="TATA Order",'📋 ORDERS'!$D$4:$D$675,IF($B$4="Vulcan PO",'📋 ORDERS'!$E$4:$E$675,'📋 ORDERS'!$Q$4:$Q$675)))=$K$4),26),0)=0,"",IFERROR(INDEX('📋 ORDERS'!$S$4:$S$675,IFERROR(_xludf.aggregate(15,6,(ROW('📋 ORDERS'!$B$4:$B$675)-3)/(IF($B$4="SKF Order",'📋 ORDERS'!$C$4:$C$675,IF($B$4="TATA Order",'📋 ORDERS'!$D$4:$D$675,IF($B$4="Vulcan PO",'📋 ORDERS'!$E$4:$E$675,'📋 ORDERS'!$Q$4:$Q$675)))=$K$4),26),0)),""))
B49: =IF(IFERROR(_xludf.aggregate(15,6,(ROW('📋 ORDERS'!$B$4:$B$675)-3)/(IF($B$4="SKF Order",'📋 ORDERS'!$C$4:$C$675,IF($B$4="TATA Order",'📋 ORDERS'!$D$4:$D$675,IF($B$4="Vulcan PO",'📋 ORDERS'!$E$4:$E$675,'📋 ORDERS'!$Q$4:$Q$675)))=$K$4),27),0)=0,"",27) | C49: =IF(IFERROR(_xludf.aggregate(15,6,(ROW('📋 ORDERS'!$B$4:$B$675)-3)/(IF($B$4="SKF Order",'📋 ORDERS'!$C$4:$C$675,IF($B$4="TATA Order",'📋 ORDERS'!$D$4:$D$675,IF($B$4="Vulcan PO",'📋 ORDERS'!$E$4:$E$675,'📋 ORDERS'!$Q$4:$Q$675)))=$K$4),27),0)=0,"",IFERROR(INDEX('📋 ORDERS'!$C$4:$C$675,IFERROR(_xludf.aggregate(15,6,(ROW('📋 ORDERS'!$B$4:$B$675)-3)/(IF($B$4="SKF Order",'📋 ORDERS'!$C$4:$C$675,IF($B$4="TATA Order",'📋 ORDERS'!$D$4:$D$675,IF($B$4="Vulcan PO",'📋 ORDERS'!$E$4:$E$675,'📋 ORDERS'!$Q$4:$Q$675)))=$K$4),27),0)),"")) | D49: =IF(IFERROR(_xludf.aggregate(15,6,(ROW('📋 ORDERS'!$B$4:$B$675)-3)/(IF($B$4="SKF Order",'📋 ORDERS'!$C$4:$C$675,IF($B$4="TATA Order",'📋 ORDERS'!$D$4:$D$675,IF($B$4="Vulcan PO",'📋 ORDERS'!$E$4:$E$675,'📋 ORDERS'!$Q$4:$Q$675)))=$K$4),27),0)=0,"",IFERROR(INDEX('📋 ORDERS'!$G$4:$G$675,IFERROR(_xludf.aggregate(15,6,(ROW('📋 ORDERS'!$B$4:$B$675)-3)/(IF($B$4="SKF Order",'📋 ORDERS'!$C$4:$C$675,IF($B$4="TATA Order",'📋 ORDERS'!$D$4:$D$675,IF($B$4="Vulcan PO",'📋 ORDERS'!$E$4:$E$675,'📋 ORDERS'!$Q$4:$Q$675)))=$K$4),27),0)),"")) | F49: =IF(IFERROR(_xludf.aggregate(15,6,(ROW('📋 ORDERS'!$B$4:$B$675)-3)/(IF($B$4="SKF Order",'📋 ORDERS'!$C$4:$C$675,IF($B$4="TATA Order",'📋 ORDERS'!$D$4:$D$675,IF($B$4="Vulcan PO",'📋 ORDERS'!$E$4:$E$675,'📋 ORDERS'!$Q$4:$Q$675)))=$K$4),27),0)=0,"",IFERROR(INDEX('📋 ORDERS'!$K$4:$K$675,IFERROR(_xludf.aggregate(15,6,(ROW('📋 ORDERS'!$B$4:$B$675)-3)/(IF($B$4="SKF Order",'📋 ORDERS'!$C$4:$C$675,IF($B$4="TATA Order",'📋 ORDERS'!$D$4:$D$675,IF($B$4="Vulcan PO",'📋 ORDERS'!$E$4:$E$675,'📋 ORDERS'!$Q$4:$Q$675)))=$K$4),27),0)),"")) | G49: =IF(IFERROR(_xludf.aggregate(15,6,(ROW('📋 ORDERS'!$B$4:$B$675)-3)/(IF($B$4="SKF Order",'📋 ORDERS'!$C$4:$C$675,IF($B$4="TATA Order",'📋 ORDERS'!$D$4:$D$675,IF($B$4="Vulcan PO",'📋 ORDERS'!$E$4:$E$675,'📋 ORDERS'!$Q$4:$Q$675)))=$K$4),27),0)=0,"",IFERROR(INDEX('📋 ORDERS'!$L$4:$L$675,IFERROR(_xludf.aggregate(15,6,(ROW('📋 ORDERS'!$B$4:$B$675)-3)/(IF($B$4="SKF Order",'📋 ORDERS'!$C$4:$C$675,IF($B$4="TATA Order",'📋 ORDERS'!$D$4:$D$675,IF($B$4="Vulcan PO",'📋 ORDERS'!$E$4:$E$675,'📋 ORDERS'!$Q$4:$Q$675)))=$K$4),27),0)),"")) | H49: =IF(IFERROR(_xludf.aggregate(15,6,(ROW('📋 ORDERS'!$B$4:$B$675)-3)/(IF($B$4="SKF Order",'📋 ORDERS'!$C$4:$C$675,IF($B$4="TATA Order",'📋 ORDERS'!$D$4:$D$675,IF($B$4="Vulcan PO",'📋 ORDERS'!$E$4:$E$675,'📋 ORDERS'!$Q$4:$Q$675)))=$K$4),27),0)=0,"",IFERROR(INDEX('📋 ORDERS'!$M$4:$M$675,IFERROR(_xludf.aggregate(15,6,(ROW('📋 ORDERS'!$B$4:$B$675)-3)/(IF($B$4="SKF Order",'📋 ORDERS'!$C$4:$C$675,IF($B$4="TATA Order",'📋 ORDERS'!$D$4:$D$675,IF($B$4="Vulcan PO",'📋 ORDERS'!$E$4:$E$675,'📋 ORDERS'!$Q$4:$Q$675)))=$K$4),27),0)),"")) | I49: =IF(IFERROR(_xludf.aggregate(15,6,(ROW('📋 ORDERS'!$B$4:$B$675)-3)/(IF($B$4="SKF Order",'📋 ORDERS'!$C$4:$C$675,IF($B$4="TATA Order",'📋 ORDERS'!$D$4:$D$675,IF($B$4="Vulcan PO",'📋 ORDERS'!$E$4:$E$675,'📋 ORDERS'!$Q$4:$Q$675)))=$K$4),27),0)=0,"",IFERROR(INDEX('📋 ORDERS'!$R$4:$R$675,IFERROR(_xludf.aggregate(15,6,(ROW('📋 ORDERS'!$B$4:$B$675)-3)/(IF($B$4="SKF Order",'📋 ORDERS'!$C$4:$C$675,IF($B$4="TATA Order",'📋 ORDERS'!$D$4:$D$675,IF($B$4="Vulcan PO",'📋 ORDERS'!$E$4:$E$675,'📋 ORDERS'!$Q$4:$Q$675)))=$K$4),27),0)),"")) | J49: =IF(IFERROR(_xludf.aggregate(15,6,(ROW('📋 ORDERS'!$B$4:$B$675)-3)/(IF($B$4="SKF Order",'📋 ORDERS'!$C$4:$C$675,IF($B$4="TATA Order",'📋 ORDERS'!$D$4:$D$675,IF($B$4="Vulcan PO",'📋 ORDERS'!$E$4:$E$675,'📋 ORDERS'!$Q$4:$Q$675)))=$K$4),27),0)=0,"",IFERROR(INDEX('📋 ORDERS'!$S$4:$S$675,IFERROR(_xludf.aggregate(15,6,(ROW('📋 ORDERS'!$B$4:$B$675)-3)/(IF($B$4="SKF Order",'📋 ORDERS'!$C$4:$C$675,IF($B$4="TATA Order",'📋 ORDERS'!$D$4:$D$675,IF($B$4="Vulcan PO",'📋 ORDERS'!$E$4:$E$675,'📋 ORDERS'!$Q$4:$Q$675)))=$K$4),27),0)),""))
B50: =IF(IFERROR(_xludf.aggregate(15,6,(ROW('📋 ORDERS'!$B$4:$B$675)-3)/(IF($B$4="SKF Order",'📋 ORDERS'!$C$4:$C$675,IF($B$4="TATA Order",'📋 ORDERS'!$D$4:$D$675,IF($B$4="Vulcan PO",'📋 ORDERS'!$E$4:$E$675,'📋 ORDERS'!$Q$4:$Q$675)))=$K$4),28),0)=0,"",28) | C50: =IF(IFERROR(_xludf.aggregate(15,6,(ROW('📋 ORDERS'!$B$4:$B$675)-3)/(IF($B$4="SKF Order",'📋 ORDERS'!$C$4:$C$675,IF($B$4="TATA Order",'📋 ORDERS'!$D$4:$D$675,IF($B$4="Vulcan PO",'📋 ORDERS'!$E$4:$E$675,'📋 ORDERS'!$Q$4:$Q$675)))=$K$4),28),0)=0,"",IFERROR(INDEX('📋 ORDERS'!$C$4:$C$675,IFERROR(_xludf.aggregate(15,6,(ROW('📋 ORDERS'!$B$4:$B$675)-3)/(IF($B$4="SKF Order",'📋 ORDERS'!$C$4:$C$675,IF($B$4="TATA Order",'📋 ORDERS'!$D$4:$D$675,IF($B$4="Vulcan PO",'📋 ORDERS'!$E$4:$E$675,'📋 ORDERS'!$Q$4:$Q$675)))=$K$4),28),0)),"")) | D50: =IF(IFERROR(_xludf.aggregate(15,6,(ROW('📋 ORDERS'!$B$4:$B$675)-3)/(IF($B$4="SKF Order",'📋 ORDERS'!$C$4:$C$675,IF($B$4="TATA Order",'📋 ORDERS'!$D$4:$D$675,IF($B$4="Vulcan PO",'📋 ORDERS'!$E$4:$E$675,'📋 ORDERS'!$Q$4:$Q$675)))=$K$4),28),0)=0,"",IFERROR(INDEX('📋 ORDERS'!$G$4:$G$675,IFERROR(_xludf.aggregate(15,6,(ROW('📋 ORDERS'!$B$4:$B$675)-3)/(IF($B$4="SKF Order",'📋 ORDERS'!$C$4:$C$675,IF($B$4="TATA Order",'📋 ORDERS'!$D$4:$D$675,IF($B$4="Vulcan PO",'📋 ORDERS'!$E$4:$E$675,'📋 ORDERS'!$Q$4:$Q$675)))=$K$4),28),0)),"")) | F50: =IF(IFERROR(_xludf.aggregate(15,6,(ROW('📋 ORDERS'!$B$4:$B$675)-3)/(IF($B$4="SKF Order",'📋 ORDERS'!$C$4:$C$675,IF($B$4="TATA Order",'📋 ORDERS'!$D$4:$D$675,IF($B$4="Vulcan PO",'📋 ORDERS'!$E$4:$E$675,'📋 ORDERS'!$Q$4:$Q$675)))=$K$4),28),0)=0,"",IFERROR(INDEX('📋 ORDERS'!$K$4:$K$675,IFERROR(_xludf.aggregate(15,6,(ROW('📋 ORDERS'!$B$4:$B$675)-3)/(IF($B$4="SKF Order",'📋 ORDERS'!$C$4:$C$675,IF($B$4="TATA Order",'📋 ORDERS'!$D$4:$D$675,IF($B$4="Vulcan PO",'📋 ORDERS'!$E$4:$E$675,'📋 ORDERS'!$Q$4:$Q$675)))=$K$4),28),0)),"")) | G50: =IF(IFERROR(_xludf.aggregate(15,6,(ROW('📋 ORDERS'!$B$4:$B$675)-3)/(IF($B$4="SKF Order",'📋 ORDERS'!$C$4:$C$675,IF($B$4="TATA Order",'📋 ORDERS'!$D$4:$D$675,IF($B$4="Vulcan PO",'📋 ORDERS'!$E$4:$E$675,'📋 ORDERS'!$Q$4:$Q$675)))=$K$4),28),0)=0,"",IFERROR(INDEX('📋 ORDERS'!$L$4:$L$675,IFERROR(_xludf.aggregate(15,6,(ROW('📋 ORDERS'!$B$4:$B$675)-3)/(IF($B$4="SKF Order",'📋 ORDERS'!$C$4:$C$675,IF($B$4="TATA Order",'📋 ORDERS'!$D$4:$D$675,IF($B$4="Vulcan PO",'📋 ORDERS'!$E$4:$E$675,'📋 ORDERS'!$Q$4:$Q$675)))=$K$4),28),0)),"")) | H50: =IF(IFERROR(_xludf.aggregate(15,6,(ROW('📋 ORDERS'!$B$4:$B$675)-3)/(IF($B$4="SKF Order",'📋 ORDERS'!$C$4:$C$675,IF($B$4="TATA Order",'📋 ORDERS'!$D$4:$D$675,IF($B$4="Vulcan PO",'📋 ORDERS'!$E$4:$E$675,'📋 ORDERS'!$Q$4:$Q$675)))=$K$4),28),0)=0,"",IFERROR(INDEX('📋 ORDERS'!$M$4:$M$675,IFERROR(_xludf.aggregate(15,6,(ROW('📋 ORDERS'!$B$4:$B$675)-3)/(IF($B$4="SKF Order",'📋 ORDERS'!$C$4:$C$675,IF($B$4="TATA Order",'📋 ORDERS'!$D$4:$D$675,IF($B$4="Vulcan PO",'📋 ORDERS'!$E$4:$E$675,'📋 ORDERS'!$Q$4:$Q$675)))=$K$4),28),0)),"")) | I50: =IF(IFERROR(_xludf.aggregate(15,6,(ROW('📋 ORDERS'!$B$4:$B$675)-3)/(IF($B$4="SKF Order",'📋 ORDERS'!$C$4:$C$675,IF($B$4="TATA Order",'📋 ORDERS'!$D$4:$D$675,IF($B$4="Vulcan PO",'📋 ORDERS'!$E$4:$E$675,'📋 ORDERS'!$Q$4:$Q$675)))=$K$4),28),0)=0,"",IFERROR(INDEX('📋 ORDERS'!$R$4:$R$675,IFERROR(_xludf.aggregate(15,6,(ROW('📋 ORDERS'!$B$4:$B$675)-3)/(IF($B$4="SKF Order",'📋 ORDERS'!$C$4:$C$675,IF($B$4="TATA Order",'📋 ORDERS'!$D$4:$D$675,IF($B$4="Vulcan PO",'📋 ORDERS'!$E$4:$E$675,'📋 ORDERS'!$Q$4:$Q$675)))=$K$4),28),0)),"")) | J50: =IF(IFERROR(_xludf.aggregate(15,6,(ROW('📋 ORDERS'!$B$4:$B$675)-3)/(IF($B$4="SKF Order",'📋 ORDERS'!$C$4:$C$675,IF($B$4="TATA Order",'📋 ORDERS'!$D$4:$D$675,IF($B$4="Vulcan PO",'📋 ORDERS'!$E$4:$E$675,'📋 ORDERS'!$Q$4:$Q$675)))=$K$4),28),0)=0,"",IFERROR(INDEX('📋 ORDERS'!$S$4:$S$675,IFERROR(_xludf.aggregate(15,6,(ROW('📋 ORDERS'!$B$4:$B$675)-3)/(IF($B$4="SKF Order",'📋 ORDERS'!$C$4:$C$675,IF($B$4="TATA Order",'📋 ORDERS'!$D$4:$D$675,IF($B$4="Vulcan PO",'📋 ORDERS'!$E$4:$E$675,'📋 ORDERS'!$Q$4:$Q$675)))=$K$4),28),0)),""))
B51: =IF(IFERROR(_xludf.aggregate(15,6,(ROW('📋 ORDERS'!$B$4:$B$675)-3)/(IF($B$4="SKF Order",'📋 ORDERS'!$C$4:$C$675,IF($B$4="TATA Order",'📋 ORDERS'!$D$4:$D$675,IF($B$4="Vulcan PO",'📋 ORDERS'!$E$4:$E$675,'📋 ORDERS'!$Q$4:$Q$675)))=$K$4),29),0)=0,"",29) | C51: =IF(IFERROR(_xludf.aggregate(15,6,(ROW('📋 ORDERS'!$B$4:$B$675)-3)/(IF($B$4="SKF Order",'📋 ORDERS'!$C$4:$C$675,IF($B$4="TATA Order",'📋 ORDERS'!$D$4:$D$675,IF($B$4="Vulcan PO",'📋 ORDERS'!$E$4:$E$675,'📋 ORDERS'!$Q$4:$Q$675)))=$K$4),29),0)=0,"",IFERROR(INDEX('📋 ORDERS'!$C$4:$C$675,IFERROR(_xludf.aggregate(15,6,(ROW('📋 ORDERS'!$B$4:$B$675)-3)/(IF($B$4="SKF Order",'📋 ORDERS'!$C$4:$C$675,IF($B$4="TATA Order",'📋 ORDERS'!$D$4:$D$675,IF($B$4="Vulcan PO",'📋 ORDERS'!$E$4:$E$675,'📋 ORDERS'!$Q$4:$Q$675)))=$K$4),29),0)),"")) | D51: =IF(IFERROR(_xludf.aggregate(15,6,(ROW('📋 ORDERS'!$B$4:$B$675)-3)/(IF($B$4="SKF Order",'📋 ORDERS'!$C$4:$C$675,IF($B$4="TATA Order",'📋 ORDERS'!$D$4:$D$675,IF($B$4="Vulcan PO",'📋 ORDERS'!$E$4:$E$675,'📋 ORDERS'!$Q$4:$Q$675)))=$K$4),29),0)=0,"",IFERROR(INDEX('📋 ORDERS'!$G$4:$G$675,IFERROR(_xludf.aggregate(15,6,(ROW('📋 ORDERS'!$B$4:$B$675)-3)/(IF($B$4="SKF Order",'📋 ORDERS'!$C$4:$C$675,IF($B$4="TATA Order",'📋 ORDERS'!$D$4:$D$675,IF($B$4="Vulcan PO",'📋 ORDERS'!$E$4:$E$675,'📋 ORDERS'!$Q$4:$Q$675)))=$K$4),29),0)),"")) | F51: =IF(IFERROR(_xludf.aggregate(15,6,(ROW('📋 ORDERS'!$B$4:$B$675)-3)/(IF($B$4="SKF Order",'📋 ORDERS'!$C$4:$C$675,IF($B$4="TATA Order",'📋 ORDERS'!$D$4:$D$675,IF($B$4="Vulcan PO",'📋 ORDERS'!$E$4:$E$675,'📋 ORDERS'!$Q$4:$Q$675)))=$K$4),29),0)=0,"",IFERROR(INDEX('📋 ORDERS'!$K$4:$K$675,IFERROR(_xludf.aggregate(15,6,(ROW('📋 ORDERS'!$B$4:$B$675)-3)/(IF($B$4="SKF Order",'📋 ORDERS'!$C$4:$C$675,IF($B$4="TATA Order",'📋 ORDERS'!$D$4:$D$675,IF($B$4="Vulcan PO",'📋 ORDERS'!$E$4:$E$675,'📋 ORDERS'!$Q$4:$Q$675)))=$K$4),29),0)),"")) | G51: =IF(IFERROR(_xludf.aggregate(15,6,(ROW('📋 ORDERS'!$B$4:$B$675)-3)/(IF($B$4="SKF Order",'📋 ORDERS'!$C$4:$C$675,IF($B$4="TATA Order",'📋 ORDERS'!$D$4:$D$675,IF($B$4="Vulcan PO",'📋 ORDERS'!$E$4:$E$675,'📋 ORDERS'!$Q$4:$Q$675)))=$K$4),29),0)=0,"",IFERROR(INDEX('📋 ORDERS'!$L$4:$L$675,IFERROR(_xludf.aggregate(15,6,(ROW('📋 ORDERS'!$B$4:$B$675)-3)/(IF($B$4="SKF Order",'📋 ORDERS'!$C$4:$C$675,IF($B$4="TATA Order",'📋 ORDERS'!$D$4:$D$675,IF($B$4="Vulcan PO",'📋 ORDERS'!$E$4:$E$675,'📋 ORDERS'!$Q$4:$Q$675)))=$K$4),29),0)),"")) | H51: =IF(IFERROR(_xludf.aggregate(15,6,(ROW('📋 ORDERS'!$B$4:$B$675)-3)/(IF($B$4="SKF Order",'📋 ORDERS'!$C$4:$C$675,IF($B$4="TATA Order",'📋 ORDERS'!$D$4:$D$675,IF($B$4="Vulcan PO",'📋 ORDERS'!$E$4:$E$675,'📋 ORDERS'!$Q$4:$Q$675)))=$K$4),29),0)=0,"",IFERROR(INDEX('📋 ORDERS'!$M$4:$M$675,IFERROR(_xludf.aggregate(15,6,(ROW('📋 ORDERS'!$B$4:$B$675)-3)/(IF($B$4="SKF Order",'📋 ORDERS'!$C$4:$C$675,IF($B$4="TATA Order",'📋 ORDERS'!$D$4:$D$675,IF($B$4="Vulcan PO",'📋 ORDERS'!$E$4:$E$675,'📋 ORDERS'!$Q$4:$Q$675)))=$K$4),29),0)),"")) | I51: =IF(IFERROR(_xludf.aggregate(15,6,(ROW('📋 ORDERS'!$B$4:$B$675)-3)/(IF($B$4="SKF Order",'📋 ORDERS'!$C$4:$C$675,IF($B$4="TATA Order",'📋 ORDERS'!$D$4:$D$675,IF($B$4="Vulcan PO",'📋 ORDERS'!$E$4:$E$675,'📋 ORDERS'!$Q$4:$Q$675)))=$K$4),29),0)=0,"",IFERROR(INDEX('📋 ORDERS'!$R$4:$R$675,IFERROR(_xludf.aggregate(15,6,(ROW('📋 ORDERS'!$B$4:$B$675)-3)/(IF($B$4="SKF Order",'📋 ORDERS'!$C$4:$C$675,IF($B$4="TATA Order",'📋 ORDERS'!$D$4:$D$675,IF($B$4="Vulcan PO",'📋 ORDERS'!$E$4:$E$675,'📋 ORDERS'!$Q$4:$Q$675)))=$K$4),29),0)),"")) | J51: =IF(IFERROR(_xludf.aggregate(15,6,(ROW('📋 ORDERS'!$B$4:$B$675)-3)/(IF($B$4="SKF Order",'📋 ORDERS'!$C$4:$C$675,IF($B$4="TATA Order",'📋 ORDERS'!$D$4:$D$675,IF($B$4="Vulcan PO",'📋 ORDERS'!$E$4:$E$675,'📋 ORDERS'!$Q$4:$Q$675)))=$K$4),29),0)=0,"",IFERROR(INDEX('📋 ORDERS'!$S$4:$S$675,IFERROR(_xludf.aggregate(15,6,(ROW('📋 ORDERS'!$B$4:$B$675)-3)/(IF($B$4="SKF Order",'📋 ORDERS'!$C$4:$C$675,IF($B$4="TATA Order",'📋 ORDERS'!$D$4:$D$675,IF($B$4="Vulcan PO",'📋 ORDERS'!$E$4:$E$675,'📋 ORDERS'!$Q$4:$Q$675)))=$K$4),29),0)),""))
B52: =IF(IFERROR(_xludf.aggregate(15,6,(ROW('📋 ORDERS'!$B$4:$B$675)-3)/(IF($B$4="SKF Order",'📋 ORDERS'!$C$4:$C$675,IF($B$4="TATA Order",'📋 ORDERS'!$D$4:$D$675,IF($B$4="Vulcan PO",'📋 ORDERS'!$E$4:$E$675,'📋 ORDERS'!$Q$4:$Q$675)))=$K$4),30),0)=0,"",30) | C52: =IF(IFERROR(_xludf.aggregate(15,6,(ROW('📋 ORDERS'!$B$4:$B$675)-3)/(IF($B$4="SKF Order",'📋 ORDERS'!$C$4:$C$675,IF($B$4="TATA Order",'📋 ORDERS'!$D$4:$D$675,IF($B$4="Vulcan PO",'📋 ORDERS'!$E$4:$E$675,'📋 ORDERS'!$Q$4:$Q$675)))=$K$4),30),0)=0,"",IFERROR(INDEX('📋 ORDERS'!$C$4:$C$675,IFERROR(_xludf.aggregate(15,6,(ROW('📋 ORDERS'!$B$4:$B$675)-3)/(IF($B$4="SKF Order",'📋 ORDERS'!$C$4:$C$675,IF($B$4="TATA Order",'📋 ORDERS'!$D$4:$D$675,IF($B$4="Vulcan PO",'📋 ORDERS'!$E$4:$E$675,'📋 ORDERS'!$Q$4:$Q$675)))=$K$4),30),0)),"")) | D52: =IF(IFERROR(_xludf.aggregate(15,6,(ROW('📋 ORDERS'!$B$4:$B$675)-3)/(IF($B$4="SKF Order",'📋 ORDERS'!$C$4:$C$675,IF($B$4="TATA Order",'📋 ORDERS'!$D$4:$D$675,IF($B$4="Vulcan PO",'📋 ORDERS'!$E$4:$E$675,'📋 ORDERS'!$Q$4:$Q$675)))=$K$4),30),0)=0,"",IFERROR(INDEX('📋 ORDERS'!$G$4:$G$675,IFERROR(_xludf.aggregate(15,6,(ROW('📋 ORDERS'!$B$4:$B$675)-3)/(IF($B$4="SKF Order",'📋 ORDERS'!$C$4:$C$675,IF($B$4="TATA Order",'📋 ORDERS'!$D$4:$D$675,IF($B$4="Vulcan PO",'📋 ORDERS'!$E$4:$E$675,'📋 ORDERS'!$Q$4:$Q$675)))=$K$4),30),0)),"")) | F52: =IF(IFERROR(_xludf.aggregate(15,6,(ROW('📋 ORDERS'!$B$4:$B$675)-3)/(IF($B$4="SKF Order",'📋 ORDERS'!$C$4:$C$675,IF($B$4="TATA Order",'📋 ORDERS'!$D$4:$D$675,IF($B$4="Vulcan PO",'📋 ORDERS'!$E$4:$E$675,'📋 ORDERS'!$Q$4:$Q$675)))=$K$4),30),0)=0,"",IFERROR(INDEX('📋 ORDERS'!$K$4:$K$675,IFERROR(_xludf.aggregate(15,6,(ROW('📋 ORDERS'!$B$4:$B$675)-3)/(IF($B$4="SKF Order",'📋 ORDERS'!$C$4:$C$675,IF($B$4="TATA Order",'📋 ORDERS'!$D$4:$D$675,IF($B$4="Vulcan PO",'📋 ORDERS'!$E$4:$E$675,'📋 ORDERS'!$Q$4:$Q$675)))=$K$4),30),0)),"")) | G52: =IF(IFERROR(_xludf.aggregate(15,6,(ROW('📋 ORDERS'!$B$4:$B$675)-3)/(IF($B$4="SKF Order",'📋 ORDERS'!$C$4:$C$675,IF($B$4="TATA Order",'📋 ORDERS'!$D$4:$D$675,IF($B$4="Vulcan PO",'📋 ORDERS'!$E$4:$E$675,'📋 ORDERS'!$Q$4:$Q$675)))=$K$4),30),0)=0,"",IFERROR(INDEX('📋 ORDERS'!$L$4:$L$675,IFERROR(_xludf.aggregate(15,6,(ROW('📋 ORDERS'!$B$4:$B$675)-3)/(IF($B$4="SKF Order",'📋 ORDERS'!$C$4:$C$675,IF($B$4="TATA Order",'📋 ORDERS'!$D$4:$D$675,IF($B$4="Vulcan PO",'📋 ORDERS'!$E$4:$E$675,'📋 ORDERS'!$Q$4:$Q$675)))=$K$4),30),0)),"")) | H52: =IF(IFERROR(_xludf.aggregate(15,6,(ROW('📋 ORDERS'!$B$4:$B$675)-3)/(IF($B$4="SKF Order",'📋 ORDERS'!$C$4:$C$675,IF($B$4="TATA Order",'📋 ORDERS'!$D$4:$D$675,IF($B$4="Vulcan PO",'📋 ORDERS'!$E$4:$E$675,'📋 ORDERS'!$Q$4:$Q$675)))=$K$4),30),0)=0,"",IFERROR(INDEX('📋 ORDERS'!$M$4:$M$675,IFERROR(_xludf.aggregate(15,6,(ROW('📋 ORDERS'!$B$4:$B$675)-3)/(IF($B$4="SKF Order",'📋 ORDERS'!$C$4:$C$675,IF($B$4="TATA Order",'📋 ORDERS'!$D$4:$D$675,IF($B$4="Vulcan PO",'📋 ORDERS'!$E$4:$E$675,'📋 ORDERS'!$Q$4:$Q$675)))=$K$4),30),0)),"")) | I52: =IF(IFERROR(_xludf.aggregate(15,6,(ROW('📋 ORDERS'!$B$4:$B$675)-3)/(IF($B$4="SKF Order",'📋 ORDERS'!$C$4:$C$675,IF($B$4="TATA Order",'📋 ORDERS'!$D$4:$D$675,IF($B$4="Vulcan PO",'📋 ORDERS'!$E$4:$E$675,'📋 ORDERS'!$Q$4:$Q$675)))=$K$4),30),0)=0,"",IFERROR(INDEX('📋 ORDERS'!$R$4:$R$675,IFERROR(_xludf.aggregate(15,6,(ROW('📋 ORDERS'!$B$4:$B$675)-3)/(IF($B$4="SKF Order",'📋 ORDERS'!$C$4:$C$675,IF($B$4="TATA Order",'📋 ORDERS'!$D$4:$D$675,IF($B$4="Vulcan PO",'📋 ORDERS'!$E$4:$E$675,'📋 ORDERS'!$Q$4:$Q$675)))=$K$4),30),0)),"")) | J52: =IF(IFERROR(_xludf.aggregate(15,6,(ROW('📋 ORDERS'!$B$4:$B$675)-3)/(IF($B$4="SKF Order",'📋 ORDERS'!$C$4:$C$675,IF($B$4="TATA Order",'📋 ORDERS'!$D$4:$D$675,IF($B$4="Vulcan PO",'📋 ORDERS'!$E$4:$E$675,'📋 ORDERS'!$Q$4:$Q$675)))=$K$4),30),0)=0,"",IFERROR(INDEX('📋 ORDERS'!$S$4:$S$675,IFERROR(_xludf.aggregate(15,6,(ROW('📋 ORDERS'!$B$4:$B$675)-3)/(IF($B$4="SKF Order",'📋 ORDERS'!$C$4:$C$675,IF($B$4="TATA Order",'📋 ORDERS'!$D$4:$D$675,IF($B$4="Vulcan PO",'📋 ORDERS'!$E$4:$E$675,'📋 ORDERS'!$Q$4:$Q$675)))=$K$4),30),0)),""))
B53: =IF(IFERROR(_xludf.aggregate(15,6,(ROW('📋 ORDERS'!$B$4:$B$675)-3)/(IF($B$4="SKF Order",'📋 ORDERS'!$C$4:$C$675,IF($B$4="TATA Order",'📋 ORDERS'!$D$4:$D$675,IF($B$4="Vulcan PO",'📋 ORDERS'!$E$4:$E$675,'📋 ORDERS'!$Q$4:$Q$675)))=$K$4),31),0)=0,"",31) | C53: =IF(IFERROR(_xludf.aggregate(15,6,(ROW('📋 ORDERS'!$B$4:$B$675)-3)/(IF($B$4="SKF Order",'📋 ORDERS'!$C$4:$C$675,IF($B$4="TATA Order",'📋 ORDERS'!$D$4:$D$675,IF($B$4="Vulcan PO",'📋 ORDERS'!$E$4:$E$675,'📋 ORDERS'!$Q$4:$Q$675)))=$K$4),31),0)=0,"",IFERROR(INDEX('📋 ORDERS'!$C$4:$C$675,IFERROR(_xludf.aggregate(15,6,(ROW('📋 ORDERS'!$B$4:$B$675)-3)/(IF($B$4="SKF Order",'📋 ORDERS'!$C$4:$C$675,IF($B$4="TATA Order",'📋 ORDERS'!$D$4:$D$675,IF($B$4="Vulcan PO",'📋 ORDERS'!$E$4:$E$675,'📋 ORDERS'!$Q$4:$Q$675)))=$K$4),31),0)),"")) | D53: =IF(IFERROR(_xludf.aggregate(15,6,(ROW('📋 ORDERS'!$B$4:$B$675)-3)/(IF($B$4="SKF Order",'📋 ORDERS'!$C$4:$C$675,IF($B$4="TATA Order",'📋 ORDERS'!$D$4:$D$675,IF($B$4="Vulcan PO",'📋 ORDERS'!$E$4:$E$675,'📋 ORDERS'!$Q$4:$Q$675)))=$K$4),31),0)=0,"",IFERROR(INDEX('📋 ORDERS'!$G$4:$G$675,IFERROR(_xludf.aggregate(15,6,(ROW('📋 ORDERS'!$B$4:$B$675)-3)/(IF($B$4="SKF Order",'📋 ORDERS'!$C$4:$C$675,IF($B$4="TATA Order",'📋 ORDERS'!$D$4:$D$675,IF($B$4="Vulcan PO",'📋 ORDERS'!$E$4:$E$675,'📋 ORDERS'!$Q$4:$Q$675)))=$K$4),31),0)),"")) | F53: =IF(IFERROR(_xludf.aggregate(15,6,(ROW('📋 ORDERS'!$B$4:$B$675)-3)/(IF($B$4="SKF Order",'📋 ORDERS'!$C$4:$C$675,IF($B$4="TATA Order",'📋 ORDERS'!$D$4:$D$675,IF($B$4="Vulcan PO",'📋 ORDERS'!$E$4:$E$675,'📋 ORDERS'!$Q$4:$Q$675)))=$K$4),31),0)=0,"",IFERROR(INDEX('📋 ORDERS'!$K$4:$K$675,IFERROR(_xludf.aggregate(15,6,(ROW('📋 ORDERS'!$B$4:$B$675)-3)/(IF($B$4="SKF Order",'📋 ORDERS'!$C$4:$C$675,IF($B$4="TATA Order",'📋 ORDERS'!$D$4:$D$675,IF($B$4="Vulcan PO",'📋 ORDERS'!$E$4:$E$675,'📋 ORDERS'!$Q$4:$Q$675)))=$K$4),31),0)),"")) | G53: =IF(IFERROR(_xludf.aggregate(15,6,(ROW('📋 ORDERS'!$B$4:$B$675)-3)/(IF($B$4="SKF Order",'📋 ORDERS'!$C$4:$C$675,IF($B$4="TATA Order",'📋 ORDERS'!$D$4:$D$675,IF($B$4="Vulcan PO",'📋 ORDERS'!$E$4:$E$675,'📋 ORDERS'!$Q$4:$Q$675)))=$K$4),31),0)=0,"",IFERROR(INDEX('📋 ORDERS'!$L$4:$L$675,IFERROR(_xludf.aggregate(15,6,(ROW('📋 ORDERS'!$B$4:$B$675)-3)/(IF($B$4="SKF Order",'📋 ORDERS'!$C$4:$C$675,IF($B$4="TATA Order",'📋 ORDERS'!$D$4:$D$675,IF($B$4="Vulcan PO",'📋 ORDERS'!$E$4:$E$675,'📋 ORDERS'!$Q$4:$Q$675)))=$K$4),31),0)),"")) | H53: =IF(IFERROR(_xludf.aggregate(15,6,(ROW('📋 ORDERS'!$B$4:$B$675)-3)/(IF($B$4="SKF Order",'📋 ORDERS'!$C$4:$C$675,IF($B$4="TATA Order",'📋 ORDERS'!$D$4:$D$675,IF($B$4="Vulcan PO",'📋 ORDERS'!$E$4:$E$675,'📋 ORDERS'!$Q$4:$Q$675)))=$K$4),31),0)=0,"",IFERROR(INDEX('📋 ORDERS'!$M$4:$M$675,IFERROR(_xludf.aggregate(15,6,(ROW('📋 ORDERS'!$B$4:$B$675)-3)/(IF($B$4="SKF Order",'📋 ORDERS'!$C$4:$C$675,IF($B$4="TATA Order",'📋 ORDERS'!$D$4:$D$675,IF($B$4="Vulcan PO",'📋 ORDERS'!$E$4:$E$675,'📋 ORDERS'!$Q$4:$Q$675)))=$K$4),31),0)),"")) | I53: =IF(IFERROR(_xludf.aggregate(15,6,(ROW('📋 ORDERS'!$B$4:$B$675)-3)/(IF($B$4="SKF Order",'📋 ORDERS'!$C$4:$C$675,IF($B$4="TATA Order",'📋 ORDERS'!$D$4:$D$675,IF($B$4="Vulcan PO",'📋 ORDERS'!$E$4:$E$675,'📋 ORDERS'!$Q$4:$Q$675)))=$K$4),31),0)=0,"",IFERROR(INDEX('📋 ORDERS'!$R$4:$R$675,IFERROR(_xludf.aggregate(15,6,(ROW('📋 ORDERS'!$B$4:$B$675)-3)/(IF($B$4="SKF Order",'📋 ORDERS'!$C$4:$C$675,IF($B$4="TATA Order",'📋 ORDERS'!$D$4:$D$675,IF($B$4="Vulcan PO",'📋 ORDERS'!$E$4:$E$675,'📋 ORDERS'!$Q$4:$Q$675)))=$K$4),31),0)),"")) | J53: =IF(IFERROR(_xludf.aggregate(15,6,(ROW('📋 ORDERS'!$B$4:$B$675)-3)/(IF($B$4="SKF Order",'📋 ORDERS'!$C$4:$C$675,IF($B$4="TATA Order",'📋 ORDERS'!$D$4:$D$675,IF($B$4="Vulcan PO",'📋 ORDERS'!$E$4:$E$675,'📋 ORDERS'!$Q$4:$Q$675)))=$K$4),31),0)=0,"",IFERROR(INDEX('📋 ORDERS'!$S$4:$S$675,IFERROR(_xludf.aggregate(15,6,(ROW('📋 ORDERS'!$B$4:$B$675)-3)/(IF($B$4="SKF Order",'📋 ORDERS'!$C$4:$C$675,IF($B$4="TATA Order",'📋 ORDERS'!$D$4:$D$675,IF($B$4="Vulcan PO",'📋 ORDERS'!$E$4:$E$675,'📋 ORDERS'!$Q$4:$Q$675)))=$K$4),31),0)),""))
B54: =IF(IFERROR(_xludf.aggregate(15,6,(ROW('📋 ORDERS'!$B$4:$B$675)-3)/(IF($B$4="SKF Order",'📋 ORDERS'!$C$4:$C$675,IF($B$4="TATA Order",'📋 ORDERS'!$D$4:$D$675,IF($B$4="Vulcan PO",'📋 ORDERS'!$E$4:$E$675,'📋 ORDERS'!$Q$4:$Q$675)))=$K$4),32),0)=0,"",32) | C54: =IF(IFERROR(_xludf.aggregate(15,6,(ROW('📋 ORDERS'!$B$4:$B$675)-3)/(IF($B$4="SKF Order",'📋 ORDERS'!$C$4:$C$675,IF($B$4="TATA Order",'📋 ORDERS'!$D$4:$D$675,IF($B$4="Vulcan PO",'📋 ORDERS'!$E$4:$E$675,'📋 ORDERS'!$Q$4:$Q$675)))=$K$4),32),0)=0,"",IFERROR(INDEX('📋 ORDERS'!$C$4:$C$675,IFERROR(_xludf.aggregate(15,6,(ROW('📋 ORDERS'!$B$4:$B$675)-3)/(IF($B$4="SKF Order",'📋 ORDERS'!$C$4:$C$675,IF($B$4="TATA Order",'📋 ORDERS'!$D$4:$D$675,IF($B$4="Vulcan PO",'📋 ORDERS'!$E$4:$E$675,'📋 ORDERS'!$Q$4:$Q$675)))=$K$4),32),0)),"")) | D54: =IF(IFERROR(_xludf.aggregate(15,6,(ROW('📋 ORDERS'!$B$4:$B$675)-3)/(IF($B$4="SKF Order",'📋 ORDERS'!$C$4:$C$675,IF($B$4="TATA Order",'📋 ORDERS'!$D$4:$D$675,IF($B$4="Vulcan PO",'📋 ORDERS'!$E$4:$E$675,'📋 ORDERS'!$Q$4:$Q$675)))=$K$4),32),0)=0,"",IFERROR(INDEX('📋 ORDERS'!$G$4:$G$675,IFERROR(_xludf.aggregate(15,6,(ROW('📋 ORDERS'!$B$4:$B$675)-3)/(IF($B$4="SKF Order",'📋 ORDERS'!$C$4:$C$675,IF($B$4="TATA Order",'📋 ORDERS'!$D$4:$D$675,IF($B$4="Vulcan PO",'📋 ORDERS'!$E$4:$E$675,'📋 ORDERS'!$Q$4:$Q$675)))=$K$4),32),0)),"")) | F54: =IF(IFERROR(_xludf.aggregate(15,6,(ROW('📋 ORDERS'!$B$4:$B$675)-3)/(IF($B$4="SKF Order",'📋 ORDERS'!$C$4:$C$675,IF($B$4="TATA Order",'📋 ORDERS'!$D$4:$D$675,IF($B$4="Vulcan PO",'📋 ORDERS'!$E$4:$E$675,'📋 ORDERS'!$Q$4:$Q$675)))=$K$4),32),0)=0,"",IFERROR(INDEX('📋 ORDERS'!$K$4:$K$675,IFERROR(_xludf.aggregate(15,6,(ROW('📋 ORDERS'!$B$4:$B$675)-3)/(IF($B$4="SKF Order",'📋 ORDERS'!$C$4:$C$675,IF($B$4="TATA Order",'📋 ORDERS'!$D$4:$D$675,IF($B$4="Vulcan PO",'📋 ORDERS'!$E$4:$E$675,'📋 ORDERS'!$Q$4:$Q$675)))=$K$4),32),0)),"")) | G54: =IF(IFERROR(_xludf.aggregate(15,6,(ROW('📋 ORDERS'!$B$4:$B$675)-3)/(IF($B$4="SKF Order",'📋 ORDERS'!$C$4:$C$675,IF($B$4="TATA Order",'📋 ORDERS'!$D$4:$D$675,IF($B$4="Vulcan PO",'📋 ORDERS'!$E$4:$E$675,'📋 ORDERS'!$Q$4:$Q$675)))=$K$4),32),0)=0,"",IFERROR(INDEX('📋 ORDERS'!$L$4:$L$675,IFERROR(_xludf.aggregate(15,6,(ROW('📋 ORDERS'!$B$4:$B$675)-3)/(IF($B$4="SKF Order",'📋 ORDERS'!$C$4:$C$675,IF($B$4="TATA Order",'📋 ORDERS'!$D$4:$D$675,IF($B$4="Vulcan PO",'📋 ORDERS'!$E$4:$E$675,'📋 ORDERS'!$Q$4:$Q$675)))=$K$4),32),0)),"")) | H54: =IF(IFERROR(_xludf.aggregate(15,6,(ROW('📋 ORDERS'!$B$4:$B$675)-3)/(IF($B$4="SKF Order",'📋 ORDERS'!$C$4:$C$675,IF($B$4="TATA Order",'📋 ORDERS'!$D$4:$D$675,IF($B$4="Vulcan PO",'📋 ORDERS'!$E$4:$E$675,'📋 ORDERS'!$Q$4:$Q$675)))=$K$4),32),0)=0,"",IFERROR(INDEX('📋 ORDERS'!$M$4:$M$675,IFERROR(_xludf.aggregate(15,6,(ROW('📋 ORDERS'!$B$4:$B$675)-3)/(IF($B$4="SKF Order",'📋 ORDERS'!$C$4:$C$675,IF($B$4="TATA Order",'📋 ORDERS'!$D$4:$D$675,IF($B$4="Vulcan PO",'📋 ORDERS'!$E$4:$E$675,'📋 ORDERS'!$Q$4:$Q$675)))=$K$4),32),0)),"")) | I54: =IF(IFERROR(_xludf.aggregate(15,6,(ROW('📋 ORDERS'!$B$4:$B$675)-3)/(IF($B$4="SKF Order",'📋 ORDERS'!$C$4:$C$675,IF($B$4="TATA Order",'📋 ORDERS'!$D$4:$D$675,IF($B$4="Vulcan PO",'📋 ORDERS'!$E$4:$E$675,'📋 ORDERS'!$Q$4:$Q$675)))=$K$4),32),0)=0,"",IFERROR(INDEX('📋 ORDERS'!$R$4:$R$675,IFERROR(_xludf.aggregate(15,6,(ROW('📋 ORDERS'!$B$4:$B$675)-3)/(IF($B$4="SKF Order",'📋 ORDERS'!$C$4:$C$675,IF($B$4="TATA Order",'📋 ORDERS'!$D$4:$D$675,IF($B$4="Vulcan PO",'📋 ORDERS'!$E$4:$E$675,'📋 ORDERS'!$Q$4:$Q$675)))=$K$4),32),0)),"")) | J54: =IF(IFERROR(_xludf.aggregate(15,6,(ROW('📋 ORDERS'!$B$4:$B$675)-3)/(IF($B$4="SKF Order",'📋 ORDERS'!$C$4:$C$675,IF($B$4="TATA Order",'📋 ORDERS'!$D$4:$D$675,IF($B$4="Vulcan PO",'📋 ORDERS'!$E$4:$E$675,'📋 ORDERS'!$Q$4:$Q$675)))=$K$4),32),0)=0,"",IFERROR(INDEX('📋 ORDERS'!$S$4:$S$675,IFERROR(_xludf.aggregate(15,6,(ROW('📋 ORDERS'!$B$4:$B$675)-3)/(IF($B$4="SKF Order",'📋 ORDERS'!$C$4:$C$675,IF($B$4="TATA Order",'📋 ORDERS'!$D$4:$D$675,IF($B$4="Vulcan PO",'📋 ORDERS'!$E$4:$E$675,'📋 ORDERS'!$Q$4:$Q$675)))=$K$4),32),0)),""))
